Workbook

Sheet Assumptions
A1: scoup.ai financial model: Assumptions (all inputs; blue = editable input)
A2: Pre-product, pre-revenue, no customers, synthetic data only. Every figure is a plan input or its arithmetic consequence, not a forecast. $K unless stated. Year 1 = first 12 months after seed close.
A3: Input | B3: Value / Y1 | C3: Y2 / Bull | D3: Y3 / Bear | E3: Y4 / Live | F3: Y5 | G3: Y6 | H3: Y7 | I3: Status | J3: Source / reasoning
A4: Scenario control
A5: Active scenario (1 = Base, 2 = Bull, 3 = Bear) | B5: 1 | I5: CONTROL | J5: Drives every main tab. The Scenarios tab computes all three side by side regardless.
A6: Year index | B6: 1 | C6: 2 | D6: 3 | E6: 4 | F6: 5 | G6: 6 | H6: 7 | I6: STRUCTURAL | J6: Used by formulas that depend on the year number.
A7: Global inputs (same in every scenario)
A8: Compensation inflation per year | B8: 0.04 | I8: ASSUMED | J8: Planning assumption carried from the investor-pack workbook (grade C).
A9: NOK per USD | B9: 9.3817 | I9: SOURCED | J9: Norges Bank, USD/NOK monthly average Sep 2026 = 9.3817, https://data.norges-bank.no/api/data/EXR/M.USD.NOK.SP, accessed 2026-10-17. Replaces 10.5 in the prior workbook.
A10: Norway loading on gross salary (employer tax + pension + other) | B10: 1.22 | I10: ASSUMED | J10: Employer tax zone I 14.1% is SOURCED (Skatteetaten, https://www.skatteetaten.no/satser/arbeidsgiveravgift/, accessed 2026-10-17); the remaining ~8 points (mandatory pension, insurance) are assumed.
A11: US benefits share of total compensation | B11: 0.3 | I11: SOURCED | J11: BLS Employer Costs for Employee Compensation, June 2026: benefits 30.0% of private-industry compensation, https://www.bls.gov/news.release/ecec.nr0.htm, accessed 2026-10-17. Loaded cost = wage / (1 - 0.30).
A12: Norwegian corporate income tax rate | B12: 0.22 | I12: SOURCED | J12: 22% (DLA Piper Global Expansion Tax, Norway, https://intelligence.dlapiper.com/global-expansion-tax/?c=NO, accessed 2026-10-17). Unlimited loss carry-forward assumed; confirm with counsel.
A13: Days sales outstanding | B13: 60 | I13: ASSUMED | J13: Contingency fees are invoiced after the counterparty pays the customer; 60 days assumed. Unmeasured.
A14: Days payable outstanding (non-payroll costs) | B14: 30 | I14: ASSUMED | J14: Standard 30-day vendor terms assumed.
A15: Equipment capex per net new hire ($K) | B15: 3 | I15: ASSUMED | J15: Laptop and peripherals. Software development is expensed, not capitalised.
A16: Depreciation life (years) | B16: 3 | I16: ASSUMED | J16: Straight line.
A17: Interest earned on cash | B17: 0 | I17: ASSUMED | J17: Set to zero for conservatism.
A18: Opening cash at seed close, before seed ($K) | B18: 0 | I18: ASSUMED | J18: UNKNOWN; owner to confirm founder-funded cash and share capital (NOK 30,000 minimum for an AS).
A19: Series A ARR milestone ($K) | B19: 2500 | I19: ASSUMED | J19: Planning target. Reference: median ARR at Series A $2.8M in 2025 (Carta, ARR at Series A, https://carta.com/data/newsletter-arr-at-series-a/, figure confirmed via search result 2026-10-17; direct fetch returned HTTP 403).
... A33: Pessimistic CAC: paid-media cost per small-company customer ($K) | B33: 31 | I33: SOURCED | J33: Metadata.io, 2026 B2B Paid Media Benchmark Report (2025 data, 153 advertisers): small-company customer cost $31k, https://metadata.io/md/benchmark-report-2026.md, accessed 2026-10-17. Media cost only; excludes sales labour. LinkedIn cost per customer $58,572 (same source, reported by digital-marketing, not re-verified by finance).
A34: Revenue per account build, base path ($K per account per year) | B34: Y1 | C34: Y2 | D34: Y3 | E34: Y4 | F34: Y5 | G34: Y6 | H34: Y7
A35: Platform fee | B35: 0 | C35: 6 | D35: 10 | E35: 13 | F35: 15 | G35: 16 | H35: 17 | I35: ASSUMED | J35: Investor-pack workbook (grade C). Hybrid fee starts in year 2. No competitor publishes pricing (market-researcher research/01-competitors.md, 2026-10-17), so there is no market check.
A36: Amount recovered for the customer | B36: 52 | C36: 70 | D36: 85 | E36: 95 | F36: 105 | G36: 110 | H36: 115 | I36: ASSUMED | J36: Year 1 $52K = business-case base for a mid-size importer-shipper (D&D $36K + fuel surcharge $16K), built on FMC and EIA/ATRI figures; grows as modules are added. Not measured on any customer data.
A37: Recovery share (contingency %) | B37: 0.25 | C37: 0.17 | D37: 0.14 | E37: 0.12 | F37: 0.12 | G37: 0.12 | H37: 0.12 | I37: ASSUMED | J37: 25% pilot contingency, falling once the platform fee starts. No freight competitor publishes a contingency rate (market-researcher research/01-competitors.md, 2026-10-17). Only public reference: Refund Retriever (parcel audit) 40-50%, https://www.refundretriever.com/pricing, accessed 2026-10-17.
A38: Segments: shippers and SME importers are the core; carriers are a later, partner-led segment
A39: Shipper share of new shipper + importer accounts | B39: 0.5 | I39: ASSUMED | J39: Owner decision 2026-10-17: shipper- and importer-first. 50/50 split assumed; SME importers are counted (234,023, US Census) but mid-market shippers are not yet.
A40: Shipper amount recovered vs importer path | B40: 0.77 | I40: ASSUMED | J40: A domestic mid-market shipper has no ocean D&D. Business-case year-1 example: fuel-surcharge recovery $16K (business case, EIA-based) + accessorial and detention invoice audit $24K (assumed) = $40K vs $52K for an importer = 0.77.
A41: Carrier: amount recovered per carrier ($K/yr) | B41: 39.475 | C41: 39.475 | D41: 39.475 | E41: 39.475 | F41: 39.475 | G41: 39.475 | H41: 39.475 | I41: ASSUMED | J41: market-researcher research/02 and 05 (2026-10-17): $471.60 fee per power unit x 16.7 units = $7,895 per carrier at a 20% fee, so recovered = $7,895 / 20% = $39.5K. Built on assumed inputs (400 stops per truck, $100 per detained stop, 30% winnable); ATRI 39.3% detention rate sourced.
A42: Carrier: contingency share (no platform fee) | B42: 0.2 | I42: ASSUMED | J42: Fee used in the research carrier model and in gtm.md.
A43: Partner commission on carrier revenue (factoring / ELD channel) | B43: 0.2 | I43: ASSUMED | J43: Carriers come through a channel partner, not direct sales; commission booked in the Sales department.
A44: Scenario inputs (scalars) | B44: Base | C44: Bull | D44: Bear | E44: Live
A45: Annual logo churn | B45: 0.2 | C45: 0.15 | D45: 0.3 | E45: =CHOOSE($B$5,B45,C45,D45) | I45: ASSUMED | J45: Share of start-of-year accounts lost in the year. Benchmarkit median GRR 88% implies ~12% revenue churn for SaaS; a contingency service is easy to switch off, so 20% base.
A46: Revenue per account vs base path | B46: 1 | C46: 1.15 | D46: 0.8 | E46: =CHOOSE($B$5,B46,C46,D46) | I46: ASSUMED | J46: Bull: larger recoveries and early platform-fee adoption. Bear: recoveries 20% lower.
A47: Headcount and spend scale vs base plan | B47: 1 | C47: 1.1 | D47: 0.85 | E47: =CHOOSE($B$5,B47,C47,D47) | I47: ASSUMED | J47: Applied to every role except the founder, and to other operating costs from year 2.
A48: Hold headcount and spend at prior-year level from year (0 = never) | B48: 0 | C48: 0 | D48: 3 | E48: =CHOOSE($B$5,B48,C48,D48) | I48: ASSUMED | J48: Bear cost response: if the tranche-2 milestone is missed, hold at year-2 levels (investor-pack financial plan section 4 describes this but the workbook did not model it).
A49: Number of years the hold lasts | B49: 0 | C49: 0 | D49: 2 | E49: =CHOOSE($B$5,B49,C49,D49) | I49: ASSUMED | J49: Bear: years 3 and 4 held at year-2 levels, then the scaled plan resumes. A permanent hold would leave 2 claims analysts serving 235 accounts, which is not credible.
A50: Variable cost of revenue (% of revenue) | B50: 0.08 | C50: 0.07 | D50: 0.1 | E50: =CHOOSE($B$5,B50,C50,D50) | I50: ASSUMED | J50: New input: LLM inference, OCR and per-container event data. Unmeasured; replaces the gross-margin-% input of the prior workbook.
A51: Scenario inputs (by year): new shipper + importer accounts won, and carrier accounts | B51: Y1 | C51: Y2 | D51: Y3 | E51: Y4 | F51: Y5 | G51: Y6 | H51: Y7
A52: New shipper + importer accounts won - Base | B52: 6 | C52: 30 | D52: 75 | E52: 120 | F52: 165 | G52: 200 | H52: 235 | I52: ASSUMED | J52: Plan input from the investor-pack workbook (grade C). No pipeline exists yet.
A53: New shipper + importer accounts won - Bull | B53: 8 | C53: 40 | D53: 100 | E53: 160 | F53: 215 | G53: 260 | H53: 300 | I53: ASSUMED | J53: Plan input from the investor-pack workbook (grade C). No pipeline exists yet.
A54: New shipper + importer accounts won - Bear | B54: 4 | C54: 16 | D54: 35 | E54: 55 | F54: 75 | G54: 90 | H54: 105 | I54: ASSUMED | J54: Plan input from the investor-pack workbook (grade C). No pipeline exists yet.
A55: New accounts won - Live | B55: =CHOOSE($B$5,B52,B53,B54) | C55: =CHOOSE($B$5,C52,C53,C54) | D55: =CHOOSE($B$5,D52,D53,D54) | E55: =CHOOSE($B$5,E52,E53,E54) | F55: =CHOOSE($B$5,F52,F53,F54) | G55: =CHOOSE($B$5,G52,G53,G54) | H55: =CHOOSE($B$5,H52,H53,H54) | I55: DERIVED
A56: New carrier accounts via partner - Base | B56: 0 | C56: 0 | D56: 15 | E56: 30 | F56: 50 | G56: 70 | H56: 90 | I56: ASSUMED | J56: Small partner-led segment starting later (base: factoring partner from year 3; bull: partner signed in year 2; bear: partner slips to year 5).
A57: New carrier accounts via partner - Bull | B57: 0 | C57: 10 | D57: 30 | E57: 60 | F57: 90 | G57: 120 | H57: 150 | I57: ASSUMED | J57: Small partner-led segment starting later (base: factoring partner from year 3; bull: partner signed in year 2; bear: partner slips to year 5).
A58: New carrier accounts via partner - Bear | B58: 0 | C58: 0 | D58: 0 | E58: 0 | F58: 10 | G58: 20 | H58: 30 | I58: ASSUMED | J58: Small partner-led segment starting later (base: factoring partner from year 3; bull: partner signed in year 2; bear: partner slips to year 5).
A59: New carrier accounts via partner - Live | B59: =CHOOSE($B$5,B56,B57,B58) | C59: =CHOOSE($B$5,C56,C57,C58) | D59: =CHOOSE($B$5,D56,D57,D58) | E59: =CHOOSE($B$5,E56,E57,E58) | F59: =CHOOSE($B$5,F56,F57,F58) | G59: =CHOOSE($B$5,G56,G57,G58) | H59: =CHOOSE($B$5,H56,H57,H58) | I59: DERIVED
A60: Headcount plan (people at year end, base scale) and pay | B60: Y1 | C60: Y2 | D60: Y3 | E60: Y4 | F60: Y5 | G60: Y6 | H60: Y7
A61: Founder / CEO - headcount plan | B61: 1 | C61: 1 | D61: 1 | E61: 1 | F61: 1 | G61: 1 | H61: 1 | I61: ASSUMED | J61: Department: G&A. Plan from the investor-pack workbook (grade C).
A62: Founder / CEO - annual pay (NOK) | B62: 1200000 | I62: ASSUMED | J62: NOK pay held below market until Series A; equals the $140K loaded in the prior workbook at 10.5 NOK/USD.
A63: Founder / CEO - year-1 start quarter (1-4) | B63: 1 | I63: ASSUMED | J63: Hiring quarter for year-1 hires; drives the year-1 quarterly budget.
A64: Founder / CEO - loaded cost ($K/yr, year-1 prices) | B64: =B62*$B$10/$B$9/1000 | I64: DERIVED | J64: NO: pay x loading / FX. US: wage / (1 - benefits share).
A65: Software engineers - headcount plan | B65: 2 | C65: 3 | D65: 5 | E65: 8 | F65: 10 | G65: 12 | H65: 13 | I65: ASSUMED | J65: Department: Engineering. Plan from the investor-pack workbook (grade C).
A66: Software engineers - annual pay (NOK) | B66: 969240 | I66: SOURCED | J66: SSB average monthly earnings, information and communication, Nov 2025: NOK 80,770 x 12, https://www.ssb.no/arbeid-og-lonn/lonn-og-arbeidskraftkostnader/statistikk/lonn, accessed 2026-10-17.
A67: Software engineers - year-1 start quarter (1-4) | B67: 2 | I67: ASSUMED | J67: Hiring quarter for year-1 hires; drives the year-1 quarterly budget.
A68: Software engineers - loaded cost ($K/yr, year-1 prices) | B68: =B66*$B$10/$B$9/1000 | I68: DERIVED | J68: NO: pay x loading / FX. US: wage / (1 - benefits share).
A69: ML / data engineers - headcount plan | B69: 1 | C69: 1 | D69: 2 | E69: 3 | F69: 3 | G69: 4 | H69: 4 | I69: ASSUMED | J69: Department: Engineering. Plan from the investor-pack workbook (grade C).
A70: ML / data engineers - annual pay (NOK) | B70: 1060000 | I70: ASSUMED | J70: SSB sector average plus ~9% for specialist skills (ratio kept from the prior workbook).
A71: ML / data engineers - year-1 start quarter (1-4) | B71: 3 | I71: ASSUMED | J71: Hiring quarter for year-1 hires; drives the year-1 quarterly budget.
A72: ML / data engineers - loaded cost ($K/yr, year-1 prices) | B72: =B70*$B$10/$B$9/1000 | I72: DERIVED | J72: NO: pay x loading / FX. US: wage / (1 - benefits share).
A73: Security engineer - headcount plan | B73: 1 | C73: 1 | D73: 1 | E73: 2 | F73: 2 | G73: 3 | H73: 3 | I73: ASSUMED | J73: Department: Security. Plan from the investor-pack workbook (grade C).
A74: Security engineer - annual pay (NOK) | B74: 1060000 | I74: ASSUMED | J74: As ML / data engineers.
A75: Security engineer - year-1 start quarter (1-4) | B75: 2 | I75: ASSUMED | J75: Hiring quarter for year-1 hires; drives the year-1 quarterly budget.
A76: Security engineer - loaded cost ($K/yr, year-1 prices) | B76: =B74*$B$10/$B$9/1000 | I76: DERIVED | J76: NO: pay x loading / FX. US: wage / (1 - benefits share).
A77: Account executives (US) - headcount plan | B77: 0 | C77: 1 | D77: 3 | E77: 5 | F77: 7 | G77: 8 | H77: 9 | I77: ASSUMED | J77: Department: Sales. Plan from the investor-pack workbook (grade C).
A78: Account executives (US) - annual pay (USD) | B78: 161000 | I78: ASSUMED | J78: On-target earnings, set so the loaded cost equals the $230K in the prior workbook. Not re-verified.
A79: Account executives (US) - year-1 start quarter (1-4) | B79: 1 | I79: ASSUMED | J79: Hiring quarter for year-1 hires; drives the year-1 quarterly budget.
A80: Account executives (US) - loaded cost ($K/yr, year-1 prices) | B80: =B78/(1-$B$11)/1000 | I80: DERIVED | J80: NO: pay x loading / FX. US: wage / (1 - benefits share).
A81: Sales engineer (US) - headcount plan | B81: 0 | C81: 1 | D81: 1 | E81: 2 | F81: 2 | G81: 3 | H81: 3 | I81: ASSUMED | J81: Department: Sales. Plan from the investor-pack workbook (grade C).
A82: Sales engineer (US) - annual pay (USD) | B82: 124900 | I82: SOURCED | J82: BLS Occupational Outlook Handbook, sales engineers median $124,900 (May 2025), https://www.bls.gov/ooh/sales/sales-engineers.htm, accessed 2026-10-17.
A83: Sales engineer (US) - year-1 start quarter (1-4) | B83: 1 | I83: ASSUMED | J83: Hiring quarter for year-1 hires; drives the year-1 quarterly budget.
A84: Sales engineer (US) - loaded cost ($K/yr, year-1 prices) | B84: =B82/(1-$B$11)/1000 | I84: DERIVED | J84: NO: pay x loading / FX. US: wage / (1 - benefits share).
A85: Claims analysts / customer success (US) - headcount plan | B85: 1 | C85: 2 | D85: 4 | E85: 7 | F85: 10 | G85: 13 | H85: 16 | I85: ASSUMED | J85: Department: Claims operations (COGS). Plan from the investor-pack workbook (grade C).
A86: Claims analysts / customer success (US) - annual pay (USD) | B86: 70000 | I86: ASSUMED | J86: Analyst base pay ~$70K (prior workbook, grade C).
A87: Claims analysts / customer success (US) - year-1 start quarter (1-4) | B87: 3 | I87: ASSUMED | J87: Hiring quarter for year-1 hires; drives the year-1 quarterly budget.
A88: Claims analysts / customer success (US) - loaded cost ($K/yr, year-1 prices) | B88: =B86/(1-$B$11)/1000 | I88: DERIVED | J88: NO: pay x loading / FX. US: wage / (1 - benefits share).
A89: Marketing (US) - headcount plan | B89: 0 | C89: 0 | D89: 1 | E89: 1 | F89: 2 | G89: 2 | H89: 2 | I89: ASSUMED | J89: Department: Marketing. Plan from the investor-pack workbook (grade C).
A90: Marketing (US) - annual pay (USD) | B90: 105000 | I90: ASSUMED | J90: Estimate; loaded $150K as in the prior workbook.
A91: Marketing (US) - year-1 start quarter (1-4) | B91: 1 | I91: ASSUMED | J91: Hiring quarter for year-1 hires; drives the year-1 quarterly budget.
A92: Marketing (US) - loaded cost ($K/yr, year-1 prices) | B92: =B90/(1-$B$11)/1000 | I92: DERIVED | J92: NO: pay x loading / FX. US: wage / (1 - benefits share).
A93: Finance, legal operations, people - headcount plan | B93: 0 | C93: 1 | D93: 1 | E93: 2 | F93: 2 | G93: 3 | H93: 3 | I93: ASSUMED | J93: Department: G&A. Plan from the investor-pack workbook (grade C).
A94: Finance, legal operations, people - annual pay (NOK) | B94: 1120000 | I94: ASSUMED | J94: SSB sector average plus ~15%; loaded $130K at 10.5 NOK/USD in the prior workbook.
A95: Finance, legal operations, people - year-1 start quarter (1-4) | B95: 1 | I95: ASSUMED | J95: Hiring quarter for year-1 hires; drives the year-1 quarterly budget.
A96: Finance, legal operations, people - loaded cost ($K/yr, year-1 prices) | B96: =B94*$B$10/$B$9/1000 | I96: DERIVED | J96: NO: pay x loading / FX. US: wage / (1 - benefits share).
A97: Other operating costs, base plan ($K per year) | B97: Y1 | C97: Y2 | D97: Y3 | E97: Y4 | F97: Y5 | G97: Y6 | H97: Y7
A98: Cloud hosting, data feeds and tooling [COGS] | B98: 45 | C98: 80 | D98: 140 | E98: 220 | F98: 300 | G98: 370 | H98: 430 | I98: ASSUMED | J98: Terraform footprint plus container-event data fees (prior workbook, grade C).
A99: Security programme (SOC 2, pen tests, tooling, insurance) [Security] | B99: 120 | C99: 150 | D99: 170 | E99: 190 | F99: 210 | G99: 230 | H99: 250 | I99: ASSUMED | J99: SOC 2 Type II first year $50-110K and pen tests $15-35K each (vendor blogs, grade C, not re-verified).
A100: Legal and regulatory [G&A] | B100: 150 | C100: 110 | D100: 120 | E100: 140 | F100: 150 | G100: 160 | H100: 170 | I100: ASSUMED | J100: US entity, customer contracts, FMC and data-protection counsel (grade C).
A101: Marketing programmes and events [Marketing] | B101: 30 | C101: 90 | D101: 200 | E101: 320 | F101: 420 | G101: 480 | H101: 520 | I101: ASSUMED | J101: Trade shows (TIA, CSCMP, TPM), content, list data (grade C). Channel CAC from digital-marketing pending.
A102: Travel and customer visits [Sales] | B102: 60 | C102: 100 | D102: 150 | E102: 200 | F102: 240 | G102: 270 | H102: 300 | I102: ASSUMED | J102: US customer and partner visits (grade C).
A103: Office, software, admin, accounting [G&A] | B103: 50 | C103: 80 | D103: 110 | E103: 150 | F103: 180 | G103: 210 | H103: 240 | I103: ASSUMED | J103: Estimate (grade C).

Sheet Revenue
A1: Revenue build (active scenario)
A2: Accounts x revenue per account. Revenue per account = (platform fee + amount recovered x recovery share) x scenario multiplier.
A3: $K unless stated | B3: ="Y"&Assumptions!$B$6 | C3: ="Y"&Assumptions!$C$6 | D3: ="Y"&Assumptions!$D$6 | E3: ="Y"&Assumptions!$E$6 | F3: ="Y"&Assumptions!$F$6 | G3: ="Y"&Assumptions!$G$6 | H3: ="Y"&Assumptions!$H$6
A4: Accounts and revenue by segment ($K)
A5: Shippers (mid-market): new accounts | B5: =ROUND(Assumptions!$B$55*Assumptions!$B$39,0) | C5: =ROUND(Assumptions!$C$55*Assumptions!$B$39,0) | D5: =ROUND(Assumptions!$D$55*Assumptions!$B$39,0) | E5: =ROUND(Assumptions!$E$55*Assumptions!$B$39,0) | F5: =ROUND(Assumptions!$F$55*Assumptions!$B$39,0) | G5: =ROUND(Assumptions!$G$55*Assumptions!$B$39,0) | H5: =ROUND(Assumptions!$H$55*Assumptions!$B$39,0)
A6: Shippers (mid-market): accounts lost = ROUND(prior year-end x churn) | B6: =0 | C6: =ROUND(B7*Assumptions!$E$45,0) | D6: =ROUND(C7*Assumptions!$E$45,0) | E6: =ROUND(D7*Assumptions!$E$45,0) | F6: =ROUND(E7*Assumptions!$E$45,0) | G6: =ROUND(F7*Assumptions!$E$45,0) | H6: =ROUND(G7*Assumptions!$E$45,0)
A7: Shippers (mid-market): accounts at year end | B7: =B5 | C7: =B7-C6+C5 | D7: =C7-D6+D5 | E7: =D7-E6+E5 | F7: =E7-F6+F5 | G7: =F7-G6+G5 | H7: =G7-H6+H5
A8: Shippers (mid-market): average accounts | B8: =B7/2 | C8: =(B7+C7)/2 | D8: =(C7+D7)/2 | E8: =(D7+E7)/2 | F8: =(E7+F7)/2 | G8: =(F7+G7)/2 | H8: =(G7+H7)/2
A9: Shippers (mid-market): revenue per account ($K) | B9: =(Assumptions!$B$35+Assumptions!$B$36*Assumptions!$B$40*Assumptions!$B$37)*Assumptions!$E$46 | C9: =(Assumptions!$C$35+Assumptions!$C$36*Assumptions!$B$40*Assumptions!$C$37)*Assumptions!$E$46 | D9: =(Assumptions!$D$35+Assumptions!$D$36*Assumptions!$B$40*Assumptions!$D$37)*Assumptions!$E$46 | E9: =(Assumptions!$E$35+Assumptions!$E$36*Assumptions!$B$40*Assumptions!$E$37)*Assumptions!$E$46 | F9: =(Assumptions!$F$35+Assumptions!$F$36*Assumptions!$B$40*Assumptions!$F$37)*Assumptions!$E$46 | G9: =(Assumptions!$G$35+Assumptions!$G$36*Assumptions!$B$40*Assumptions!$G$37)*Assumptions!$E$46 | H9: =(Assumptions!$H$35+Assumptions!$H$36*Assumptions!$B$40*Assumptions!$H$37)*Assumptions!$E$46
A10: Shippers (mid-market): revenue | B10: =B8*B9 | C10: =C8*C9 | D10: =D8*D9 | E10: =E8*E9 | F10: =F8*F9 | G10: =G8*G9 | H10: =H8*H9
A11: Shippers (mid-market): ARR at year end | B11: =B7*B9 | C11: =C7*C9 | D11: =D7*D9 | E11: =E7*E9 | F11: =F7*F9 | G11: =G7*G9 | H11: =H7*H9
A12: SME importers: new accounts | B12: =Assumptions!$B$55-ROUND(Assumptions!$B$55*Assumptions!$B$39,0) | C12: =Assumptions!$C$55-ROUND(Assumptions!$C$55*Assumptions!$B$39,0) | D12: =Assumptions!$D$55-ROUND(Assumptions!$D$55*Assumptions!$B$39,0) | E12: =Assumptions!$E$55-ROUND(Assumptions!$E$55*Assumptions!$B$39,0) | F12: =Assumptions!$F$55-ROUND(Assumptions!$F$55*Assumptions!$B$39,0) | G12: =Assumptions!$G$55-ROUND(Assumptions!$G$55*Assumptions!$B$39,0) | H12: =Assumptions!$H$55-ROUND(Assumptions!$H$55*Assumptions!$B$39,0)
A13: SME importers: accounts lost = ROUND(prior year-end x churn) | B13: =0 | C13: =ROUND(B14*Assumptions!$E$45,0) | D13: =ROUND(C14*Assumptions!$E$45,0) | E13: =ROUND(D14*Assumptions!$E$45,0) | F13: =ROUND(E14*Assumptions!$E$45,0) | G13: =ROUND(F14*Assumptions!$E$45,0) | H13: =ROUND(G14*Assumptions!$E$45,0)
A14: SME importers: accounts at year end | B14: =B12 | C14: =B14-C13+C12 | D14: =C14-D13+D12 | E14: =D14-E13+E12 | F14: =E14-F13+F12 | G14: =F14-G13+G12 | H14: =G14-H13+H12
A15: SME importers: average accounts | B15: =B14/2 | C15: =(B14+C14)/2 | D15: =(C14+D14)/2 | E15: =(D14+E14)/2 | F15: =(E14+F14)/2 | G15: =(F14+G14)/2 | H15: =(G14+H14)/2
A16: SME importers: revenue per account ($K) | B16: =(Assumptions!$B$35+Assumptions!$B$36*Assumptions!$B$37)*Assumptions!$E$46 | C16: =(Assumptions!$C$35+Assumptions!$C$36*Assumptions!$C$37)*Assumptions!$E$46 | D16: =(Assumptions!$D$35+Assumptions!$D$36*Assumptions!$D$37)*Assumptions!$E$46 | E16: =(Assumptions!$E$35+Assumptions!$E$36*Assumptions!$E$37)*Assumptions!$E$46 | F16: =(Assumptions!$F$35+Assumptions!$F$36*Assumptions!$F$37)*Assumptions!$E$46 | G16: =(Assumptions!$G$35+Assumptions!$G$36*Assumptions!$G$37)*Assumptions!$E$46 | H16: =(Assumptions!$H$35+Assumptions!$H$36*Assumptions!$H$37)*Assumptions!$E$46
A17: SME importers: revenue | B17: =B15*B16 | C17: =C15*C16 | D17: =D15*D16 | E17: =E15*E16 | F17: =F15*F16 | G17: =G15*G16 | H17: =H15*H16
A18: SME importers: ARR at year end | B18: =B14*B16 | C18: =C14*C16 | D18: =D14*D16 | E18: =E14*E16 | F18: =F14*F16 | G18: =G14*G16 | H18: =H14*H16
A19: Carriers (partner-led): new accounts | B19: =Assumptions!$B$59 | C19: =Assumptions!$C$59 | D19: =Assumptions!$D$59 | E19: =Assumptions!$E$59 | F19: =Assumptions!$F$59 | G19: =Assumptions!$G$59 | H19: =Assumptions!$H$59
A20: Carriers (partner-led): accounts lost = ROUND(prior year-end x churn) | B20: =0 | C20: =ROUND(B21*Assumptions!$E$45,0) | D20: =ROUND(C21*Assumptions!$E$45,0) | E20: =ROUND(D21*Assumptions!$E$45,0) | F20: =ROUND(E21*Assumptions!$E$45,0) | G20: =ROUND(F21*Assumptions!$E$45,0) | H20: =ROUND(G21*Assumptions!$E$45,0)
A21: Carriers (partner-led): accounts at year end | B21: =B19 | C21: =B21-C20+C19 | D21: =C21-D20+D19 | E21: =D21-E20+E19 | F21: =E21-F20+F19 | G21: =F21-G20+G19 | H21: =G21-H20+H19
A22: Carriers (partner-led): average accounts | B22: =B21/2 | C22: =(B21+C21)/2 | D22: =(C21+D21)/2 | E22: =(D21+E21)/2 | F22: =(E21+F21)/2 | G22: =(F21+G21)/2 | H22: =(G21+H21)/2
A23: Carriers (partner-led): revenue per account ($K) | B23: =Assumptions!$B$41*Assumptions!$B$42*Assumptions!$E$46 | C23: =Assumptions!$C$41*Assumptions!$B$42*Assumptions!$E$46 | D23: =Assumptions!$D$41*Assumptions!$B$42*Assumptions!$E$46 | E23: =Assumptions!$E$41*Assumptions!$B$42*Assumptions!$E$46 | F23: =Assumptions!$F$41*Assumptions!$B$42*Assumptions!$E$46 | G23: =Assumptions!$G$41*Assumptions!$B$42*Assumptions!$E$46 | H23: =Assumptions!$H$41*Assumptions!$B$42*Assumptions!$E$46
A24: Carriers (partner-led): revenue | B24: =B22*B23 | C24: =C22*C23 | D24: =D22*D23 | E24: =E22*E23 | F24: =F22*F23 | G24: =G22*G23 | H24: =H22*H23
A25: Carriers (partner-led): ARR at year end | B25: =B21*B23 | C25: =C21*C23 | D25: =D21*D23 | E25: =E21*E23 | F25: =F21*F23 | G25: =G21*G23 | H25: =H21*H23
A26: All segments: new accounts won | B26: =B5+B12+B19 | C26: =C5+C12+C19 | D26: =D5+D12+D19 | E26: =E5+E12+E19 | F26: =F5+F12+F19 | G26: =G5+G12+G19 | H26: =H5+H12+H19
A27: All segments: accounts lost | B27: =B6+B13+B20 | C27: =C6+C13+C20 | D27: =D6+D13+D20 | E27: =E6+E13+E20 | F27: =F6+F13+F20 | G27: =G6+G13+G20 | H27: =H6+H13+H20
A28: All segments: paying accounts at year end | B28: =B7+B14+B21 | C28: =C7+C14+C21 | D28: =D7+D14+D21 | E28: =E7+E14+E21 | F28: =F7+F14+F21 | G28: =G7+G14+G21 | H28: =H7+H14+H21
A29: All segments: average paying accounts | B29: =B8+B15+B22 | C29: =C8+C15+C22 | D29: =D8+D15+D22 | E29: =E8+E15+E22 | F29: =F8+F15+F22 | G29: =G8+G15+G22 | H29: =H8+H15+H22
A30: Total revenue | B30: =B10+B17+B24 | C30: =C10+C17+C24 | D30: =D10+D17+D24 | E30: =E10+E17+E24 | F30: =F10+F17+F24 | G30: =G10+G17+G24 | H30: =H10+H17+H24
A31: ARR at year end | B31: =B11+B18+B25 | C31: =C11+C18+C25 | D31: =D11+D18+D25 | E31: =E11+E18+E25 | F31: =F11+F18+F25 | G31: =G11+G18+G25 | H31: =H11+H18+H25
A32: Blended revenue per account = ARR / accounts ($K) | B32: =IF(B28=0,0,B31/B28) | C32: =IF(C28=0,0,C31/C28) | D32: =IF(D28=0,0,D31/D28) | E32: =IF(E28=0,0,E31/E28) | F32: =IF(F28=0,0,F31/F28) | G32: =IF(G28=0,0,G31/G28) | H32: =IF(H28=0,0,H31/H28)
A33: Platform-fee revenue (shippers and importers) | B33: =(B8+B15)*Assumptions!$B$35*Assumptions!$E$46 | C33: =(C8+C15)*Assumptions!$C$35*Assumptions!$E$46 | D33: =(D8+D15)*Assumptions!$D$35*Assumptions!$E$46 | E33: =(E8+E15)*Assumptions!$E$35*Assumptions!$E$46 | F33: =(F8+F15)*Assumptions!$F$35*Assumptions!$E$46 | G33: =(G8+G15)*Assumptions!$G$35*Assumptions!$E$46 | H33: =(H8+H15)*Assumptions!$H$35*Assumptions!$E$46
A34: Recovery-share revenue | B34: =B30-B33 | C34: =C30-C33 | D34: =D30-D33 | E34: =E30-E33 | F34: =F30-F33 | G34: =G30-G33 | H34: =H30-H33
A35: Total recovered for customers | B35: =(B15*Assumptions!$B$36+B8*Assumptions!$B$36*Assumptions!$B$40+B22*Assumptions!$B$41)*Assumptions!$E$46 | C35: =(C15*Assumptions!$C$36+C8*Assumptions!$C$36*Assumptions!$B$40+C22*Assumptions!$C$41)*Assumptions!$E$46 | D35: =(D15*Assumptions!$D$36+D8*Assumptions!$D$36*Assumptions!$B$40+D22*Assumptions!$D$41)*Assumptions!$E$46 | E35: =(E15*Assumptions!$E$36+E8*Assumptions!$E$36*Assumptions!$B$40+E22*Assumptions!$E$41)*Assumptions!$E$46 | F35: =(F15*Assumptions!$F$36+F8*Assumptions!$F$36*Assumptions!$B$40+F22*Assumptions!$F$41)*Assumptions!$E$46 | G35: =(G15*Assumptions!$G$36+G8*Assumptions!$G$36*Assumptions!$B$40+G22*Assumptions!$G$41)*Assumptions!$E$46 | H35: =(H15*Assumptions!$H$36+H8*Assumptions!$H$36*Assumptions!$B$40+H22*Assumptions!$H$41)*Assumptions!$E$46
A36: Net revenue retention = sum over segments of (start accounts - lost) x revenue per account / start ARR | B36: ="" | C36: =IF(B31=0,"",((B7-C6)*C9+(B14-C13)*C16+(B21-C20)*C23)/B31) | D36: =IF(C31=0,"",((C7-D6)*D9+(C14-D13)*D16+(C21-D20)*D23)/C31) | E36: =IF(D31=0,"",((D7-E6)*E9+(D14-E13)*E16+(D21-E20)*E23)/D31) | F36: =IF(E31=0,"",((E7-F6)*F9+(E14-F13)*F16+(E21-F20)*F23)/E31) | G36: =IF(F31=0,"",((F7-G6)*G9+(F14-G13)*G16+(F21-G20)*G23)/F31) | H36: =IF(G31=0,"",((G7-H6)*H9+(G14-H13)*H16+(G21-H20)*H23)/G31)
A37: Revenue growth | B37: ="" | C37: =IF(B30=0,"",C30/B30-1) | D37: =IF(C30=0,"",D30/C30-1) | E37: =IF(D30=0,"",E30/D30-1) | F37: =IF(E30=0,"",F30/E30-1) | G37: =IF(F30=0,"",G30/F30-1) | H37: =IF(G30=0,"",H30/G30-1)
A38: Month ARR crosses the Series A milestone (linear within year) | B38: =IF(B31>=Assumptions!$B$19,12*Assumptions!$B$19/B31,"") | C38: =IF(AND(C31>=Assumptions!$B$19,B31<Assumptions!$B$19),12*(Assumptions!$C$6-1)+12*(Assumptions!$B$19-B31)/(C31-B31),"") | D38: =IF(AND(D31>=Assumptions!$B$19,C31<Assumptions!$B$19),12*(Assumptions!$D$6-1)+12*(Assumptions!$B$19-C31)/(D31-C31),"") | E38: =IF(AND(E31>=Assumptions!$B$19,D31<Assumptions!$B$19),12*(Assumptions!$E$6-1)+12*(Assumptions!$B$19-D31)/(E31-D31),"") | F38: =IF(AND(F31>=Assumptions!$B$19,E31<Assumptions!$B$19),12*(Assumptions!$F$6-1)+12*(Assumptions!$B$19-E31)/(F31-E31),"") | G38: =IF(AND(G31>=Assumptions!$B$19,F31<Assumptions!$B$19),12*(Assumptions!$G$6-1)+12*(Assumptions!$B$19-F31)/(G31-F31),"") | H38: =IF(AND(H31>=Assumptions!$B$19,G31<Assumptions!$B$19),12*(Assumptions!$H$6-1)+12*(Assumptions!$B$19-G31)/(H31-G31),"")
A39: Series A milestone month | B39: =IF(COUNT(B38:H38)=0,"not reached",ROUNDUP(SUM(B38:H38),0))
A40: Year-7 shipper + importer accounts as share of SAM accounts | B40: =IFERROR((H7+H14)/Assumptions!$B$31,"")
A41: Shipper + importer revenue as share of SAM revenue pool | B41: =IFERROR((B10+B17)/Assumptions!$B$32,"") | C41: =IFERROR((C10+C17)/Assumptions!$B$32,"") | D41: =IFERROR((D10+D17)/Assumptions!$B$32,"") | E41: =IFERROR((E10+E17)/Assumptions!$B$32,"") | F41: =IFERROR((F10+F17)/Assumptions!$B$32,"") | G41: =IFERROR((G10+G17)/Assumptions!$B$32,"") | H41: =IFERROR((H10+H17)/Assumptions!$B$32,"")

Sheet Headcount
A1: Headcount and people cost (active scenario)
A2: Headcount = ROUND(plan x scale), founder unscaled, held at prior year from the freeze year. Year-1 FTE-years use the hiring quarter; later years average start and end headcount. Cost = FTE-years x loaded cost x (1 + inflation)^(year - 1).
A3: $K unless stated | B3: ="Y"&Assumptions!$B$6 | C3: ="Y"&Assumptions!$C$6 | D3: ="Y"&Assumptions!$D$6 | E3: ="Y"&Assumptions!$E$6 | F3: ="Y"&Assumptions!$F$6 | G3: ="Y"&Assumptions!$G$6 | H3: ="Y"&Assumptions!$H$6
A4: People at year end
A5: Founder / CEO [G&A] | B5: =Assumptions!$B$61 | C5: =IF(AND(Assumptions!$E$48>0,Assumptions!$C$6>=Assumptions!$E$48,Assumptions!$C$6<Assumptions!$E$48+Assumptions!$E$49),B5,Assumptions!$C$61) | D5: =IF(AND(Assumptions!$E$48>0,Assumptions!$D$6>=Assumptions!$E$48,Assumptions!$D$6<Assumptions!$E$48+Assumptions!$E$49),C5,Assumptions!$D$61) | E5: =IF(AND(Assumptions!$E$48>0,Assumptions!$E$6>=Assumptions!$E$48,Assumptions!$E$6<Assumptions!$E$48+Assumptions!$E$49),D5,Assumptions!$E$61) | F5: =IF(AND(Assumptions!$E$48>0,Assumptions!$F$6>=Assumptions!$E$48,Assumptions!$F$6<Assumptions!$E$48+Assumptions!$E$49),E5,Assumptions!$F$61) | G5: =IF(AND(Assumptions!$E$48>0,Assumptions!$G$6>=Assumptions!$E$48,Assumptions!$G$6<Assumptions!$E$48+Assumptions!$E$49),F5,Assumptions!$G$61) | H5: =IF(AND(Assumptions!$E$48>0,Assumptions!$H$6>=Assumptions!$E$48,Assumptions!$H$6<Assumptions!$E$48+Assumptions!$E$49),G5,Assumptions!$H$61)
A6: Software engineers [Engineering] | B6: =ROUND(Assumptions!$B$65*Assumptions!$E$47,0) | C6: =IF(AND(Assumptions!$E$48>0,Assumptions!$C$6>=Assumptions!$E$48,Assumptions!$C$6<Assumptions!$E$48+Assumptions!$E$49),B6,ROUND(Assumptions!$C$65*Assumptions!$E$47,0)) | D6: =IF(AND(Assumptions!$E$48>0,Assumptions!$D$6>=Assumptions!$E$48,Assumptions!$D$6<Assumptions!$E$48+Assumptions!$E$49),C6,ROUND(Assumptions!$D$65*Assumptions!$E$47,0)) | E6: =IF(AND(Assumptions!$E$48>0,Assumptions!$E$6>=Assumptions!$E$48,Assumptions!$E$6<Assumptions!$E$48+Assumptions!$E$49),D6,ROUND(Assumptions!$E$65*Assumptions!$E$47,0)) | F6: =IF(AND(Assumptions!$E$48>0,Assumptions!$F$6>=Assumptions!$E$48,Assumptions!$F$6<Assumptions!$E$48+Assumptions!$E$49),E6,ROUND(Assumptions!$F$65*Assumptions!$E$47,0)) | G6: =IF(AND(Assumptions!$E$48>0,Assumptions!$G$6>=Assumptions!$E$48,Assumptions!$G$6<Assumptions!$E$48+Assumptions!$E$49),F6,ROUND(Assumptions!$G$65*Assumptions!$E$47,0)) | H6: =IF(AND(Assumptions!$E$48>0,Assumptions!$H$6>=Assumptions!$E$48,Assumptions!$H$6<Assumptions!$E$48+Assumptions!$E$49),G6,ROUND(Assumptions!$H$65*Assumptions!$E$47,0))
A7: ML / data engineers [Engineering] | B7: =ROUND(Assumptions!$B$69*Assumptions!$E$47,0) | C7: =IF(AND(Assumptions!$E$48>0,Assumptions!$C$6>=Assumptions!$E$48,Assumptions!$C$6<Assumptions!$E$48+Assumptions!$E$49),B7,ROUND(Assumptions!$C$69*Assumptions!$E$47,0)) | D7: =IF(AND(Assumptions!$E$48>0,Assumptions!$D$6>=Assumptions!$E$48,Assumptions!$D$6<Assumptions!$E$48+Assumptions!$E$49),C7,ROUND(Assumptions!$D$69*Assumptions!$E$47,0)) | E7: =IF(AND(Assumptions!$E$48>0,Assumptions!$E$6>=Assumptions!$E$48,Assumptions!$E$6<Assumptions!$E$48+Assumptions!$E$49),D7,ROUND(Assumptions!$E$69*Assumptions!$E$47,0)) | F7: =IF(AND(Assumptions!$E$48>0,Assumptions!$F$6>=Assumptions!$E$48,Assumptions!$F$6<Assumptions!$E$48+Assumptions!$E$49),E7,ROUND(Assumptions!$F$69*Assumptions!$E$47,0)) | G7: =IF(AND(Assumptions!$E$48>0,Assumptions!$G$6>=Assumptions!$E$48,Assumptions!$G$6<Assumptions!$E$48+Assumptions!$E$49),F7,ROUND(Assumptions!$G$69*Assumptions!$E$47,0)) | H7: =IF(AND(Assumptions!$E$48>0,Assumptions!$H$6>=Assumptions!$E$48,Assumptions!$H$6<Assumptions!$E$48+Assumptions!$E$49),G7,ROUND(Assumptions!$H$69*Assumptions!$E$47,0))
A8: Security engineer [Security] | B8: =ROUND(Assumptions!$B$73*Assumptions!$E$47,0) | C8: =IF(AND(Assumptions!$E$48>0,Assumptions!$C$6>=Assumptions!$E$48,Assumptions!$C$6<Assumptions!$E$48+Assumptions!$E$49),B8,ROUND(Assumptions!$C$73*Assumptions!$E$47,0)) | D8: =IF(AND(Assumptions!$E$48>0,Assumptions!$D$6>=Assumptions!$E$48,Assumptions!$D$6<Assumptions!$E$48+Assumptions!$E$49),C8,ROUND(Assumptions!$D$73*Assumptions!$E$47,0)) | E8: =IF(AND(Assumptions!$E$48>0,Assumptions!$E$6>=Assumptions!$E$48,Assumptions!$E$6<Assumptions!$E$48+Assumptions!$E$49),D8,ROUND(Assumptions!$E$73*Assumptions!$E$47,0)) | F8: =IF(AND(Assumptions!$E$48>0,Assumptions!$F$6>=Assumptions!$E$48,Assumptions!$F$6<Assumptions!$E$48+Assumptions!$E$49),E8,ROUND(Assumptions!$F$73*Assumptions!$E$47,0)) | G8: =IF(AND(Assumptions!$E$48>0,Assumptions!$G$6>=Assumptions!$E$48,Assumptions!$G$6<Assumptions!$E$48+Assumptions!$E$49),F8,ROUND(Assumptions!$G$73*Assumptions!$E$47,0)) | H8: =IF(AND(Assumptions!$E$48>0,Assumptions!$H$6>=Assumptions!$E$48,Assumptions!$H$6<Assumptions!$E$48+Assumptions!$E$49),G8,ROUND(Assumptions!$H$73*Assumptions!$E$47,0))
A9: Account executives (US) [Sales] | B9: =ROUND(Assumptions!$B$77*Assumptions!$E$47,0) | C9: =IF(AND(Assumptions!$E$48>0,Assumptions!$C$6>=Assumptions!$E$48,Assumptions!$C$6<Assumptions!$E$48+Assumptions!$E$49),B9,ROUND(Assumptions!$C$77*Assumptions!$E$47,0)) | D9: =IF(AND(Assumptions!$E$48>0,Assumptions!$D$6>=Assumptions!$E$48,Assumptions!$D$6<Assumptions!$E$48+Assumptions!$E$49),C9,ROUND(Assumptions!$D$77*Assumptions!$E$47,0)) | E9: =IF(AND(Assumptions!$E$48>0,Assumptions!$E$6>=Assumptions!$E$48,Assumptions!$E$6<Assumptions!$E$48+Assumptions!$E$49),D9,ROUND(Assumptions!$E$77*Assumptions!$E$47,0)) | F9: =IF(AND(Assumptions!$E$48>0,Assumptions!$F$6>=Assumptions!$E$48,Assumptions!$F$6<Assumptions!$E$48+Assumptions!$E$49),E9,ROUND(Assumptions!$F$77*Assumptions!$E$47,0)) | G9: =IF(AND(Assumptions!$E$48>0,Assumptions!$G$6>=Assumptions!$E$48,Assumptions!$G$6<Assumptions!$E$48+Assumptions!$E$49),F9,ROUND(Assumptions!$G$77*Assumptions!$E$47,0)) | H9: =IF(AND(Assumptions!$E$48>0,Assumptions!$H$6>=Assumptions!$E$48,Assumptions!$H$6<Assumptions!$E$48+Assumptions!$E$49),G9,ROUND(Assumptions!$H$77*Assumptions!$E$47,0))
A10: Sales engineer (US) [Sales] | B10: =ROUND(Assumptions!$B$81*Assumptions!$E$47,0) | C10: =IF(AND(Assumptions!$E$48>0,Assumptions!$C$6>=Assumptions!$E$48,Assumptions!$C$6<Assumptions!$E$48+Assumptions!$E$49),B10,ROUND(Assumptions!$C$81*Assumptions!$E$47,0)) | D10: =IF(AND(Assumptions!$E$48>0,Assumptions!$D$6>=Assumptions!$E$48,Assumptions!$D$6<Assumptions!$E$48+Assumptions!$E$49),C10,ROUND(Assumptions!$D$81*Assumptions!$E$47,0)) | E10: =IF(AND(Assumptions!$E$48>0,Assumptions!$E$6>=Assumptions!$E$48,Assumptions!$E$6<Assumptions!$E$48+Assumptions!$E$49),D10,ROUND(Assumptions!$E$81*Assumptions!$E$47,0)) | F10: =IF(AND(Assumptions!$E$48>0,Assumptions!$F$6>=Assumptions!$E$48,Assumptions!$F$6<Assumptions!$E$48+Assumptions!$E$49),E10,ROUND(Assumptions!$F$81*Assumptions!$E$47,0)) | G10: =IF(AND(Assumptions!$E$48>0,Assumptions!$G$6>=Assumptions!$E$48,Assumptions!$G$6<Assumptions!$E$48+Assumptions!$E$49),F10,ROUND(Assumptions!$G$81*Assumptions!$E$47,0)) | H10: =IF(AND(Assumptions!$E$48>0,Assumptions!$H$6>=Assumptions!$E$48,Assumptions!$H$6<Assumptions!$E$48+Assumptions!$E$49),G10,ROUND(Assumptions!$H$81*Assumptions!$E$47,0))
A11: Claims analysts / customer success (US) [Claims operations (COGS)] | B11: =ROUND(Assumptions!$B$85*Assumptions!$E$47,0) | C11: =IF(AND(Assumptions!$E$48>0,Assumptions!$C$6>=Assumptions!$E$48,Assumptions!$C$6<Assumptions!$E$48+Assumptions!$E$49),B11,ROUND(Assumptions!$C$85*Assumptions!$E$47,0)) | D11: =IF(AND(Assumptions!$E$48>0,Assumptions!$D$6>=Assumptions!$E$48,Assumptions!$D$6<Assumptions!$E$48+Assumptions!$E$49),C11,ROUND(Assumptions!$D$85*Assumptions!$E$47,0)) | E11: =IF(AND(Assumptions!$E$48>0,Assumptions!$E$6>=Assumptions!$E$48,Assumptions!$E$6<Assumptions!$E$48+Assumptions!$E$49),D11,ROUND(Assumptions!$E$85*Assumptions!$E$47,0)) | F11: =IF(AND(Assumptions!$E$48>0,Assumptions!$F$6>=Assumptions!$E$48,Assumptions!$F$6<Assumptions!$E$48+Assumptions!$E$49),E11,ROUND(Assumptions!$F$85*Assumptions!$E$47,0)) | G11: =IF(AND(Assumptions!$E$48>0,Assumptions!$G$6>=Assumptions!$E$48,Assumptions!$G$6<Assumptions!$E$48+Assumptions!$E$49),F11,ROUND(Assumptions!$G$85*Assumptions!$E$47,0)) | H11: =IF(AND(Assumptions!$E$48>0,Assumptions!$H$6>=Assumptions!$E$48,Assumptions!$H$6<Assumptions!$E$48+Assumptions!$E$49),G11,ROUND(Assumptions!$H$85*Assumptions!$E$47,0))
A12: Marketing (US) [Marketing] | B12: =ROUND(Assumptions!$B$89*Assumptions!$E$47,0) | C12: =IF(AND(Assumptions!$E$48>0,Assumptions!$C$6>=Assumptions!$E$48,Assumptions!$C$6<Assumptions!$E$48+Assumptions!$E$49),B12,ROUND(Assumptions!$C$89*Assumptions!$E$47,0)) | D12: =IF(AND(Assumptions!$E$48>0,Assumptions!$D$6>=Assumptions!$E$48,Assumptions!$D$6<Assumptions!$E$48+Assumptions!$E$49),C12,ROUND(Assumptions!$D$89*Assumptions!$E$47,0)) | E12: =IF(AND(Assumptions!$E$48>0,Assumptions!$E$6>=Assumptions!$E$48,Assumptions!$E$6<Assumptions!$E$48+Assumptions!$E$49),D12,ROUND(Assumptions!$E$89*Assumptions!$E$47,0)) | F12: =IF(AND(Assumptions!$E$48>0,Assumptions!$F$6>=Assumptions!$E$48,Assumptions!$F$6<Assumptions!$E$48+Assumptions!$E$49),E12,ROUND(Assumptions!$F$89*Assumptions!$E$47,0)) | G12: =IF(AND(Assumptions!$E$48>0,Assumptions!$G$6>=Assumptions!$E$48,Assumptions!$G$6<Assumptions!$E$48+Assumptions!$E$49),F12,ROUND(Assumptions!$G$89*Assumptions!$E$47,0)) | H12: =IF(AND(Assumptions!$E$48>0,Assumptions!$H$6>=Assumptions!$E$48,Assumptions!$H$6<Assumptions!$E$48+Assumptions!$E$49),G12,ROUND(Assumptions!$H$89*Assumptions!$E$47,0))
A13: Finance, legal operations, people [G&A] | B13: =ROUND(Assumptions!$B$93*Assumptions!$E$47,0) | C13: =IF(AND(Assumptions!$E$48>0,Assumptions!$C$6>=Assumptions!$E$48,Assumptions!$C$6<Assumptions!$E$48+Assumptions!$E$49),B13,ROUND(Assumptions!$C$93*Assumptions!$E$47,0)) | D13: =IF(AND(Assumptions!$E$48>0,Assumptions!$D$6>=Assumptions!$E$48,Assumptions!$D$6<Assumptions!$E$48+Assumptions!$E$49),C13,ROUND(Assumptions!$D$93*Assumptions!$E$47,0)) | E13: =IF(AND(Assumptions!$E$48>0,Assumptions!$E$6>=Assumptions!$E$48,Assumptions!$E$6<Assumptions!$E$48+Assumptions!$E$49),D13,ROUND(Assumptions!$E$93*Assumptions!$E$47,0)) | F13: =IF(AND(Assumptions!$E$48>0,Assumptions!$F$6>=Assumptions!$E$48,Assumptions!$F$6<Assumptions!$E$48+Assumptions!$E$49),E13,ROUND(Assumptions!$F$93*Assumptions!$E$47,0)) | G13: =IF(AND(Assumptions!$E$48>0,Assumptions!$G$6>=Assumptions!$E$48,Assumptions!$G$6<Assumptions!$E$48+Assumptions!$E$49),F13,ROUND(Assumptions!$G$93*Assumptions!$E$47,0)) | H13: =IF(AND(Assumptions!$E$48>0,Assumptions!$H$6>=Assumptions!$E$48,Assumptions!$H$6<Assumptions!$E$48+Assumptions!$E$49),G13,ROUND(Assumptions!$H$93*Assumptions!$E$47,0))
A14: Total headcount at year end | B14: =SUM(B5:B13) | C14: =SUM(C5:C13) | D14: =SUM(D5:D13) | E14: =SUM(E5:E13) | F14: =SUM(F5:F13) | G14: =SUM(G5:G13) | H14: =SUM(H5:H13)
A15: Net new hires | B15: =B14 | C15: =MAX(0,C14-B14) | D15: =MAX(0,D14-C14) | E15: =MAX(0,E14-D14) | F15: =MAX(0,F14-E14) | G15: =MAX(0,G14-F14) | H15: =MAX(0,H14-G14)
A16: FTE-years paid in the year
A17: Founder / CEO | B17: =B5*(5-Assumptions!$B$63)/4 | C17: =(B5+C5)/2 | D17: =(C5+D5)/2 | E17: =(D5+E5)/2 | F17: =(E5+F5)/2 | G17: =(F5+G5)/2 | H17: =(G5+H5)/2
A18: Software engineers | B18: =B6*(5-Assumptions!$B$67)/4 | C18: =(B6+C6)/2 | D18: =(C6+D6)/2 | E18: =(D6+E6)/2 | F18: =(E6+F6)/2 | G18: =(F6+G6)/2 | H18: =(G6+H6)/2
A19: ML / data engineers | B19: =B7*(5-Assumptions!$B$71)/4 | C19: =(B7+C7)/2 | D19: =(C7+D7)/2 | E19: =(D7+E7)/2 | F19: =(E7+F7)/2 | G19: =(F7+G7)/2 | H19: =(G7+H7)/2
A20: Security engineer | B20: =B8*(5-Assumptions!$B$75)/4 | C20: =(B8+C8)/2 | D20: =(C8+D8)/2 | E20: =(D8+E8)/2 | F20: =(E8+F8)/2 | G20: =(F8+G8)/2 | H20: =(G8+H8)/2
A21: Account executives (US) | B21: =B9*(5-Assumptions!$B$79)/4 | C21: =(B9+C9)/2 | D21: =(C9+D9)/2 | E21: =(D9+E9)/2 | F21: =(E9+F9)/2 | G21: =(F9+G9)/2 | H21: =(G9+H9)/2
A22: Sales engineer (US) | B22: =B10*(5-Assumptions!$B$83)/4 | C22: =(B10+C10)/2 | D22: =(C10+D10)/2 | E22: =(D10+E10)/2 | F22: =(E10+F10)/2 | G22: =(F10+G10)/2 | H22: =(G10+H10)/2
A23: Claims analysts / customer success (US) | B23: =B11*(5-Assumptions!$B$87)/4 | C23: =(B11+C11)/2 | D23: =(C11+D11)/2 | E23: =(D11+E11)/2 | F23: =(E11+F11)/2 | G23: =(F11+G11)/2 | H23: =(G11+H11)/2
A24: Marketing (US) | B24: =B12*(5-Assumptions!$B$91)/4 | C24: =(B12+C12)/2 | D24: =(C12+D12)/2 | E24: =(D12+E12)/2 | F24: =(E12+F12)/2 | G24: =(F12+G12)/2 | H24: =(G12+H12)/2
A25: Finance, legal operations, people | B25: =B13*(5-Assumptions!$B$95)/4 | C25: =(B13+C13)/2 | D25: =(C13+D13)/2 | E25: =(D13+E13)/2 | F25: =(E13+F13)/2 | G25: =(F13+G13)/2 | H25: =(G13+H13)/2
A26: People cost ($K)
A27: Founder / CEO | B27: =B17*Assumptions!$B$64*(1+Assumptions!$B$8)^(Assumptions!$B$6-1) | C27: =C17*Assumptions!$B$64*(1+Assumptions!$B$8)^(Assumptions!$C$6-1) | D27: =D17*Assumptions!$B$64*(1+Assumptions!$B$8)^(Assumptions!$D$6-1) | E27: =E17*Assumptions!$B$64*(1+Assumptions!$B$8)^(Assumptions!$E$6-1) | F27: =F17*Assumptions!$B$64*(1+Assumptions!$B$8)^(Assumptions!$F$6-1) | G27: =G17*Assumptions!$B$64*(1+Assumptions!$B$8)^(Assumptions!$G$6-1) | H27: =H17*Assumptions!$B$64*(1+Assumptions!$B$8)^(Assumptions!$H$6-1)
A28: Software engineers | B28: =B18*Assumptions!$B$68*(1+Assumptions!$B$8)^(Assumptions!$B$6-1) | C28: =C18*Assumptions!$B$68*(1+Assumptions!$B$8)^(Assumptions!$C$6-1) | D28: =D18*Assumptions!$B$68*(1+Assumptions!$B$8)^(Assumptions!$D$6-1) | E28: =E18*Assumptions!$B$68*(1+Assumptions!$B$8)^(Assumptions!$E$6-1) | F28: =F18*Assumptions!$B$68*(1+Assumptions!$B$8)^(Assumptions!$F$6-1) | G28: =G18*Assumptions!$B$68*(1+Assumptions!$B$8)^(Assumptions!$G$6-1) | H28: =H18*Assumptions!$B$68*(1+Assumptions!$B$8)^(Assumptions!$H$6-1)
A29: ML / data engineers | B29: =B19*Assumptions!$B$72*(1+Assumptions!$B$8)^(Assumptions!$B$6-1) | C29: =C19*Assumptions!$B$72*(1+Assumptions!$B$8)^(Assumptions!$C$6-1) | D29: =D19*Assumptions!$B$72*(1+Assumptions!$B$8)^(Assumptions!$D$6-1) | E29: =E19*Assumptions!$B$72*(1+Assumptions!$B$8)^(Assumptions!$E$6-1) | F29: =F19*Assumptions!$B$72*(1+Assumptions!$B$8)^(Assumptions!$F$6-1) | G29: =G19*Assumptions!$B$72*(1+Assumptions!$B$8)^(Assumptions!$G$6-1) | H29: =H19*Assumptions!$B$72*(1+Assumptions!$B$8)^(Assumptions!$H$6-1)
A30: Security engineer | B30: =B20*Assumptions!$B$76*(1+Assumptions!$B$8)^(Assumptions!$B$6-1) | C30: =C20*Assumptions!$B$76*(1+Assumptions!$B$8)^(Assumptions!$C$6-1) | D30: =D20*Assumptions!$B$76*(1+Assumptions!$B$8)^(Assumptions!$D$6-1) | E30: =E20*Assumptions!$B$76*(1+Assumptions!$B$8)^(Assumptions!$E$6-1) | F30: =F20*Assumptions!$B$76*(1+Assumptions!$B$8)^(Assumptions!$F$6-1) | G30: =G20*Assumptions!$B$76*(1+Assumptions!$B$8)^(Assumptions!$G$6-1) | H30: =H20*Assumptions!$B$76*(1+Assumptions!$B$8)^(Assumptions!$H$6-1)
A31: Account executives (US) | B31: =B21*Assumptions!$B$80*(1+Assumptions!$B$8)^(Assumptions!$B$6-1) | C31: =C21*Assumptions!$B$80*(1+Assumptions!$B$8)^(Assumptions!$C$6-1) | D31: =D21*Assumptions!$B$80*(1+Assumptions!$B$8)^(Assumptions!$D$6-1) | E31: =E21*Assumptions!$B$80*(1+Assumptions!$B$8)^(Assumptions!$E$6-1) | F31: =F21*Assumptions!$B$80*(1+Assumptions!$B$8)^(Assumptions!$F$6-1) | G31: =G21*Assumptions!$B$80*(1+Assumptions!$B$8)^(Assumptions!$G$6-1) | H31: =H21*Assumptions!$B$80*(1+Assumptions!$B$8)^(Assumptions!$H$6-1)
A32: Sales engineer (US) | B32: =B22*Assumptions!$B$84*(1+Assumptions!$B$8)^(Assumptions!$B$6-1) | C32: =C22*Assumptions!$B$84*(1+Assumptions!$B$8)^(Assumptions!$C$6-1) | D32: =D22*Assumptions!$B$84*(1+Assumptions!$B$8)^(Assumptions!$D$6-1) | E32: =E22*Assumptions!$B$84*(1+Assumptions!$B$8)^(Assumptions!$E$6-1) | F32: =F22*Assumptions!$B$84*(1+Assumptions!$B$8)^(Assumptions!$F$6-1) | G32: =G22*Assumptions!$B$84*(1+Assumptions!$B$8)^(Assumptions!$G$6-1) | H32: =H22*Assumptions!$B$84*(1+Assumptions!$B$8)^(Assumptions!$H$6-1)
A33: Claims analysts / customer success (US) | B33: =B23*Assumptions!$B$88*(1+Assumptions!$B$8)^(Assumptions!$B$6-1) | C33: =C23*Assumptions!$B$88*(1+Assumptions!$B$8)^(Assumptions!$C$6-1) | D33: =D23*Assumptions!$B$88*(1+Assumptions!$B$8)^(Assumptions!$D$6-1) | E33: =E23*Assumptions!$B$88*(1+Assumptions!$B$8)^(Assumptions!$E$6-1) | F33: =F23*Assumptions!$B$88*(1+Assumptions!$B$8)^(Assumptions!$F$6-1) | G33: =G23*Assumptions!$B$88*(1+Assumptions!$B$8)^(Assumptions!$G$6-1) | H33: =H23*Assumptions!$B$88*(1+Assumptions!$B$8)^(Assumptions!$H$6-1)
A34: Marketing (US) | B34: =B24*Assumptions!$B$92*(1+Assumptions!$B$8)^(Assumptions!$B$6-1) | C34: =C24*Assumptions!$B$92*(1+Assumptions!$B$8)^(Assumptions!$C$6-1) | D34: =D24*Assumptions!$B$92*(1+Assumptions!$B$8)^(Assumptions!$D$6-1) | E34: =E24*Assumptions!$B$92*(1+Assumptions!$B$8)^(Assumptions!$E$6-1) | F34: =F24*Assumptions!$B$92*(1+Assumptions!$B$8)^(Assumptions!$F$6-1) | G34: =G24*Assumptions!$B$92*(1+Assumptions!$B$8)^(Assumptions!$G$6-1) | H34: =H24*Assumptions!$B$92*(1+Assumptions!$B$8)^(Assumptions!$H$6-1)
A35: Finance, legal operations, people | B35: =B25*Assumptions!$B$96*(1+Assumptions!$B$8)^(Assumptions!$B$6-1) | C35: =C25*Assumptions!$B$96*(1+Assumptions!$B$8)^(Assumptions!$C$6-1) | D35: =D25*Assumptions!$B$96*(1+Assumptions!$B$8)^(Assumptions!$D$6-1) | E35: =E25*Assumptions!$B$96*(1+Assumptions!$B$8)^(Assumptions!$E$6-1) | F35: =F25*Assumptions!$B$96*(1+Assumptions!$B$8)^(Assumptions!$F$6-1) | G35: =G25*Assumptions!$B$96*(1+Assumptions!$B$8)^(Assumptions!$G$6-1) | H35: =H25*Assumptions!$B$96*(1+Assumptions!$B$8)^(Assumptions!$H$6-1)
A36: Total people cost | B36: =SUM(B27:B35) | C36: =SUM(C27:C35) | D36: =SUM(D27:D35) | E36: =SUM(E27:E35) | F36: =SUM(F27:F35) | G36: =SUM(G27:G35) | H36: =SUM(H27:H35)
A37: People cost by department ($K)
A38: Engineering | B38: =B28+B29 | C38: =C28+C29 | D38: =D28+D29 | E38: =E28+E29 | F38: =F28+F29 | G38: =G28+G29 | H38: =H28+H29
A39: Security | B39: =B30 | C39: =C30 | D39: =D30 | E39: =E30 | F39: =F30 | G39: =G30 | H39: =H30
A40: Sales | B40: =B31+B32 | C40: =C31+C32 | D40: =D31+D32 | E40: =E31+E32 | F40: =F31+F32 | G40: =G31+G32 | H40: =H31+H32
A41: Marketing | B41: =B34 | C41: =C34 | D41: =D34 | E41: =E34 | F41: =F34 | G41: =G34 | H41: =H34
A42: G&A | B42: =B27+B35 | C42: =C27+C35 | D42: =D27+D35 | E42: =E27+E35 | F42: =F27+F35 | G42: =G27+G35 | H42: =H27+H35
A43: Claims operations (COGS) | B43: =B33 | C43: =C33 | D43: =D33 | E43: =E33 | F43: =F33 | G43: =G33 | H43: =H33
A44: Headcount by department at year end
A45: Engineering | B45: =B6+B7 | C45: =C6+C7 | D45: =D6+D7 | E45: =E6+E7 | F45: =F6+F7 | G45: =G6+G7 | H45: =H6+H7
A46: Security | B46: =B8 | C46: =C8 | D46: =D8 | E46: =E8 | F46: =F8 | G46: =G8 | H46: =H8
A47: Sales | B47: =B9+B10 | C47: =C9+C10 | D47: =D9+D10 | E47: =E9+E10 | F47: =F9+F10 | G47: =G9+G10 | H47: =H9+H10
A48: Marketing | B48: =B12 | C48: =C12 | D48: =D12 | E48: =E12 | F48: =F12 | G48: =G12 | H48: =H12
A49: G&A | B49: =B5+B13 | C49: =C5+C13 | D49: =D5+D13 | E49: =E5+E13 | F49: =F5+F13 | G49: =G5+G13 | H49: =H5+H13
A50: Claims operations (COGS) | B50: =B11 | C50: =C11 | D50: =D11 | E50: =E11 | F50: =F11 | G50: =G11 | H50: =H11
A51: Equipment capex = net new hires x capex per hire ($K) | B51: =B15*Assumptions!$B$15 | C51: =C15*Assumptions!$B$15 | D51: =D15*Assumptions!$B$15 | E51: =E15*Assumptions!$B$15 | F51: =F15*Assumptions!$B$15 | G51: =G15*Assumptions!$B$15 | H51: =H15*Assumptions!$B$15

Sheet OpEx
A1: Operating costs (active scenario)
A2: Other costs = base plan (year 1) and base plan x scale (year 2 on), held at prior year from the freeze year. Departments combine people cost and programme spend.
A3: $K unless stated | B3: ="Y"&Assumptions!$B$6 | C3: ="Y"&Assumptions!$C$6 | D3: ="Y"&Assumptions!$D$6 | E3: ="Y"&Assumptions!$E$6 | F3: ="Y"&Assumptions!$F$6 | G3: ="Y"&Assumptions!$G$6 | H3: ="Y"&Assumptions!$H$6
A4: Other operating costs ($K)
A5: Cloud hosting, data feeds and tooling [COGS] | B5: =Assumptions!$B$98 | C5: =IF(AND(Assumptions!$E$48>0,Assumptions!$C$6>=Assumptions!$E$48,Assumptions!$C$6<Assumptions!$E$48+Assumptions!$E$49),B5,Assumptions!$C$98*Assumptions!$E$47) | D5: =IF(AND(Assumptions!$E$48>0,Assumptions!$D$6>=Assumptions!$E$48,Assumptions!$D$6<Assumptions!$E$48+Assumptions!$E$49),C5,Assumptions!$D$98*Assumptions!$E$47) | E5: =IF(AND(Assumptions!$E$48>0,Assumptions!$E$6>=Assumptions!$E$48,Assumptions!$E$6<Assumptions!$E$48+Assumptions!$E$49),D5,Assumptions!$E$98*Assumptions!$E$47) | F5: =IF(AND(Assumptions!$E$48>0,Assumptions!$F$6>=Assumptions!$E$48,Assumptions!$F$6<Assumptions!$E$48+Assumptions!$E$49),E5,Assumptions!$F$98*Assumptions!$E$47) | G5: =IF(AND(Assumptions!$E$48>0,Assumptions!$G$6>=Assumptions!$E$48,Assumptions!$G$6<Assumptions!$E$48+Assumptions!$E$49),F5,Assumptions!$G$98*Assumptions!$E$47) | H5: =IF(AND(Assumptions!$E$48>0,Assumptions!$H$6>=Assumptions!$E$48,Assumptions!$H$6<Assumptions!$E$48+Assumptions!$E$49),G5,Assumptions!$H$98*Assumptions!$E$47)
A6: Security programme (SOC 2, pen tests, tooling, insurance) [Security] | B6: =Assumptions!$B$99 | C6: =IF(AND(Assumptions!$E$48>0,Assumptions!$C$6>=Assumptions!$E$48,Assumptions!$C$6<Assumptions!$E$48+Assumptions!$E$49),B6,Assumptions!$C$99*Assumptions!$E$47) | D6: =IF(AND(Assumptions!$E$48>0,Assumptions!$D$6>=Assumptions!$E$48,Assumptions!$D$6<Assumptions!$E$48+Assumptions!$E$49),C6,Assumptions!$D$99*Assumptions!$E$47) | E6: =IF(AND(Assumptions!$E$48>0,Assumptions!$E$6>=Assumptions!$E$48,Assumptions!$E$6<Assumptions!$E$48+Assumptions!$E$49),D6,Assumptions!$E$99*Assumptions!$E$47) | F6: =IF(AND(Assumptions!$E$48>0,Assumptions!$F$6>=Assumptions!$E$48,Assumptions!$F$6<Assumptions!$E$48+Assumptions!$E$49),E6,Assumptions!$F$99*Assumptions!$E$47) | G6: =IF(AND(Assumptions!$E$48>0,Assumptions!$G$6>=Assumptions!$E$48,Assumptions!$G$6<Assumptions!$E$48+Assumptions!$E$49),F6,Assumptions!$G$99*Assumptions!$E$47) | H6: =IF(AND(Assumptions!$E$48>0,Assumptions!$H$6>=Assumptions!$E$48,Assumptions!$H$6<Assumptions!$E$48+Assumptions!$E$49),G6,Assumptions!$H$99*Assumptions!$E$47)
A7: Legal and regulatory [G&A] | B7: =Assumptions!$B$100 | C7: =IF(AND(Assumptions!$E$48>0,Assumptions!$C$6>=Assumptions!$E$48,Assumptions!$C$6<Assumptions!$E$48+Assumptions!$E$49),B7,Assumptions!$C$100*Assumptions!$E$47) | D7: =IF(AND(Assumptions!$E$48>0,Assumptions!$D$6>=Assumptions!$E$48,Assumptions!$D$6<Assumptions!$E$48+Assumptions!$E$49),C7,Assumptions!$D$100*Assumptions!$E$47) | E7: =IF(AND(Assumptions!$E$48>0,Assumptions!$E$6>=Assumptions!$E$48,Assumptions!$E$6<Assumptions!$E$48+Assumptions!$E$49),D7,Assumptions!$E$100*Assumptions!$E$47) | F7: =IF(AND(Assumptions!$E$48>0,Assumptions!$F$6>=Assumptions!$E$48,Assumptions!$F$6<Assumptions!$E$48+Assumptions!$E$49),E7,Assumptions!$F$100*Assumptions!$E$47) | G7: =IF(AND(Assumptions!$E$48>0,Assumptions!$G$6>=Assumptions!$E$48,Assumptions!$G$6<Assumptions!$E$48+Assumptions!$E$49),F7,Assumptions!$G$100*Assumptions!$E$47) | H7: =IF(AND(Assumptions!$E$48>0,Assumptions!$H$6>=Assumptions!$E$48,Assumptions!$H$6<Assumptions!$E$48+Assumptions!$E$49),G7,Assumptions!$H$100*Assumptions!$E$47)
A8: Marketing programmes and events [Marketing] | B8: =Assumptions!$B$101 | C8: =IF(AND(Assumptions!$E$48>0,Assumptions!$C$6>=Assumptions!$E$48,Assumptions!$C$6<Assumptions!$E$48+Assumptions!$E$49),B8,Assumptions!$C$101*Assumptions!$E$47) | D8: =IF(AND(Assumptions!$E$48>0,Assumptions!$D$6>=Assumptions!$E$48,Assumptions!$D$6<Assumptions!$E$48+Assumptions!$E$49),C8,Assumptions!$D$101*Assumptions!$E$47) | E8: =IF(AND(Assumptions!$E$48>0,Assumptions!$E$6>=Assumptions!$E$48,Assumptions!$E$6<Assumptions!$E$48+Assumptions!$E$49),D8,Assumptions!$E$101*Assumptions!$E$47) | F8: =IF(AND(Assumptions!$E$48>0,Assumptions!$F$6>=Assumptions!$E$48,Assumptions!$F$6<Assumptions!$E$48+Assumptions!$E$49),E8,Assumptions!$F$101*Assumptions!$E$47) | G8: =IF(AND(Assumptions!$E$48>0,Assumptions!$G$6>=Assumptions!$E$48,Assumptions!$G$6<Assumptions!$E$48+Assumptions!$E$49),F8,Assumptions!$G$101*Assumptions!$E$47) | H8: =IF(AND(Assumptions!$E$48>0,Assumptions!$H$6>=Assumptions!$E$48,Assumptions!$H$6<Assumptions!$E$48+Assumptions!$E$49),G8,Assumptions!$H$101*Assumptions!$E$47)
A9: Travel and customer visits [Sales] | B9: =Assumptions!$B$102 | C9: =IF(AND(Assumptions!$E$48>0,Assumptions!$C$6>=Assumptions!$E$48,Assumptions!$C$6<Assumptions!$E$48+Assumptions!$E$49),B9,Assumptions!$C$102*Assumptions!$E$47) | D9: =IF(AND(Assumptions!$E$48>0,Assumptions!$D$6>=Assumptions!$E$48,Assumptions!$D$6<Assumptions!$E$48+Assumptions!$E$49),C9,Assumptions!$D$102*Assumptions!$E$47) | E9: =IF(AND(Assumptions!$E$48>0,Assumptions!$E$6>=Assumptions!$E$48,Assumptions!$E$6<Assumptions!$E$48+Assumptions!$E$49),D9,Assumptions!$E$102*Assumptions!$E$47) | F9: =IF(AND(Assumptions!$E$48>0,Assumptions!$F$6>=Assumptions!$E$48,Assumptions!$F$6<Assumptions!$E$48+Assumptions!$E$49),E9,Assumptions!$F$102*Assumptions!$E$47) | G9: =IF(AND(Assumptions!$E$48>0,Assumptions!$G$6>=Assumptions!$E$48,Assumptions!$G$6<Assumptions!$E$48+Assumptions!$E$49),F9,Assumptions!$G$102*Assumptions!$E$47) | H9: =IF(AND(Assumptions!$E$48>0,Assumptions!$H$6>=Assumptions!$E$48,Assumptions!$H$6<Assumptions!$E$48+Assumptions!$E$49),G9,Assumptions!$H$102*Assumptions!$E$47)
A10: Office, software, admin, accounting [G&A] | B10: =Assumptions!$B$103 | C10: =IF(AND(Assumptions!$E$48>0,Assumptions!$C$6>=Assumptions!$E$48,Assumptions!$C$6<Assumptions!$E$48+Assumptions!$E$49),B10,Assumptions!$C$103*Assumptions!$E$47) | D10: =IF(AND(Assumptions!$E$48>0,Assumptions!$D$6>=Assumptions!$E$48,Assumptions!$D$6<Assumptions!$E$48+Assumptions!$E$49),C10,Assumptions!$D$103*Assumptions!$E$47) | E10: =IF(AND(Assumptions!$E$48>0,Assumptions!$E$6>=Assumptions!$E$48,Assumptions!$E$6<Assumptions!$E$48+Assumptions!$E$49),D10,Assumptions!$E$103*Assumptions!$E$47) | F10: =IF(AND(Assumptions!$E$48>0,Assumptions!$F$6>=Assumptions!$E$48,Assumptions!$F$6<Assumptions!$E$48+Assumptions!$E$49),E10,Assumptions!$F$103*Assumptions!$E$47) | G10: =IF(AND(Assumptions!$E$48>0,Assumptions!$G$6>=Assumptions!$E$48,Assumptions!$G$6<Assumptions!$E$48+Assumptions!$E$49),F10,Assumptions!$G$103*Assumptions!$E$47) | H10: =IF(AND(Assumptions!$E$48>0,Assumptions!$H$6>=Assumptions!$E$48,Assumptions!$H$6<Assumptions!$E$48+Assumptions!$E$49),G10,Assumptions!$H$103*Assumptions!$E$47)
A11: Partner commission on carrier revenue [Sales] | B11: =Revenue!B24*Assumptions!$B$43 | C11: =Revenue!C24*Assumptions!$B$43 | D11: =Revenue!D24*Assumptions!$B$43 | E11: =Revenue!E24*Assumptions!$B$43 | F11: =Revenue!F24*Assumptions!$B$43 | G11: =Revenue!G24*Assumptions!$B$43 | H11: =Revenue!H24*Assumptions!$B$43
A12: Operating expense by department, excluding cost of revenue ($K)
A13: Engineering | B13: =Headcount!B38 | C13: =Headcount!C38 | D13: =Headcount!D38 | E13: =Headcount!E38 | F13: =Headcount!F38 | G13: =Headcount!G38 | H13: =Headcount!H38
A14: Security | B14: =Headcount!B39+B6 | C14: =Headcount!C39+C6 | D14: =Headcount!D39+D6 | E14: =Headcount!E39+E6 | F14: =Headcount!F39+F6 | G14: =Headcount!G39+G6 | H14: =Headcount!H39+H6
A15: Sales | B15: =Headcount!B40+B9+B11 | C15: =Headcount!C40+C9+C11 | D15: =Headcount!D40+D9+D11 | E15: =Headcount!E40+E9+E11 | F15: =Headcount!F40+F9+F11 | G15: =Headcount!G40+G9+G11 | H15: =Headcount!H40+H9+H11
A16: Marketing | B16: =Headcount!B41+B8 | C16: =Headcount!C41+C8 | D16: =Headcount!D41+D8 | E16: =Headcount!E41+E8 | F16: =Headcount!F41+F8 | G16: =Headcount!G41+G8 | H16: =Headcount!H41+H8
A17: G&A | B17: =Headcount!B42+B7+B10 | C17: =Headcount!C42+C7+C10 | D17: =Headcount!D42+D7+D10 | E17: =Headcount!E42+E7+E10 | F17: =Headcount!F42+F7+F10 | G17: =Headcount!G42+G7+G10 | H17: =Headcount!H42+H7+H10
A18: Total operating expense | B18: =SUM(B13:B17) | C18: =SUM(C13:C17) | D18: =SUM(D13:D17) | E18: =SUM(E13:E17) | F18: =SUM(F13:F17) | G18: =SUM(G13:G17) | H18: =SUM(H13:H17)
A19: Sales and marketing (Sales + Marketing departments) | B19: =B15+B16 | C19: =C15+C16 | D19: =D15+D16 | E19: =E15+E16 | F19: =F15+F16 | G19: =G15+G16 | H19: =H15+H16
A20: Cost of revenue ($K)
A21: Claims operations people | B21: =Headcount!B43 | C21: =Headcount!C43 | D21: =Headcount!D43 | E21: =Headcount!E43 | F21: =Headcount!F43 | G21: =Headcount!G43 | H21: =Headcount!H43
A22: Hosting, data feeds and tooling | B22: =B5 | C22: =C5 | D22: =D5 | E22: =E5 | F22: =F5 | G22: =G5 | H22: =H5
A23: Variable cost = revenue x variable cost % | B23: =Revenue!B30*Assumptions!$E$50 | C23: =Revenue!C30*Assumptions!$E$50 | D23: =Revenue!D30*Assumptions!$E$50 | E23: =Revenue!E30*Assumptions!$E$50 | F23: =Revenue!F30*Assumptions!$E$50 | G23: =Revenue!G30*Assumptions!$E$50 | H23: =Revenue!H30*Assumptions!$E$50
A24: Total cost of revenue | B24: =B21+B22+B23 | C24: =C21+C22+C23 | D24: =D21+D22+D23 | E24: =E21+E22+E23 | F24: =F21+F22+F23 | G24: =G21+G22+G23 | H24: =H21+H22+H23
A26: Year-1 budget by department and quarter ($K). People cost starts in the hiring quarter; non-people costs are spread evenly. | B26: Q1 | C26: Q2 | D26: Q3 | E26: Q4 | F26: Year 1
A27: Founder / CEO [G&A] | B27: =Headcount!B5*IF(1>=Assumptions!$B$63,1,0)*Assumptions!$B$64/4 | C27: =Headcount!B5*IF(2>=Assumptions!$B$63,1,0)*Assumptions!$B$64/4 | D27: =Headcount!B5*IF(3>=Assumptions!$B$63,1,0)*Assumptions!$B$64/4 | E27: =Headcount!B5*IF(4>=Assumptions!$B$63,1,0)*Assumptions!$B$64/4 | F27: =SUM(B27:E27)
A28: Software engineers [Engineering] | B28: =Headcount!B6*IF(1>=Assumptions!$B$67,1,0)*Assumptions!$B$68/4 | C28: =Headcount!B6*IF(2>=Assumptions!$B$67,1,0)*Assumptions!$B$68/4 | D28: =Headcount!B6*IF(3>=Assumptions!$B$67,1,0)*Assumptions!$B$68/4 | E28: =Headcount!B6*IF(4>=Assumptions!$B$67,1,0)*Assumptions!$B$68/4 | F28: =SUM(B28:E28)
A29: ML / data engineers [Engineering] | B29: =Headcount!B7*IF(1>=Assumptions!$B$71,1,0)*Assumptions!$B$72/4 | C29: =Headcount!B7*IF(2>=Assumptions!$B$71,1,0)*Assumptions!$B$72/4 | D29: =Headcount!B7*IF(3>=Assumptions!$B$71,1,0)*Assumptions!$B$72/4 | E29: =Headcount!B7*IF(4>=Assumptions!$B$71,1,0)*Assumptions!$B$72/4 | F29: =SUM(B29:E29)
A30: Security engineer [Security] | B30: =Headcount!B8*IF(1>=Assumptions!$B$75,1,0)*Assumptions!$B$76/4 | C30: =Headcount!B8*IF(2>=Assumptions!$B$75,1,0)*Assumptions!$B$76/4 | D30: =Headcount!B8*IF(3>=Assumptions!$B$75,1,0)*Assumptions!$B$76/4 | E30: =Headcount!B8*IF(4>=Assumptions!$B$75,1,0)*Assumptions!$B$76/4 | F30: =SUM(B30:E30)
A31: Account executives (US) [Sales] | B31: =Headcount!B9*IF(1>=Assumptions!$B$79,1,0)*Assumptions!$B$80/4 | C31: =Headcount!B9*IF(2>=Assumptions!$B$79,1,0)*Assumptions!$B$80/4 | D31: =Headcount!B9*IF(3>=Assumptions!$B$79,1,0)*Assumptions!$B$80/4 | E31: =Headcount!B9*IF(4>=Assumptions!$B$79,1,0)*Assumptions!$B$80/4 | F31: =SUM(B31:E31)
A32: Sales engineer (US) [Sales] | B32: =Headcount!B10*IF(1>=Assumptions!$B$83,1,0)*Assumptions!$B$84/4 | C32: =Headcount!B10*IF(2>=Assumptions!$B$83,1,0)*Assumptions!$B$84/4 | D32: =Headcount!B10*IF(3>=Assumptions!$B$83,1,0)*Assumptions!$B$84/4 | E32: =Headcount!B10*IF(4>=Assumptions!$B$83,1,0)*Assumptions!$B$84/4 | F32: =SUM(B32:E32)
A33: Claims analysts / customer success (US) [Claims operations (COGS)] | B33: =Headcount!B11*IF(1>=Assumptions!$B$87,1,0)*Assumptions!$B$88/4 | C33: =Headcount!B11*IF(2>=Assumptions!$B$87,1,0)*Assumptions!$B$88/4 | D33: =Headcount!B11*IF(3>=Assumptions!$B$87,1,0)*Assumptions!$B$88/4 | E33: =Headcount!B11*IF(4>=Assumptions!$B$87,1,0)*Assumptions!$B$88/4 | F33: =SUM(B33:E33)
A34: Marketing (US) [Marketing] | B34: =Headcount!B12*IF(1>=Assumptions!$B$91,1,0)*Assumptions!$B$92/4 | C34: =Headcount!B12*IF(2>=Assumptions!$B$91,1,0)*Assumptions!$B$92/4 | D34: =Headcount!B12*IF(3>=Assumptions!$B$91,1,0)*Assumptions!$B$92/4 | E34: =Headcount!B12*IF(4>=Assumptions!$B$91,1,0)*Assumptions!$B$92/4 | F34: =SUM(B34:E34)
A35: Finance, legal operations, people [G&A] | B35: =Headcount!B13*IF(1>=Assumptions!$B$95,1,0)*Assumptions!$B$96/4 | C35: =Headcount!B13*IF(2>=Assumptions!$B$95,1,0)*Assumptions!$B$96/4 | D35: =Headcount!B13*IF(3>=Assumptions!$B$95,1,0)*Assumptions!$B$96/4 | E35: =Headcount!B13*IF(4>=Assumptions!$B$95,1,0)*Assumptions!$B$96/4 | F35: =SUM(B35:E35)
A36: Cloud hosting, data feeds and tooling [COGS] | B36: =B5/4 | C36: =B5/4 | D36: =B5/4 | E36: =B5/4 | F36: =SUM(B36:E36)
A37: Security programme (SOC 2, pen tests, tooling, insurance) [Security] | B37: =B6/4 | C37: =B6/4 | D37: =B6/4 | E37: =B6/4 | F37: =SUM(B37:E37)
A38: Legal and regulatory [G&A] | B38: =B7/4 | C38: =B7/4 | D38: =B7/4 | E38: =B7/4 | F38: =SUM(B38:E38)
A39: Marketing programmes and events [Marketing] | B39: =B8/4 | C39: =B8/4 | D39: =B8/4 | E39: =B8/4 | F39: =SUM(B39:E39)
A40: Travel and customer visits [Sales] | B40: =B9/4 | C40: =B9/4 | D40: =B9/4 | E40: =B9/4 | F40: =SUM(B40:E40)
A41: Office, software, admin, accounting [G&A] | B41: =B10/4 | C41: =B10/4 | D41: =B10/4 | E41: =B10/4 | F41: =SUM(B41:E41)
A42: Partner commission [Sales] | B42: =B11/4 | C42: =B11/4 | D42: =B11/4 | E42: =B11/4 | F42: =SUM(B42:E42)
A43: Variable cost of revenue [COGS] | B43: =B23/4 | C43: =B23/4 | D43: =B23/4 | E43: =B23/4 | F43: =SUM(B43:E43)
A44: Year-1 budget: department totals ($K) | B44: Q1 | C44: Q2 | D44: Q3 | E44: Q4 | F44: Year 1
A45: Engineering | B45: =B28+B29 | C45: =C28+C29 | D45: =D28+D29 | E45: =E28+E29 | F45: =F28+F29
A46: Security | B46: =B30+B37 | C46: =C30+C37 | D46: =D30+D37 | E46: =E30+E37 | F46: =F30+F37
A47: Sales | B47: =B31+B32+B40+B42 | C47: =C31+C32+C40+C42 | D47: =D31+D32+D40+D42 | E47: =E31+E32+E40+E42 | F47: =F31+F32+F40+F42
A48: Marketing | B48: =B34+B39 | C48: =C34+C39 | D48: =D34+D39 | E48: =E34+E39 | F48: =F34+F39
A49: G&A | B49: =B27+B35+B38+B41 | C49: =C27+C35+C38+C41 | D49: =D27+D35+D38+D41 | E49: =E27+E35+E38+E41 | F49: =F27+F35+F38+F41
A50: Claims operations (COGS) | B50: =B33+B36+B43 | C50: =C33+C36+C43 | D50: =D33+D36+D43 | E50: =E33+E36+E43 | F50: =F33+F36+F43
A51: Total year-1 spend (operating expense + cost of revenue) | B51: =SUM(B45:B50) | C51: =SUM(C45:C50) | D51: =SUM(D45:D50) | E51: =SUM(E45:E50) | F51: =SUM(F45:F50)
A52: Check: year-1 budget total minus annual model (must be 0) | B52: =ROUND(F51-(B18+B24),6)

Sheet P&L
A1: Income statement (active scenario)
A2: Cost of revenue is built bottom-up (claims staff, hosting and data, variable cost); gross margin is an output.
A3: $K unless stated | B3: ="Y"&Assumptions!$B$6 | C3: ="Y"&Assumptions!$C$6 | D3: ="Y"&Assumptions!$D$6 | E3: ="Y"&Assumptions!$E$6 | F3: ="Y"&Assumptions!$F$6 | G3: ="Y"&Assumptions!$G$6 | H3: ="Y"&Assumptions!$H$6
A4: Revenue | B4: =Revenue!B30 | C4: =Revenue!C30 | D4: =Revenue!D30 | E4: =Revenue!E30 | F4: =Revenue!F30 | G4: =Revenue!G30 | H4: =Revenue!H30
A5: Cost of revenue | B5: =OpEx!B24 | C5: =OpEx!C24 | D5: =OpEx!D24 | E5: =OpEx!E24 | F5: =OpEx!F24 | G5: =OpEx!G24 | H5: =OpEx!H24
A6: Gross profit | B6: =B4-B5 | C6: =C4-C5 | D6: =D4-D5 | E6: =E4-E5 | F6: =F4-F5 | G6: =G4-G5 | H6: =H4-H5
A7: Gross margin | B7: =IF(B4=0,0,B6/B4) | C7: =IF(C4=0,0,C6/C4) | D7: =IF(D4=0,0,D6/D4) | E7: =IF(E4=0,0,E6/E4) | F7: =IF(F4=0,0,F6/F4) | G7: =IF(G4=0,0,G6/G4) | H7: =IF(H4=0,0,H6/H4)
A8: Operating expense: Engineering | B8: =OpEx!B13 | C8: =OpEx!C13 | D8: =OpEx!D13 | E8: =OpEx!E13 | F8: =OpEx!F13 | G8: =OpEx!G13 | H8: =OpEx!H13
A9: Operating expense: Security | B9: =OpEx!B14 | C9: =OpEx!C14 | D9: =OpEx!D14 | E9: =OpEx!E14 | F9: =OpEx!F14 | G9: =OpEx!G14 | H9: =OpEx!H14
A10: Operating expense: Sales | B10: =OpEx!B15 | C10: =OpEx!C15 | D10: =OpEx!D15 | E10: =OpEx!E15 | F10: =OpEx!F15 | G10: =OpEx!G15 | H10: =OpEx!H15
A11: Operating expense: Marketing | B11: =OpEx!B16 | C11: =OpEx!C16 | D11: =OpEx!D16 | E11: =OpEx!E16 | F11: =OpEx!F16 | G11: =OpEx!G16 | H11: =OpEx!H16
A12: Operating expense: G&A | B12: =OpEx!B17 | C12: =OpEx!C17 | D12: =OpEx!D17 | E12: =OpEx!E17 | F12: =OpEx!F17 | G12: =OpEx!G17 | H12: =OpEx!H17
A13: Total operating expense | B13: =SUM(B8:B12) | C13: =SUM(C8:C12) | D13: =SUM(D8:D12) | E13: =SUM(E8:E12) | F13: =SUM(F8:F12) | G13: =SUM(G8:G12) | H13: =SUM(H8:H12)
A14: EBITDA | B14: =B6-B13 | C14: =C6-C13 | D14: =D6-D13 | E14: =E6-E13 | F14: =F6-F13 | G14: =G6-G13 | H14: =H6-H13
A15: EBITDA margin | B15: =IF(B4=0,0,B14/B4) | C15: =IF(C4=0,0,C14/C4) | D15: =IF(D4=0,0,D14/D4) | E15: =IF(E4=0,0,E14/E4) | F15: =IF(F4=0,0,F14/F4) | G15: =IF(G4=0,0,G14/G4) | H15: =IF(H4=0,0,H14/H4)
A16: Depreciation = capex of the last N years / N (N = depreciation life) | B16: =SUMPRODUCT((Assumptions!$B$6:$H$6<=Assumptions!$B$6)*(Assumptions!$B$6:$H$6>Assumptions!$B$6-Assumptions!$B$16)*Headcount!$B$51:$H$51)/Assumptions!$B$16 | C16: =SUMPRODUCT((Assumptions!$B$6:$H$6<=Assumptions!$C$6)*(Assumptions!$B$6:$H$6>Assumptions!$C$6-Assumptions!$B$16)*Headcount!$B$51:$H$51)/Assumptions!$B$16 | D16: =SUMPRODUCT((Assumptions!$B$6:$H$6<=Assumptions!$D$6)*(Assumptions!$B$6:$H$6>Assumptions!$D$6-Assumptions!$B$16)*Headcount!$B$51:$H$51)/Assumptions!$B$16 | E16: =SUMPRODUCT((Assumptions!$B$6:$H$6<=Assumptions!$E$6)*(Assumptions!$B$6:$H$6>Assumptions!$E$6-Assumptions!$B$16)*Headcount!$B$51:$H$51)/Assumptions!$B$16 | F16: =SUMPRODUCT((Assumptions!$B$6:$H$6<=Assumptions!$F$6)*(Assumptions!$B$6:$H$6>Assumptions!$F$6-Assumptions!$B$16)*Headcount!$B$51:$H$51)/Assumptions!$B$16 | G16: =SUMPRODUCT((Assumptions!$B$6:$H$6<=Assumptions!$G$6)*(Assumptions!$B$6:$H$6>Assumptions!$G$6-Assumptions!$B$16)*Headcount!$B$51:$H$51)/Assumptions!$B$16 | H16: =SUMPRODUCT((Assumptions!$B$6:$H$6<=Assumptions!$H$6)*(Assumptions!$B$6:$H$6>Assumptions!$H$6-Assumptions!$B$16)*Headcount!$B$51:$H$51)/Assumptions!$B$16
A17: Operating profit (EBIT) | B17: =B14-B16 | C17: =C14-C16 | D17: =D14-D16 | E17: =E14-E16 | F17: =F14-F16 | G17: =G14-G16 | H17: =H14-H16
A18: Interest income on prior year-end cash | B18: =Assumptions!$B$18*Assumptions!$B$17 | C18: ='Cash Flow'!B17*Assumptions!$B$17 | D18: ='Cash Flow'!C17*Assumptions!$B$17 | E18: ='Cash Flow'!D17*Assumptions!$B$17 | F18: ='Cash Flow'!E17*Assumptions!$B$17 | G18: ='Cash Flow'!F17*Assumptions!$B$17 | H18: ='Cash Flow'!G17*Assumptions!$B$17
A19: Profit before tax | B19: =B17+B18 | C19: =C17+C18 | D19: =D17+D18 | E19: =E17+E18 | F19: =F17+F18 | G19: =G17+G18 | H19: =H17+H18
A20: Cumulative profit before tax (loss pool when negative) | B20: =B19 | C20: =B20+C19 | D20: =C20+D19 | E20: =D20+E19 | F20: =E20+F19 | G20: =F20+G19 | H20: =G20+H19
A21: Income tax after loss carry-forward = rate x increase in positive cumulative profit | B21: =MAX(0,B20)*Assumptions!$B$12 | C21: =MAX(0,MAX(0,C20)-MAX(0,B20))*Assumptions!$B$12 | D21: =MAX(0,MAX(0,D20)-MAX(0,C20))*Assumptions!$B$12 | E21: =MAX(0,MAX(0,E20)-MAX(0,D20))*Assumptions!$B$12 | F21: =MAX(0,MAX(0,F20)-MAX(0,E20))*Assumptions!$B$12 | G21: =MAX(0,MAX(0,G20)-MAX(0,F20))*Assumptions!$B$12 | H21: =MAX(0,MAX(0,H20)-MAX(0,G20))*Assumptions!$B$12
A22: Net income | B22: =B19-B21 | C22: =C19-C21 | D22: =D19-D21 | E22: =E19-E21 | F22: =F19-F21 | G22: =G19-G21 | H22: =H19-H21

Sheet Cash Flow
A1: Cash flow statement (active scenario)
A2: Indirect method. Financing = seed tranches and Series A in the years set on Assumptions.
A3: $K unless stated | B3: ="Y"&Assumptions!$B$6 | C3: ="Y"&Assumptions!$C$6 | D3: ="Y"&Assumptions!$D$6 | E3: ="Y"&Assumptions!$E$6 | F3: ="Y"&Assumptions!$F$6 | G3: ="Y"&Assumptions!$G$6 | H3: ="Y"&Assumptions!$H$6
A4: Net income | B4: ='P&L'!B22 | C4: ='P&L'!C22 | D4: ='P&L'!D22 | E4: ='P&L'!E22 | F4: ='P&L'!F22 | G4: ='P&L'!G22 | H4: ='P&L'!H22
A5: Add back depreciation | B5: ='P&L'!B16 | C5: ='P&L'!C16 | D5: ='P&L'!D16 | E5: ='P&L'!E16 | F5: ='P&L'!F16 | G5: ='P&L'!G16 | H5: ='P&L'!H16
A6: Less increase in receivables | B6: =-('Balance Sheet'!B5-0) | C6: =-('Balance Sheet'!C5-'Balance Sheet'!B5) | D6: =-('Balance Sheet'!D5-'Balance Sheet'!C5) | E6: =-('Balance Sheet'!E5-'Balance Sheet'!D5) | F6: =-('Balance Sheet'!F5-'Balance Sheet'!E5) | G6: =-('Balance Sheet'!G5-'Balance Sheet'!F5) | H6: =-('Balance Sheet'!H5-'Balance Sheet'!G5)
A7: Add increase in payables | B7: ='Balance Sheet'!B8-0 | C7: ='Balance Sheet'!C8-'Balance Sheet'!B8 | D7: ='Balance Sheet'!D8-'Balance Sheet'!C8 | E7: ='Balance Sheet'!E8-'Balance Sheet'!D8 | F7: ='Balance Sheet'!F8-'Balance Sheet'!E8 | G7: ='Balance Sheet'!G8-'Balance Sheet'!F8 | H7: ='Balance Sheet'!H8-'Balance Sheet'!G8
A8: Cash flow from operations | B8: =SUM(B4:B7) | C8: =SUM(C4:C7) | D8: =SUM(D4:D7) | E8: =SUM(E4:E7) | F8: =SUM(F4:F7) | G8: =SUM(G4:G7) | H8: =SUM(H4:H7)
A9: Capital expenditure (equipment) | B9: =-Headcount!B51 | C9: =-Headcount!C51 | D9: =-Headcount!D51 | E9: =-Headcount!E51 | F9: =-Headcount!F51 | G9: =-Headcount!G51 | H9: =-Headcount!H51
A10: Free cash flow (before financing) | B10: =B8+B9 | C10: =C8+C9 | D10: =D8+D9 | E10: =E8+E9 | F10: =F8+F9 | G10: =G8+G9 | H10: =H8+H9
A11: Seed tranche 1 | B11: =IF(Assumptions!$B$6=Assumptions!$B$22,Assumptions!$B$21,0) | C11: =IF(Assumptions!$C$6=Assumptions!$B$22,Assumptions!$B$21,0) | D11: =IF(Assumptions!$D$6=Assumptions!$B$22,Assumptions!$B$21,0) | E11: =IF(Assumptions!$E$6=Assumptions!$B$22,Assumptions!$B$21,0) | F11: =IF(Assumptions!$F$6=Assumptions!$B$22,Assumptions!$B$21,0) | G11: =IF(Assumptions!$G$6=Assumptions!$B$22,Assumptions!$B$21,0) | H11: =IF(Assumptions!$H$6=Assumptions!$B$22,Assumptions!$B$21,0)
A12: Seed tranche 2 | B12: =IF(Assumptions!$B$6=Assumptions!$B$24,Assumptions!$B$23,0) | C12: =IF(Assumptions!$C$6=Assumptions!$B$24,Assumptions!$B$23,0) | D12: =IF(Assumptions!$D$6=Assumptions!$B$24,Assumptions!$B$23,0) | E12: =IF(Assumptions!$E$6=Assumptions!$B$24,Assumptions!$B$23,0) | F12: =IF(Assumptions!$F$6=Assumptions!$B$24,Assumptions!$B$23,0) | G12: =IF(Assumptions!$G$6=Assumptions!$B$24,Assumptions!$B$23,0) | H12: =IF(Assumptions!$H$6=Assumptions!$B$24,Assumptions!$B$23,0)
A13: Series A | B13: =IF(Assumptions!$B$6=Assumptions!$B$26,Assumptions!$B$25,0) | C13: =IF(Assumptions!$C$6=Assumptions!$B$26,Assumptions!$B$25,0) | D13: =IF(Assumptions!$D$6=Assumptions!$B$26,Assumptions!$B$25,0) | E13: =IF(Assumptions!$E$6=Assumptions!$B$26,Assumptions!$B$25,0) | F13: =IF(Assumptions!$F$6=Assumptions!$B$26,Assumptions!$B$25,0) | G13: =IF(Assumptions!$G$6=Assumptions!$B$26,Assumptions!$B$25,0) | H13: =IF(Assumptions!$H$6=Assumptions!$B$26,Assumptions!$B$25,0)
A14: Cash flow from financing | B14: =SUM(B11:B13) | C14: =SUM(C11:C13) | D14: =SUM(D11:D13) | E14: =SUM(E11:E13) | F14: =SUM(F11:F13) | G14: =SUM(G11:G13) | H14: =SUM(H11:H13)
A15: Net change in cash | B15: =B10+B14 | C15: =C10+C14 | D15: =D10+D14 | E15: =E10+E14 | F15: =F10+F14 | G15: =G10+G14 | H15: =H10+H14
A16: Opening cash | B16: =Assumptions!$B$18 | C16: =B17 | D16: =C17 | E16: =D17 | F16: =E17 | G16: =F17 | H16: =G17
A17: Closing cash | B17: =B16+B15 | C17: =C16+C15 | D17: =D16+D15 | E17: =E16+E15 | F17: =F16+F15 | G17: =G16+G15 | H17: =H16+H15
A18: Average monthly net burn = MAX(0, -free cash flow) / 12 | B18: =MAX(0,-B10)/12 | C18: =MAX(0,-C10)/12 | D18: =MAX(0,-D10)/12 | E18: =MAX(0,-E10)/12 | F18: =MAX(0,-F10)/12 | G18: =MAX(0,-G10)/12 | H18: =MAX(0,-H10)/12
A19: Cumulative free cash flow | B19: =B10 | C19: =B19+C10 | D19: =C19+D10 | E19: =D19+E10 | F19: =E19+F10 | G19: =F19+G10 | H19: =G19+H10
A20: Cumulative free cash flow before the Series A year (0 from that year) | B20: =IF(Assumptions!$B$6<Assumptions!$B$26,B19,0) | C20: =IF(Assumptions!$C$6<Assumptions!$B$26,C19,0) | D20: =IF(Assumptions!$D$6<Assumptions!$B$26,D19,0) | E20: =IF(Assumptions!$E$6<Assumptions!$B$26,E19,0) | F20: =IF(Assumptions!$F$6<Assumptions!$B$26,F19,0) | G20: =IF(Assumptions!$G$6<Assumptions!$B$26,G19,0) | H20: =IF(Assumptions!$H$6<Assumptions!$B$26,H19,0)
A21: Cash if only the seed is raised (both tranches, no Series A) | B21: =Assumptions!$B$18+Assumptions!$B$21+Assumptions!$B$23+B19 | C21: =Assumptions!$B$18+Assumptions!$B$21+Assumptions!$B$23+C19 | D21: =Assumptions!$B$18+Assumptions!$B$21+Assumptions!$B$23+D19 | E21: =Assumptions!$B$18+Assumptions!$B$21+Assumptions!$B$23+E19 | F21: =Assumptions!$B$18+Assumptions!$B$21+Assumptions!$B$23+F19 | G21: =Assumptions!$B$18+Assumptions!$B$21+Assumptions!$B$23+G19 | H21: =Assumptions!$B$18+Assumptions!$B$21+Assumptions!$B$23+H19
A22: Month the seed-only cash runs out (linear within year) | B22: =IF(B21<0,12*(Assumptions!$B$18+Assumptions!$B$21+Assumptions!$B$23)/(Assumptions!$B$18+Assumptions!$B$21+Assumptions!$B$23-B21),"") | C22: =IF(AND(C21<0,B21>=0),12*(Assumptions!$C$6-1)+12*B21/(B21-C21),"") | D22: =IF(AND(D21<0,C21>=0),12*(Assumptions!$D$6-1)+12*C21/(C21-D21),"") | E22: =IF(AND(E21<0,D21>=0),12*(Assumptions!$E$6-1)+12*D21/(D21-E21),"") | F22: =IF(AND(F21<0,E21>=0),12*(Assumptions!$F$6-1)+12*E21/(E21-F21),"") | G22: =IF(AND(G21<0,F21>=0),12*(Assumptions!$G$6-1)+12*F21/(F21-G21),"") | H22: =IF(AND(H21<0,G21>=0),12*(Assumptions!$H$6-1)+12*G21/(G21-H21),"")
A23: Funding requirement ($K)
A24: Seed need = deepest cash point before a mid-year Series A x (1 + buffer) | B24: =MAX(0,-MIN(0,MIN(B20:H20),SUMPRODUCT((Assumptions!$B$6:$H$6<Assumptions!$B$26)*'Cash Flow'!$B$10:$H$10)+0.5*SUMPRODUCT((Assumptions!$B$6:$H$6=Assumptions!$B$26)*'Cash Flow'!$B$10:$H$10)))*(1+Assumptions!$B$20)
A25: Total equity need over 7 years = deepest cumulative free cash flow x (1 + buffer) | B25: =MAX(0,-MIN(B19:H19))*(1+Assumptions!$B$20)
A26: Lowest year-end cash with the planned rounds (must stay above 0) | B26: =MIN(B17:H17)
A27: Seed runway in months from close, without a Series A | B27: =IF(COUNT(B22:H22)=0,"beyond month 84",ROUNDDOWN(SUM(B22:H22),0))
A28: Year-1 average monthly net burn | B28: =B18
A29: Use of seed: years before the Series A year ($K)
A30: Operating expense: Engineering | B30: =SUMPRODUCT((Assumptions!$B$6:$H$6<Assumptions!$B$26)*OpEx!$B$13:$H$13)
A31: Operating expense: Security | B31: =SUMPRODUCT((Assumptions!$B$6:$H$6<Assumptions!$B$26)*OpEx!$B$14:$H$14)
A32: Operating expense: Sales | B32: =SUMPRODUCT((Assumptions!$B$6:$H$6<Assumptions!$B$26)*OpEx!$B$15:$H$15)
A33: Operating expense: Marketing | B33: =SUMPRODUCT((Assumptions!$B$6:$H$6<Assumptions!$B$26)*OpEx!$B$16:$H$16)
A34: Operating expense: G&A | B34: =SUMPRODUCT((Assumptions!$B$6:$H$6<Assumptions!$B$26)*OpEx!$B$17:$H$17)
A35: Cost of revenue (claims operations, hosting, variable) | B35: =SUMPRODUCT((Assumptions!$B$6:$H$6<Assumptions!$B$26)*OpEx!$B$24:$H$24)
A36: Equipment capex | B36: =-SUMPRODUCT((Assumptions!$B$6:$H$6<Assumptions!$B$26)*'Cash Flow'!$B$9:$H$9)
A37: Working capital (receivables build less payables) | B37: =-(SUMPRODUCT((Assumptions!$B$6:$H$6<Assumptions!$B$26)*'Cash Flow'!$B$6:$H$6)+SUMPRODUCT((Assumptions!$B$6:$H$6<Assumptions!$B$26)*'Cash Flow'!$B$7:$H$7))
A38: Income tax | B38: =SUMPRODUCT((Assumptions!$B$6:$H$6<Assumptions!$B$26)*'P&L'!$B$21:$H$21)
A39: Gross uses | B39: =SUM(B30:B38)
A40: Less revenue earned in the period | B40: =-SUMPRODUCT((Assumptions!$B$6:$H$6<Assumptions!$B$26)*'P&L'!$B$4:$H$4)
A41: Less interest income | B41: =-SUMPRODUCT((Assumptions!$B$6:$H$6<Assumptions!$B$26)*'P&L'!$B$18:$H$18)
A42: Net use of cash before the Series A year | B42: =SUM(B39:B41)
A43: Seed raised (both tranches) | B43: =Assumptions!$B$21+Assumptions!$B$23
A44: Seed remaining at the start of the Series A year | B44: =B43+Assumptions!$B$18-B42
A45: Seed investor ownership at the assumed pre-money (both tranches at one price, before option pool) | B45: =(Assumptions!$B$21+Assumptions!$B$23)/(Assumptions!$B$27+Assumptions!$B$21+Assumptions!$B$23)

Sheet Balance Sheet
A1: Balance sheet at year end (active scenario)
A2: Asset-light: scoup.ai never holds customer funds. The check row must be zero.
A3: $K unless stated | B3: ="Y"&Assumptions!$B$6 | C3: ="Y"&Assumptions!$C$6 | D3: ="Y"&Assumptions!$D$6 | E3: ="Y"&Assumptions!$E$6 | F3: ="Y"&Assumptions!$F$6 | G3: ="Y"&Assumptions!$G$6 | H3: ="Y"&Assumptions!$H$6
A4: Cash | B4: ='Cash Flow'!B17 | C4: ='Cash Flow'!C17 | D4: ='Cash Flow'!D17 | E4: ='Cash Flow'!E17 | F4: ='Cash Flow'!F17 | G4: ='Cash Flow'!G17 | H4: ='Cash Flow'!H17
A5: Accounts receivable = revenue x DSO / 365 | B5: ='P&L'!B4*Assumptions!$B$13/365 | C5: ='P&L'!C4*Assumptions!$B$13/365 | D5: ='P&L'!D4*Assumptions!$B$13/365 | E5: ='P&L'!E4*Assumptions!$B$13/365 | F5: ='P&L'!F4*Assumptions!$B$13/365 | G5: ='P&L'!G4*Assumptions!$B$13/365 | H5: ='P&L'!H4*Assumptions!$B$13/365
A6: Equipment, net | B6: =Headcount!B51-'P&L'!B16 | C6: =B6+Headcount!C51-'P&L'!C16 | D6: =C6+Headcount!D51-'P&L'!D16 | E6: =D6+Headcount!E51-'P&L'!E16 | F6: =E6+Headcount!F51-'P&L'!F16 | G6: =F6+Headcount!G51-'P&L'!G16 | H6: =G6+Headcount!H51-'P&L'!H16
A7: Total assets | B7: =SUM(B4:B6) | C7: =SUM(C4:C6) | D7: =SUM(D4:D6) | E7: =SUM(E4:E6) | F7: =SUM(F4:F6) | G7: =SUM(G4:G6) | H7: =SUM(H4:H6)
A8: Accounts payable = non-payroll costs x DPO / 365 | B8: =(OpEx!B22+OpEx!B23+OpEx!B6+OpEx!B7+OpEx!B8+OpEx!B9+OpEx!B10+OpEx!B11)*Assumptions!$B$14/365 | C8: =(OpEx!C22+OpEx!C23+OpEx!C6+OpEx!C7+OpEx!C8+OpEx!C9+OpEx!C10+OpEx!C11)*Assumptions!$B$14/365 | D8: =(OpEx!D22+OpEx!D23+OpEx!D6+OpEx!D7+OpEx!D8+OpEx!D9+OpEx!D10+OpEx!D11)*Assumptions!$B$14/365 | E8: =(OpEx!E22+OpEx!E23+OpEx!E6+OpEx!E7+OpEx!E8+OpEx!E9+OpEx!E10+OpEx!E11)*Assumptions!$B$14/365 | F8: =(OpEx!F22+OpEx!F23+OpEx!F6+OpEx!F7+OpEx!F8+OpEx!F9+OpEx!F10+OpEx!F11)*Assumptions!$B$14/365 | G8: =(OpEx!G22+OpEx!G23+OpEx!G6+OpEx!G7+OpEx!G8+OpEx!G9+OpEx!G10+OpEx!G11)*Assumptions!$B$14/365 | H8: =(OpEx!H22+OpEx!H23+OpEx!H6+OpEx!H7+OpEx!H8+OpEx!H9+OpEx!H10+OpEx!H11)*Assumptions!$B$14/365
A9: Total liabilities | B9: =B8 | C9: =C8 | D9: =D8 | E9: =E8 | F9: =F8 | G9: =G8 | H9: =H8
A10: Paid-in capital | B10: =Assumptions!$B$18+'Cash Flow'!B14 | C10: =B10+'Cash Flow'!C14 | D10: =C10+'Cash Flow'!D14 | E10: =D10+'Cash Flow'!E14 | F10: =E10+'Cash Flow'!F14 | G10: =F10+'Cash Flow'!G14 | H10: =G10+'Cash Flow'!H14
A11: Retained earnings (accumulated deficit) | B11: ='P&L'!B22 | C11: =B11+'P&L'!C22 | D11: =C11+'P&L'!D22 | E11: =D11+'P&L'!E22 | F11: =E11+'P&L'!F22 | G11: =F11+'P&L'!G22 | H11: =G11+'P&L'!H22
A12: Total equity | B12: =B10+B11 | C12: =C10+C11 | D12: =D10+D11 | E12: =E10+E11 | F12: =F10+F11 | G12: =G10+G11 | H12: =H10+H11
A13: Total liabilities and equity | B13: =B9+B12 | C13: =C9+C12 | D13: =D9+D12 | E13: =E9+E12 | F13: =F9+F12 | G13: =G9+G12 | H13: =H9+H12
A14: Check: assets minus liabilities and equity (must be 0) | B14: =ROUND(B7-B13,6) | C14: =ROUND(C7-C13,6) | D14: =ROUND(D7-D13,6) | E14: =ROUND(E7-E13,6) | F14: =ROUND(F7-F13,6) | G14: =ROUND(G7-G13,6) | H14: =ROUND(H7-H13,6)

Sheet Unit Economics
A1: Unit economics (active scenario)
A2: Direct segments (shippers + SME importers): CAC = sales and marketing cost excluding partner commission / new direct accounts. Carriers: CAC = partner commission / new carrier accounts. LTV = revenue per account x gross margin / churn (undiscounted). Company gross margin is negative in early years, so read years 3-7.
A3: $K unless stated | B3: ="Y"&Assumptions!$B$6 | C3: ="Y"&Assumptions!$C$6 | D3: ="Y"&Assumptions!$D$6 | E3: ="Y"&Assumptions!$E$6 | F3: ="Y"&Assumptions!$F$6 | G3: ="Y"&Assumptions!$G$6 | H3: ="Y"&Assumptions!$H$6
A4: New direct accounts won (shippers + SME importers) | B4: =Revenue!B5+Revenue!B12 | C4: =Revenue!C5+Revenue!C12 | D4: =Revenue!D5+Revenue!D12 | E4: =Revenue!E5+Revenue!E12 | F4: =Revenue!F5+Revenue!F12 | G4: =Revenue!G5+Revenue!G12 | H4: =Revenue!H5+Revenue!H12
A5: Sales and marketing cost excluding partner commission ($K) | B5: =OpEx!B19-OpEx!B11 | C5: =OpEx!C19-OpEx!C11 | D5: =OpEx!D19-OpEx!D11 | E5: =OpEx!E19-OpEx!E11 | F5: =OpEx!F19-OpEx!F11 | G5: =OpEx!G19-OpEx!G11 | H5: =OpEx!H19-OpEx!H11
A6: CAC per new account = S&M / new accounts ($K) | B6: =IF(B4=0,0,B5/B4) | C6: =IF(C4=0,0,C5/C4) | D6: =IF(D4=0,0,D5/D4) | E6: =IF(E4=0,0,E5/E4) | F6: =IF(F4=0,0,F5/F4) | G6: =IF(G4=0,0,G5/G4) | H6: =IF(H4=0,0,H5/H4)
A7: Revenue per direct account = (shipper + importer ARR) / their accounts ($K) | B7: =IF(Revenue!B7+Revenue!B14=0,0,(Revenue!B11+Revenue!B18)/(Revenue!B7+Revenue!B14)) | C7: =IF(Revenue!C7+Revenue!C14=0,0,(Revenue!C11+Revenue!C18)/(Revenue!C7+Revenue!C14)) | D7: =IF(Revenue!D7+Revenue!D14=0,0,(Revenue!D11+Revenue!D18)/(Revenue!D7+Revenue!D14)) | E7: =IF(Revenue!E7+Revenue!E14=0,0,(Revenue!E11+Revenue!E18)/(Revenue!E7+Revenue!E14)) | F7: =IF(Revenue!F7+Revenue!F14=0,0,(Revenue!F11+Revenue!F18)/(Revenue!F7+Revenue!F14)) | G7: =IF(Revenue!G7+Revenue!G14=0,0,(Revenue!G11+Revenue!G18)/(Revenue!G7+Revenue!G14)) | H7: =IF(Revenue!H7+Revenue!H14=0,0,(Revenue!H11+Revenue!H18)/(Revenue!H7+Revenue!H14))
A8: Gross margin (company level) | B8: ='P&L'!B7 | C8: ='P&L'!C7 | D8: ='P&L'!D7 | E8: ='P&L'!E7 | F8: ='P&L'!F7 | G8: ='P&L'!G7 | H8: ='P&L'!H7
A9: Gross profit per account per year = revenue per account x gross margin ($K) | B9: =B7*B8 | C9: =C7*C8 | D9: =D7*D8 | E9: =E7*E8 | F9: =F7*F8 | G9: =G7*G8 | H9: =H7*H8
A10: Expected account lifetime (years) = 1 / churn | B10: =1/Assumptions!$E$45 | C10: =1/Assumptions!$E$45 | D10: =1/Assumptions!$E$45 | E10: =1/Assumptions!$E$45 | F10: =1/Assumptions!$E$45 | G10: =1/Assumptions!$E$45 | H10: =1/Assumptions!$E$45
A11: LTV = gross profit per account / churn ($K) | B11: =B9*B10 | C11: =C9*C10 | D11: =D9*D10 | E11: =E9*E10 | F11: =F9*F10 | G11: =G9*G10 | H11: =H9*H10
A12: LTV : CAC | B12: =IF(OR(B6<=0,B11<=0),"n/m",B11/B6) | C12: =IF(OR(C6<=0,C11<=0),"n/m",C11/C6) | D12: =IF(OR(D6<=0,D11<=0),"n/m",D11/D6) | E12: =IF(OR(E6<=0,E11<=0),"n/m",E11/E6) | F12: =IF(OR(F6<=0,F11<=0),"n/m",F11/F6) | G12: =IF(OR(G6<=0,G11<=0),"n/m",G11/G6) | H12: =IF(OR(H6<=0,H11<=0),"n/m",H11/H6)
A13: CAC payback = CAC / (gross profit per account / 12), months | B13: =IF(B9<=0,"n/m",B6/(B9/12)) | C13: =IF(C9<=0,"n/m",C6/(C9/12)) | D13: =IF(D9<=0,"n/m",D6/(D9/12)) | E13: =IF(E9<=0,"n/m",E6/(E9/12)) | F13: =IF(F9<=0,"n/m",F6/(F9/12)) | G13: =IF(G9<=0,"n/m",G6/(G9/12)) | H13: =IF(H9<=0,"n/m",H6/(H9/12))
A14: Net revenue retention | B14: =Revenue!B36 | C14: =Revenue!C36 | D14: =Revenue!D36 | E14: =Revenue!E36 | F14: =Revenue!F36 | G14: =Revenue!G36 | H14: =Revenue!H36
A15: S&M per $1 of new ARR = S&M / (new accounts x revenue per account) | B15: =IF(B4=0,0,B5/(B4*B7)) | C15: =IF(C4=0,0,C5/(C4*C7)) | D15: =IF(D4=0,0,D5/(D4*D7)) | E15: =IF(E4=0,0,E5/(E4*E7)) | F15: =IF(F4=0,0,F5/(F4*F7)) | G15: =IF(G4=0,0,G5/(G4*G7)) | H15: =IF(H4=0,0,H5/(H4*H7))
A16: CAC at the $2.00 benchmark = 2.00 x revenue per account ($K) | B16: =Assumptions!$B$28*B7 | C16: =Assumptions!$B$28*C7 | D16: =Assumptions!$B$28*D7 | E16: =Assumptions!$B$28*E7 | F16: =Assumptions!$B$28*F7 | G16: =Assumptions!$B$28*G7 | H16: =Assumptions!$B$28*H7
A17: LTV : CAC at the benchmark CAC | B17: =IF(B11<=0,"n/m",B11/B16) | C17: =IF(C11<=0,"n/m",C11/C16) | D17: =IF(D11<=0,"n/m",D11/D16) | E17: =IF(E11<=0,"n/m",E11/E16) | F17: =IF(F11<=0,"n/m",F11/F16) | G17: =IF(G11<=0,"n/m",G11/G16) | H17: =IF(H11<=0,"n/m",H11/H16)
A18: CAC payback at the benchmark CAC, months | B18: =IF(B9<=0,"n/m",B16/(B9/12)) | C18: =IF(C9<=0,"n/m",C16/(C9/12)) | D18: =IF(D9<=0,"n/m",D16/(D9/12)) | E18: =IF(E9<=0,"n/m",E16/(E9/12)) | F18: =IF(F9<=0,"n/m",F16/(F9/12)) | G18: =IF(G9<=0,"n/m",G16/(G9/12)) | H18: =IF(H9<=0,"n/m",H16/(H9/12))
A19: Carriers (partner-led segment)
A20: New carrier accounts | B20: =Revenue!B19 | C20: =Revenue!C19 | D20: =Revenue!D19 | E20: =Revenue!E19 | F20: =Revenue!F19 | G20: =Revenue!G19 | H20: =Revenue!H19
A21: Carrier CAC = partner commission / new carrier accounts ($K) | B21: =IF(B20=0,0,OpEx!B11/B20) | C21: =IF(C20=0,0,OpEx!C11/C20) | D21: =IF(D20=0,0,OpEx!D11/D20) | E21: =IF(E20=0,0,OpEx!E11/E20) | F21: =IF(F20=0,0,OpEx!F11/F20) | G21: =IF(G20=0,0,OpEx!G11/G20) | H21: =IF(H20=0,0,OpEx!H11/H20)
A22: Carrier revenue per account ($K) | B22: =Revenue!B23 | C22: =Revenue!C23 | D22: =Revenue!D23 | E22: =Revenue!E23 | F22: =Revenue!F23 | G22: =Revenue!G23 | H22: =Revenue!H23
A23: Carrier LTV = revenue per account x gross margin / churn ($K) | B23: =B22*B8/Assumptions!$E$45 | C23: =C22*C8/Assumptions!$E$45 | D23: =D22*D8/Assumptions!$E$45 | E23: =E22*E8/Assumptions!$E$45 | F23: =F22*F8/Assumptions!$E$45 | G23: =G22*G8/Assumptions!$E$45 | H23: =H22*H8/Assumptions!$E$45
A24: Pessimistic acquisition cost (direct segments)
A25: Pessimistic CAC: paid-media cost per small-company customer ($K, Metadata 2026) | B25: =Assumptions!$B$33 | C25: =Assumptions!$B$33 | D25: =Assumptions!$B$33 | E25: =Assumptions!$B$33 | F25: =Assumptions!$B$33 | G25: =Assumptions!$B$33 | H25: =Assumptions!$B$33
A26: LTV : CAC at the pessimistic CAC | B26: =IF(B11<=0,"n/m",B11/B25) | C26: =IF(C11<=0,"n/m",C11/C25) | D26: =IF(D11<=0,"n/m",D11/D25) | E26: =IF(E11<=0,"n/m",E11/E25) | F26: =IF(F11<=0,"n/m",F11/F25) | G26: =IF(G11<=0,"n/m",G11/G25) | H26: =IF(H11<=0,"n/m",H11/H25)
A27: CAC payback at the pessimistic CAC, months | B27: =IF(B9<=0,"n/m",B25/(B9/12)) | C27: =IF(C9<=0,"n/m",C25/(C9/12)) | D27: =IF(D9<=0,"n/m",D25/(D9/12)) | E27: =IF(E9<=0,"n/m",E25/(E9/12)) | F27: =IF(F9<=0,"n/m",F25/(F9/12)) | G27: =IF(G9<=0,"n/m",G25/(G9/12)) | H27: =IF(H9<=0,"n/m",H25/(H9/12))

Sheet Scenarios
A1: Scenarios: Base, Bull and Bear computed side by side ($K)
A2: Same logic as the main tabs, run once per scenario column of Assumptions. The scenarios differ only in the inputs listed under Scenario inputs on Assumptions. Check rows at the bottom compare the active scenario with the main tabs.
A4: Base case | B4: ="Y"&Assumptions!$B$6 | C4: ="Y"&Assumptions!$C$6 | D4: ="Y"&Assumptions!$D$6 | E4: ="Y"&Assumptions!$E$6 | F4: ="Y"&Assumptions!$F$6 | G4: ="Y"&Assumptions!$G$6 | H4: ="Y"&Assumptions!$H$6
A5: Shippers (mid-market): new accounts | B5: =ROUND(Assumptions!$B$52*Assumptions!$B$39,0) | C5: =ROUND(Assumptions!$C$52*Assumptions!$B$39,0) | D5: =ROUND(Assumptions!$D$52*Assumptions!$B$39,0) | E5: =ROUND(Assumptions!$E$52*Assumptions!$B$39,0) | F5: =ROUND(Assumptions!$F$52*Assumptions!$B$39,0) | G5: =ROUND(Assumptions!$G$52*Assumptions!$B$39,0) | H5: =ROUND(Assumptions!$H$52*Assumptions!$B$39,0)
A6: Shippers (mid-market): accounts lost = ROUND(prior year-end x churn) | B6: =0 | C6: =ROUND(B7*Assumptions!$B$45,0) | D6: =ROUND(C7*Assumptions!$B$45,0) | E6: =ROUND(D7*Assumptions!$B$45,0) | F6: =ROUND(E7*Assumptions!$B$45,0) | G6: =ROUND(F7*Assumptions!$B$45,0) | H6: =ROUND(G7*Assumptions!$B$45,0)
A7: Shippers (mid-market): accounts at year end | B7: =B5 | C7: =B7-C6+C5 | D7: =C7-D6+D5 | E7: =D7-E6+E5 | F7: =E7-F6+F5 | G7: =F7-G6+G5 | H7: =G7-H6+H5
A8: Shippers (mid-market): average accounts | B8: =B7/2 | C8: =(B7+C7)/2 | D8: =(C7+D7)/2 | E8: =(D7+E7)/2 | F8: =(E7+F7)/2 | G8: =(F7+G7)/2 | H8: =(G7+H7)/2
A9: Shippers (mid-market): revenue per account ($K) | B9: =(Assumptions!$B$35+Assumptions!$B$36*Assumptions!$B$40*Assumptions!$B$37)*Assumptions!$B$46 | C9: =(Assumptions!$C$35+Assumptions!$C$36*Assumptions!$B$40*Assumptions!$C$37)*Assumptions!$B$46 | D9: =(Assumptions!$D$35+Assumptions!$D$36*Assumptions!$B$40*Assumptions!$D$37)*Assumptions!$B$46 | E9: =(Assumptions!$E$35+Assumptions!$E$36*Assumptions!$B$40*Assumptions!$E$37)*Assumptions!$B$46 | F9: =(Assumptions!$F$35+Assumptions!$F$36*Assumptions!$B$40*Assumptions!$F$37)*Assumptions!$B$46 | G9: =(Assumptions!$G$35+Assumptions!$G$36*Assumptions!$B$40*Assumptions!$G$37)*Assumptions!$B$46 | H9: =(Assumptions!$H$35+Assumptions!$H$36*Assumptions!$B$40*Assumptions!$H$37)*Assumptions!$B$46
A10: Shippers (mid-market): revenue | B10: =B8*B9 | C10: =C8*C9 | D10: =D8*D9 | E10: =E8*E9 | F10: =F8*F9 | G10: =G8*G9 | H10: =H8*H9
A11: Shippers (mid-market): ARR at year end | B11: =B7*B9 | C11: =C7*C9 | D11: =D7*D9 | E11: =E7*E9 | F11: =F7*F9 | G11: =G7*G9 | H11: =H7*H9
A12: SME importers: new accounts | B12: =Assumptions!$B$52-ROUND(Assumptions!$B$52*Assumptions!$B$39,0) | C12: =Assumptions!$C$52-ROUND(Assumptions!$C$52*Assumptions!$B$39,0) | D12: =Assumptions!$D$52-ROUND(Assumptions!$D$52*Assumptions!$B$39,0) | E12: =Assumptions!$E$52-ROUND(Assumptions!$E$52*Assumptions!$B$39,0) | F12: =Assumptions!$F$52-ROUND(Assumptions!$F$52*Assumptions!$B$39,0) | G12: =Assumptions!$G$52-ROUND(Assumptions!$G$52*Assumptions!$B$39,0) | H12: =Assumptions!$H$52-ROUND(Assumptions!$H$52*Assumptions!$B$39,0)
A13: SME importers: accounts lost = ROUND(prior year-end x churn) | B13: =0 | C13: =ROUND(B14*Assumptions!$B$45,0) | D13: =ROUND(C14*Assumptions!$B$45,0) | E13: =ROUND(D14*Assumptions!$B$45,0) | F13: =ROUND(E14*Assumptions!$B$45,0) | G13: =ROUND(F14*Assumptions!$B$45,0) | H13: =ROUND(G14*Assumptions!$B$45,0)
A14: SME importers: accounts at year end | B14: =B12 | C14: =B14-C13+C12 | D14: =C14-D13+D12 | E14: =D14-E13+E12 | F14: =E14-F13+F12 | G14: =F14-G13+G12 | H14: =G14-H13+H12
A15: SME importers: average accounts | B15: =B14/2 | C15: =(B14+C14)/2 | D15: =(C14+D14)/2 | E15: =(D14+E14)/2 | F15: =(E14+F14)/2 | G15: =(F14+G14)/2 | H15: =(G14+H14)/2
A16: SME importers: revenue per account ($K) | B16: =(Assumptions!$B$35+Assumptions!$B$36*Assumptions!$B$37)*Assumptions!$B$46 | C16: =(Assumptions!$C$35+Assumptions!$C$36*Assumptions!$C$37)*Assumptions!$B$46 | D16: =(Assumptions!$D$35+Assumptions!$D$36*Assumptions!$D$37)*Assumptions!$B$46 | E16: =(Assumptions!$E$35+Assumptions!$E$36*Assumptions!$E$37)*Assumptions!$B$46 | F16: =(Assumptions!$F$35+Assumptions!$F$36*Assumptions!$F$37)*Assumptions!$B$46 | G16: =(Assumptions!$G$35+Assumptions!$G$36*Assumptions!$G$37)*Assumptions!$B$46 | H16: =(Assumptions!$H$35+Assumptions!$H$36*Assumptions!$H$37)*Assumptions!$B$46
A17: SME importers: revenue | B17: =B15*B16 | C17: =C15*C16 | D17: =D15*D16 | E17: =E15*E16 | F17: =F15*F16 | G17: =G15*G16 | H17: =H15*H16
A18: SME importers: ARR at year end | B18: =B14*B16 | C18: =C14*C16 | D18: =D14*D16 | E18: =E14*E16 | F18: =F14*F16 | G18: =G14*G16 | H18: =H14*H16
A19: Carriers (partner-led): new accounts | B19: =Assumptions!$B$56 | C19: =Assumptions!$C$56 | D19: =Assumptions!$D$56 | E19: =Assumptions!$E$56 | F19: =Assumptions!$F$56 | G19: =Assumptions!$G$56 | H19: =Assumptions!$H$56
A20: Carriers (partner-led): accounts lost = ROUND(prior year-end x churn) | B20: =0 | C20: =ROUND(B21*Assumptions!$B$45,0) | D20: =ROUND(C21*Assumptions!$B$45,0) | E20: =ROUND(D21*Assumptions!$B$45,0) | F20: =ROUND(E21*Assumptions!$B$45,0) | G20: =ROUND(F21*Assumptions!$B$45,0) | H20: =ROUND(G21*Assumptions!$B$45,0)
A21: Carriers (partner-led): accounts at year end | B21: =B19 | C21: =B21-C20+C19 | D21: =C21-D20+D19 | E21: =D21-E20+E19 | F21: =E21-F20+F19 | G21: =F21-G20+G19 | H21: =G21-H20+H19
A22: Carriers (partner-led): average accounts | B22: =B21/2 | C22: =(B21+C21)/2 | D22: =(C21+D21)/2 | E22: =(D21+E21)/2 | F22: =(E21+F21)/2 | G22: =(F21+G21)/2 | H22: =(G21+H21)/2
A23: Carriers (partner-led): revenue per account ($K) | B23: =Assumptions!$B$41*Assumptions!$B$42*Assumptions!$B$46 | C23: =Assumptions!$C$41*Assumptions!$B$42*Assumptions!$B$46 | D23: =Assumptions!$D$41*Assumptions!$B$42*Assumptions!$B$46 | E23: =Assumptions!$E$41*Assumptions!$B$42*Assumptions!$B$46 | F23: =Assumptions!$F$41*Assumptions!$B$42*Assumptions!$B$46 | G23: =Assumptions!$G$41*Assumptions!$B$42*Assumptions!$B$46 | H23: =Assumptions!$H$41*Assumptions!$B$42*Assumptions!$B$46
A24: Carriers (partner-led): revenue | B24: =B22*B23 | C24: =C22*C23 | D24: =D22*D23 | E24: =E22*E23 | F24: =F22*F23 | G24: =G22*G23 | H24: =H22*H23
A25: Carriers (partner-led): ARR at year end | B25: =B21*B23 | C25: =C21*C23 | D25: =D21*D23 | E25: =E21*E23 | F25: =F21*F23 | G25: =G21*G23 | H25: =H21*H23
A26: All segments: new accounts won | B26: =B5+B12+B19 | C26: =C5+C12+C19 | D26: =D5+D12+D19 | E26: =E5+E12+E19 | F26: =F5+F12+F19 | G26: =G5+G12+G19 | H26: =H5+H12+H19
A27: All segments: accounts lost | B27: =B6+B13+B20 | C27: =C6+C13+C20 | D27: =D6+D13+D20 | E27: =E6+E13+E20 | F27: =F6+F13+F20 | G27: =G6+G13+G20 | H27: =H6+H13+H20
A28: All segments: paying accounts at year end | B28: =B7+B14+B21 | C28: =C7+C14+C21 | D28: =D7+D14+D21 | E28: =E7+E14+E21 | F28: =F7+F14+F21 | G28: =G7+G14+G21 | H28: =H7+H14+H21
A29: All segments: average paying accounts | B29: =B8+B15+B22 | C29: =C8+C15+C22 | D29: =D8+D15+D22 | E29: =E8+E15+E22 | F29: =F8+F15+F22 | G29: =G8+G15+G22 | H29: =H8+H15+H22
A30: Total revenue | B30: =B10+B17+B24 | C30: =C10+C17+C24 | D30: =D10+D17+D24 | E30: =E10+E17+E24 | F30: =F10+F17+F24 | G30: =G10+G17+G24 | H30: =H10+H17+H24
A31: ARR at year end | B31: =B11+B18+B25 | C31: =C11+C18+C25 | D31: =D11+D18+D25 | E31: =E11+E18+E25 | F31: =F11+F18+F25 | G31: =G11+G18+G25 | H31: =H11+H18+H25
A32: Blended revenue per account = ARR / accounts ($K) | B32: =IF(B28=0,0,B31/B28) | C32: =IF(C28=0,0,C31/C28) | D32: =IF(D28=0,0,D31/D28) | E32: =IF(E28=0,0,E31/E28) | F32: =IF(F28=0,0,F31/F28) | G32: =IF(G28=0,0,G31/G28) | H32: =IF(H28=0,0,H31/H28)
A33: Founder / CEO | B33: =Assumptions!$B$61 | C33: =IF(AND(Assumptions!$B$48>0,Assumptions!$C$6>=Assumptions!$B$48,Assumptions!$C$6<Assumptions!$B$48+Assumptions!$B$49),B33,Assumptions!$C$61) | D33: =IF(AND(Assumptions!$B$48>0,Assumptions!$D$6>=Assumptions!$B$48,Assumptions!$D$6<Assumptions!$B$48+Assumptions!$B$49),C33,Assumptions!$D$61) | E33: =IF(AND(Assumptions!$B$48>0,Assumptions!$E$6>=Assumptions!$B$48,Assumptions!$E$6<Assumptions!$B$48+Assumptions!$B$49),D33,Assumptions!$E$61) | F33: =IF(AND(Assumptions!$B$48>0,Assumptions!$F$6>=Assumptions!$B$48,Assumptions!$F$6<Assumptions!$B$48+Assumptions!$B$49),E33,Assumptions!$F$61) | G33: =IF(AND(Assumptions!$B$48>0,Assumptions!$G$6>=Assumptions!$B$48,Assumptions!$G$6<Assumptions!$B$48+Assumptions!$B$49),F33,Assumptions!$G$61) | H33: =IF(AND(Assumptions!$B$48>0,Assumptions!$H$6>=Assumptions!$B$48,Assumptions!$H$6<Assumptions!$B$48+Assumptions!$B$49),G33,Assumptions!$H$61)
A34: Software engineers | B34: =ROUND(Assumptions!$B$65*Assumptions!$B$47,0) | C34: =IF(AND(Assumptions!$B$48>0,Assumptions!$C$6>=Assumptions!$B$48,Assumptions!$C$6<Assumptions!$B$48+Assumptions!$B$49),B34,ROUND(Assumptions!$C$65*Assumptions!$B$47,0)) | D34: =IF(AND(Assumptions!$B$48>0,Assumptions!$D$6>=Assumptions!$B$48,Assumptions!$D$6<Assumptions!$B$48+Assumptions!$B$49),C34,ROUND(Assumptions!$D$65*Assumptions!$B$47,0)) | E34: =IF(AND(Assumptions!$B$48>0,Assumptions!$E$6>=Assumptions!$B$48,Assumptions!$E$6<Assumptions!$B$48+Assumptions!$B$49),D34,ROUND(Assumptions!$E$65*Assumptions!$B$47,0)) | F34: =IF(AND(Assumptions!$B$48>0,Assumptions!$F$6>=Assumptions!$B$48,Assumptions!$F$6<Assumptions!$B$48+Assumptions!$B$49),E34,ROUND(Assumptions!$F$65*Assumptions!$B$47,0)) | G34: =IF(AND(Assumptions!$B$48>0,Assumptions!$G$6>=Assumptions!$B$48,Assumptions!$G$6<Assumptions!$B$48+Assumptions!$B$49),F34,ROUND(Assumptions!$G$65*Assumptions!$B$47,0)) | H34: =IF(AND(Assumptions!$B$48>0,Assumptions!$H$6>=Assumptions!$B$48,Assumptions!$H$6<Assumptions!$B$48+Assumptions!$B$49),G34,ROUND(Assumptions!$H$65*Assumptions!$B$47,0))
A35: ML / data engineers | B35: =ROUND(Assumptions!$B$69*Assumptions!$B$47,0) | C35: =IF(AND(Assumptions!$B$48>0,Assumptions!$C$6>=Assumptions!$B$48,Assumptions!$C$6<Assumptions!$B$48+Assumptions!$B$49),B35,ROUND(Assumptions!$C$69*Assumptions!$B$47,0)) | D35: =IF(AND(Assumptions!$B$48>0,Assumptions!$D$6>=Assumptions!$B$48,Assumptions!$D$6<Assumptions!$B$48+Assumptions!$B$49),C35,ROUND(Assumptions!$D$69*Assumptions!$B$47,0)) | E35: =IF(AND(Assumptions!$B$48>0,Assumptions!$E$6>=Assumptions!$B$48,Assumptions!$E$6<Assumptions!$B$48+Assumptions!$B$49),D35,ROUND(Assumptions!$E$69*Assumptions!$B$47,0)) | F35: =IF(AND(Assumptions!$B$48>0,Assumptions!$F$6>=Assumptions!$B$48,Assumptions!$F$6<Assumptions!$B$48+Assumptions!$B$49),E35,ROUND(Assumptions!$F$69*Assumptions!$B$47,0)) | G35: =IF(AND(Assumptions!$B$48>0,Assumptions!$G$6>=Assumptions!$B$48,Assumptions!$G$6<Assumptions!$B$48+Assumptions!$B$49),F35,ROUND(Assumptions!$G$69*Assumptions!$B$47,0)) | H35: =IF(AND(Assumptions!$B$48>0,Assumptions!$H$6>=Assumptions!$B$48,Assumptions!$H$6<Assumptions!$B$48+Assumptions!$B$49),G35,ROUND(Assumptions!$H$69*Assumptions!$B$47,0))
A36: Security engineer | B36: =ROUND(Assumptions!$B$73*Assumptions!$B$47,0) | C36: =IF(AND(Assumptions!$B$48>0,Assumptions!$C$6>=Assumptions!$B$48,Assumptions!$C$6<Assumptions!$B$48+Assumptions!$B$49),B36,ROUND(Assumptions!$C$73*Assumptions!$B$47,0)) | D36: =IF(AND(Assumptions!$B$48>0,Assumptions!$D$6>=Assumptions!$B$48,Assumptions!$D$6<Assumptions!$B$48+Assumptions!$B$49),C36,ROUND(Assumptions!$D$73*Assumptions!$B$47,0)) | E36: =IF(AND(Assumptions!$B$48>0,Assumptions!$E$6>=Assumptions!$B$48,Assumptions!$E$6<Assumptions!$B$48+Assumptions!$B$49),D36,ROUND(Assumptions!$E$73*Assumptions!$B$47,0)) | F36: =IF(AND(Assumptions!$B$48>0,Assumptions!$F$6>=Assumptions!$B$48,Assumptions!$F$6<Assumptions!$B$48+Assumptions!$B$49),E36,ROUND(Assumptions!$F$73*Assumptions!$B$47,0)) | G36: =IF(AND(Assumptions!$B$48>0,Assumptions!$G$6>=Assumptions!$B$48,Assumptions!$G$6<Assumptions!$B$48+Assumptions!$B$49),F36,ROUND(Assumptions!$G$73*Assumptions!$B$47,0)) | H36: =IF(AND(Assumptions!$B$48>0,Assumptions!$H$6>=Assumptions!$B$48,Assumptions!$H$6<Assumptions!$B$48+Assumptions!$B$49),G36,ROUND(Assumptions!$H$73*Assumptions!$B$47,0))
A37: Account executives (US) | B37: =ROUND(Assumptions!$B$77*Assumptions!$B$47,0) | C37: =IF(AND(Assumptions!$B$48>0,Assumptions!$C$6>=Assumptions!$B$48,Assumptions!$C$6<Assumptions!$B$48+Assumptions!$B$49),B37,ROUND(Assumptions!$C$77*Assumptions!$B$47,0)) | D37: =IF(AND(Assumptions!$B$48>0,Assumptions!$D$6>=Assumptions!$B$48,Assumptions!$D$6<Assumptions!$B$48+Assumptions!$B$49),C37,ROUND(Assumptions!$D$77*Assumptions!$B$47,0)) | E37: =IF(AND(Assumptions!$B$48>0,Assumptions!$E$6>=Assumptions!$B$48,Assumptions!$E$6<Assumptions!$B$48+Assumptions!$B$49),D37,ROUND(Assumptions!$E$77*Assumptions!$B$47,0)) | F37: =IF(AND(Assumptions!$B$48>0,Assumptions!$F$6>=Assumptions!$B$48,Assumptions!$F$6<Assumptions!$B$48+Assumptions!$B$49),E37,ROUND(Assumptions!$F$77*Assumptions!$B$47,0)) | G37: =IF(AND(Assumptions!$B$48>0,Assumptions!$G$6>=Assumptions!$B$48,Assumptions!$G$6<Assumptions!$B$48+Assumptions!$B$49),F37,ROUND(Assumptions!$G$77*Assumptions!$B$47,0)) | H37: =IF(AND(Assumptions!$B$48>0,Assumptions!$H$6>=Assumptions!$B$48,Assumptions!$H$6<Assumptions!$B$48+Assumptions!$B$49),G37,ROUND(Assumptions!$H$77*Assumptions!$B$47,0))
A38: Sales engineer (US) | B38: =ROUND(Assumptions!$B$81*Assumptions!$B$47,0) | C38: =IF(AND(Assumptions!$B$48>0,Assumptions!$C$6>=Assumptions!$B$48,Assumptions!$C$6<Assumptions!$B$48+Assumptions!$B$49),B38,ROUND(Assumptions!$C$81*Assumptions!$B$47,0)) | D38: =IF(AND(Assumptions!$B$48>0,Assumptions!$D$6>=Assumptions!$B$48,Assumptions!$D$6<Assumptions!$B$48+Assumptions!$B$49),C38,ROUND(Assumptions!$D$81*Assumptions!$B$47,0)) | E38: =IF(AND(Assumptions!$B$48>0,Assumptions!$E$6>=Assumptions!$B$48,Assumptions!$E$6<Assumptions!$B$48+Assumptions!$B$49),D38,ROUND(Assumptions!$E$81*Assumptions!$B$47,0)) | F38: =IF(AND(Assumptions!$B$48>0,Assumptions!$F$6>=Assumptions!$B$48,Assumptions!$F$6<Assumptions!$B$48+Assumptions!$B$49),E38,ROUND(Assumptions!$F$81*Assumptions!$B$47,0)) | G38: =IF(AND(Assumptions!$B$48>0,Assumptions!$G$6>=Assumptions!$B$48,Assumptions!$G$6<Assumptions!$B$48+Assumptions!$B$49),F38,ROUND(Assumptions!$G$81*Assumptions!$B$47,0)) | H38: =IF(AND(Assumptions!$B$48>0,Assumptions!$H$6>=Assumptions!$B$48,Assumptions!$H$6<Assumptions!$B$48+Assumptions!$B$49),G38,ROUND(Assumptions!$H$81*Assumptions!$B$47,0))
A39: Claims analysts / customer success (US) | B39: =ROUND(Assumptions!$B$85*Assumptions!$B$47,0) | C39: =IF(AND(Assumptions!$B$48>0,Assumptions!$C$6>=Assumptions!$B$48,Assumptions!$C$6<Assumptions!$B$48+Assumptions!$B$49),B39,ROUND(Assumptions!$C$85*Assumptions!$B$47,0)) | D39: =IF(AND(Assumptions!$B$48>0,Assumptions!$D$6>=Assumptions!$B$48,Assumptions!$D$6<Assumptions!$B$48+Assumptions!$B$49),C39,ROUND(Assumptions!$D$85*Assumptions!$B$47,0)) | E39: =IF(AND(Assumptions!$B$48>0,Assumptions!$E$6>=Assumptions!$B$48,Assumptions!$E$6<Assumptions!$B$48+Assumptions!$B$49),D39,ROUND(Assumptions!$E$85*Assumptions!$B$47,0)) | F39: =IF(AND(Assumptions!$B$48>0,Assumptions!$F$6>=Assumptions!$B$48,Assumptions!$F$6<Assumptions!$B$48+Assumptions!$B$49),E39,ROUND(Assumptions!$F$85*Assumptions!$B$47,0)) | G39: =IF(AND(Assumptions!$B$48>0,Assumptions!$G$6>=Assumptions!$B$48,Assumptions!$G$6<Assumptions!$B$48+Assumptions!$B$49),F39,ROUND(Assumptions!$G$85*Assumptions!$B$47,0)) | H39: =IF(AND(Assumptions!$B$48>0,Assumptions!$H$6>=Assumptions!$B$48,Assumptions!$H$6<Assumptions!$B$48+Assumptions!$B$49),G39,ROUND(Assumptions!$H$85*Assumptions!$B$47,0))
A40: Marketing (US) | B40: =ROUND(Assumptions!$B$89*Assumptions!$B$47,0) | C40: =IF(AND(Assumptions!$B$48>0,Assumptions!$C$6>=Assumptions!$B$48,Assumptions!$C$6<Assumptions!$B$48+Assumptions!$B$49),B40,ROUND(Assumptions!$C$89*Assumptions!$B$47,0)) | D40: =IF(AND(Assumptions!$B$48>0,Assumptions!$D$6>=Assumptions!$B$48,Assumptions!$D$6<Assumptions!$B$48+Assumptions!$B$49),C40,ROUND(Assumptions!$D$89*Assumptions!$B$47,0)) | E40: =IF(AND(Assumptions!$B$48>0,Assumptions!$E$6>=Assumptions!$B$48,Assumptions!$E$6<Assumptions!$B$48+Assumptions!$B$49),D40,ROUND(Assumptions!$E$89*Assumptions!$B$47,0)) | F40: =IF(AND(Assumptions!$B$48>0,Assumptions!$F$6>=Assumptions!$B$48,Assumptions!$F$6<Assumptions!$B$48+Assumptions!$B$49),E40,ROUND(Assumptions!$F$89*Assumptions!$B$47,0)) | G40: =IF(AND(Assumptions!$B$48>0,Assumptions!$G$6>=Assumptions!$B$48,Assumptions!$G$6<Assumptions!$B$48+Assumptions!$B$49),F40,ROUND(Assumptions!$G$89*Assumptions!$B$47,0)) | H40: =IF(AND(Assumptions!$B$48>0,Assumptions!$H$6>=Assumptions!$B$48,Assumptions!$H$6<Assumptions!$B$48+Assumptions!$B$49),G40,ROUND(Assumptions!$H$89*Assumptions!$B$47,0))
A41: Finance, legal operations, people | B41: =ROUND(Assumptions!$B$93*Assumptions!$B$47,0) | C41: =IF(AND(Assumptions!$B$48>0,Assumptions!$C$6>=Assumptions!$B$48,Assumptions!$C$6<Assumptions!$B$48+Assumptions!$B$49),B41,ROUND(Assumptions!$C$93*Assumptions!$B$47,0)) | D41: =IF(AND(Assumptions!$B$48>0,Assumptions!$D$6>=Assumptions!$B$48,Assumptions!$D$6<Assumptions!$B$48+Assumptions!$B$49),C41,ROUND(Assumptions!$D$93*Assumptions!$B$47,0)) | E41: =IF(AND(Assumptions!$B$48>0,Assumptions!$E$6>=Assumptions!$B$48,Assumptions!$E$6<Assumptions!$B$48+Assumptions!$B$49),D41,ROUND(Assumptions!$E$93*Assumptions!$B$47,0)) | F41: =IF(AND(Assumptions!$B$48>0,Assumptions!$F$6>=Assumptions!$B$48,Assumptions!$F$6<Assumptions!$B$48+Assumptions!$B$49),E41,ROUND(Assumptions!$F$93*Assumptions!$B$47,0)) | G41: =IF(AND(Assumptions!$B$48>0,Assumptions!$G$6>=Assumptions!$B$48,Assumptions!$G$6<Assumptions!$B$48+Assumptions!$B$49),F41,ROUND(Assumptions!$G$93*Assumptions!$B$47,0)) | H41: =IF(AND(Assumptions!$B$48>0,Assumptions!$H$6>=Assumptions!$B$48,Assumptions!$H$6<Assumptions!$B$48+Assumptions!$B$49),G41,ROUND(Assumptions!$H$93*Assumptions!$B$47,0))
A42: Headcount at year end | B42: =SUM(B33:B41) | C42: =SUM(C33:C41) | D42: =SUM(D33:D41) | E42: =SUM(E33:E41) | F42: =SUM(F33:F41) | G42: =SUM(G33:G41) | H42: =SUM(H33:H41)
A43: Claims operations people cost | B43: =(B39*(5-Assumptions!$B$87)/4*Assumptions!$B$88)*(1+Assumptions!$B$8)^(Assumptions!$B$6-1) | C43: =((B39+C39)/2*Assumptions!$B$88)*(1+Assumptions!$B$8)^(Assumptions!$C$6-1) | D43: =((C39+D39)/2*Assumptions!$B$88)*(1+Assumptions!$B$8)^(Assumptions!$D$6-1) | E43: =((D39+E39)/2*Assumptions!$B$88)*(1+Assumptions!$B$8)^(Assumptions!$E$6-1) | F43: =((E39+F39)/2*Assumptions!$B$88)*(1+Assumptions!$B$8)^(Assumptions!$F$6-1) | G43: =((F39+G39)/2*Assumptions!$B$88)*(1+Assumptions!$B$8)^(Assumptions!$G$6-1) | H43: =((G39+H39)/2*Assumptions!$B$88)*(1+Assumptions!$B$8)^(Assumptions!$H$6-1)
A44: Other people cost | B44: =(B33*(5-Assumptions!$B$63)/4*Assumptions!$B$64+B34*(5-Assumptions!$B$67)/4*Assumptions!$B$68+B35*(5-Assumptions!$B$71)/4*Assumptions!$B$72+B36*(5-Assumptions!$B$75)/4*Assumptions!$B$76+B37*(5-Assumptions!$B$79)/4*Assumptions!$B$80+B38*(5-Assumptions!$B$83)/4*Assumptions!$B$84+B40*(5-Assumptions!$B$91)/4*Assumptions!$B$92+B41*(5-Assumptions!$B$95)/4*Assumptions!$B$96)*(1+Assumptions!$B$8)^(Assumptions!$B$6-1) | C44: =((B33+C33)/2*Assumptions!$B$64+(B34+C34)/2*Assumptions!$B$68+(B35+C35)/2*Assumptions!$B$72+(B36+C36)/2*Assumptions!$B$76+(B37+C37)/2*Assumptions!$B$80+(B38+C38)/2*Assumptions!$B$84+(B40+C40)/2*Assumptions!$B$92+(B41+C41)/2*Assumptions!$B$96)*(1+Assumptions!$B$8)^(Assumptions!$C$6-1) | D44: =((C33+D33)/2*Assumptions!$B$64+(C34+D34)/2*Assumptions!$B$68+(C35+D35)/2*Assumptions!$B$72+(C36+D36)/2*Assumptions!$B$76+(C37+D37)/2*Assumptions!$B$80+(C38+D38)/2*Assumptions!$B$84+(C40+D40)/2*Assumptions!$B$92+(C41+D41)/2*Assumptions!$B$96)*(1+Assumptions!$B$8)^(Assumptions!$D$6-1) | E44: =((D33+E33)/2*Assumptions!$B$64+(D34+E34)/2*Assumptions!$B$68+(D35+E35)/2*Assumptions!$B$72+(D36+E36)/2*Assumptions!$B$76+(D37+E37)/2*Assumptions!$B$80+(D38+E38)/2*Assumptions!$B$84+(D40+E40)/2*Assumptions!$B$92+(D41+E41)/2*Assumptions!$B$96)*(1+Assumptions!$B$8)^(Assumptions!$E$6-1) | F44: =((E33+F33)/2*Assumptions!$B$64+(E34+F34)/2*Assumptions!$B$68+(E35+F35)/2*Assumptions!$B$72+(E36+F36)/2*Assumptions!$B$76+(E37+F37)/2*Assumptions!$B$80+(E38+F38)/2*Assumptions!$B$84+(E40+F40)/2*Assumptions!$B$92+(E41+F41)/2*Assumptions!$B$96)*(1+Assumptions!$B$8)^(Assumptions!$F$6-1) | G44: =((F33+G33)/2*Assumptions!$B$64+(F34+G34)/2*Assumptions!$B$68+(F35+G35)/2*Assumptions!$B$72+(F36+G36)/2*Assumptions!$B$76+(F37+G37)/2*Assumptions!$B$80+(F38+G38)/2*Assumptions!$B$84+(F40+G40)/2*Assumptions!$B$92+(F41+G41)/2*Assumptions!$B$96)*(1+Assumptions!$B$8)^(Assumptions!$G$6-1) | H44: =((G33+H33)/2*Assumptions!$B$64+(G34+H34)/2*Assumptions!$B$68+(G35+H35)/2*Assumptions!$B$72+(G36+H36)/2*Assumptions!$B$76+(G37+H37)/2*Assumptions!$B$80+(G38+H38)/2*Assumptions!$B$84+(G40+H40)/2*Assumptions!$B$92+(G41+H41)/2*Assumptions!$B$96)*(1+Assumptions!$B$8)^(Assumptions!$H$6-1)
A45: Cloud hosting, data feeds and tooling | B45: =Assumptions!$B$98 | C45: =IF(AND(Assumptions!$B$48>0,Assumptions!$C$6>=Assumptions!$B$48,Assumptions!$C$6<Assumptions!$B$48+Assumptions!$B$49),B45,Assumptions!$C$98*Assumptions!$B$47) | D45: =IF(AND(Assumptions!$B$48>0,Assumptions!$D$6>=Assumptions!$B$48,Assumptions!$D$6<Assumptions!$B$48+Assumptions!$B$49),C45,Assumptions!$D$98*Assumptions!$B$47) | E45: =IF(AND(Assumptions!$B$48>0,Assumptions!$E$6>=Assumptions!$B$48,Assumptions!$E$6<Assumptions!$B$48+Assumptions!$B$49),D45,Assumptions!$E$98*Assumptions!$B$47) | F45: =IF(AND(Assumptions!$B$48>0,Assumptions!$F$6>=Assumptions!$B$48,Assumptions!$F$6<Assumptions!$B$48+Assumptions!$B$49),E45,Assumptions!$F$98*Assumptions!$B$47) | G45: =IF(AND(Assumptions!$B$48>0,Assumptions!$G$6>=Assumptions!$B$48,Assumptions!$G$6<Assumptions!$B$48+Assumptions!$B$49),F45,Assumptions!$G$98*Assumptions!$B$47) | H45: =IF(AND(Assumptions!$B$48>0,Assumptions!$H$6>=Assumptions!$B$48,Assumptions!$H$6<Assumptions!$B$48+Assumptions!$B$49),G45,Assumptions!$H$98*Assumptions!$B$47)
A46: Security programme (SOC 2, pen tests, tooling, insurance) | B46: =Assumptions!$B$99 | C46: =IF(AND(Assumptions!$B$48>0,Assumptions!$C$6>=Assumptions!$B$48,Assumptions!$C$6<Assumptions!$B$48+Assumptions!$B$49),B46,Assumptions!$C$99*Assumptions!$B$47) | D46: =IF(AND(Assumptions!$B$48>0,Assumptions!$D$6>=Assumptions!$B$48,Assumptions!$D$6<Assumptions!$B$48+Assumptions!$B$49),C46,Assumptions!$D$99*Assumptions!$B$47) | E46: =IF(AND(Assumptions!$B$48>0,Assumptions!$E$6>=Assumptions!$B$48,Assumptions!$E$6<Assumptions!$B$48+Assumptions!$B$49),D46,Assumptions!$E$99*Assumptions!$B$47) | F46: =IF(AND(Assumptions!$B$48>0,Assumptions!$F$6>=Assumptions!$B$48,Assumptions!$F$6<Assumptions!$B$48+Assumptions!$B$49),E46,Assumptions!$F$99*Assumptions!$B$47) | G46: =IF(AND(Assumptions!$B$48>0,Assumptions!$G$6>=Assumptions!$B$48,Assumptions!$G$6<Assumptions!$B$48+Assumptions!$B$49),F46,Assumptions!$G$99*Assumptions!$B$47) | H46: =IF(AND(Assumptions!$B$48>0,Assumptions!$H$6>=Assumptions!$B$48,Assumptions!$H$6<Assumptions!$B$48+Assumptions!$B$49),G46,Assumptions!$H$99*Assumptions!$B$47)
A47: Legal and regulatory | B47: =Assumptions!$B$100 | C47: =IF(AND(Assumptions!$B$48>0,Assumptions!$C$6>=Assumptions!$B$48,Assumptions!$C$6<Assumptions!$B$48+Assumptions!$B$49),B47,Assumptions!$C$100*Assumptions!$B$47) | D47: =IF(AND(Assumptions!$B$48>0,Assumptions!$D$6>=Assumptions!$B$48,Assumptions!$D$6<Assumptions!$B$48+Assumptions!$B$49),C47,Assumptions!$D$100*Assumptions!$B$47) | E47: =IF(AND(Assumptions!$B$48>0,Assumptions!$E$6>=Assumptions!$B$48,Assumptions!$E$6<Assumptions!$B$48+Assumptions!$B$49),D47,Assumptions!$E$100*Assumptions!$B$47) | F47: =IF(AND(Assumptions!$B$48>0,Assumptions!$F$6>=Assumptions!$B$48,Assumptions!$F$6<Assumptions!$B$48+Assumptions!$B$49),E47,Assumptions!$F$100*Assumptions!$B$47) | G47: =IF(AND(Assumptions!$B$48>0,Assumptions!$G$6>=Assumptions!$B$48,Assumptions!$G$6<Assumptions!$B$48+Assumptions!$B$49),F47,Assumptions!$G$100*Assumptions!$B$47) | H47: =IF(AND(Assumptions!$B$48>0,Assumptions!$H$6>=Assumptions!$B$48,Assumptions!$H$6<Assumptions!$B$48+Assumptions!$B$49),G47,Assumptions!$H$100*Assumptions!$B$47)
A48: Marketing programmes and events | B48: =Assumptions!$B$101 | C48: =IF(AND(Assumptions!$B$48>0,Assumptions!$C$6>=Assumptions!$B$48,Assumptions!$C$6<Assumptions!$B$48+Assumptions!$B$49),B48,Assumptions!$C$101*Assumptions!$B$47) | D48: =IF(AND(Assumptions!$B$48>0,Assumptions!$D$6>=Assumptions!$B$48,Assumptions!$D$6<Assumptions!$B$48+Assumptions!$B$49),C48,Assumptions!$D$101*Assumptions!$B$47) | E48: =IF(AND(Assumptions!$B$48>0,Assumptions!$E$6>=Assumptions!$B$48,Assumptions!$E$6<Assumptions!$B$48+Assumptions!$B$49),D48,Assumptions!$E$101*Assumptions!$B$47) | F48: =IF(AND(Assumptions!$B$48>0,Assumptions!$F$6>=Assumptions!$B$48,Assumptions!$F$6<Assumptions!$B$48+Assumptions!$B$49),E48,Assumptions!$F$101*Assumptions!$B$47) | G48: =IF(AND(Assumptions!$B$48>0,Assumptions!$G$6>=Assumptions!$B$48,Assumptions!$G$6<Assumptions!$B$48+Assumptions!$B$49),F48,Assumptions!$G$101*Assumptions!$B$47) | H48: =IF(AND(Assumptions!$B$48>0,Assumptions!$H$6>=Assumptions!$B$48,Assumptions!$H$6<Assumptions!$B$48+Assumptions!$B$49),G48,Assumptions!$H$101*Assumptions!$B$47)
A49: Travel and customer visits | B49: =Assumptions!$B$102 | C49: =IF(AND(Assumptions!$B$48>0,Assumptions!$C$6>=Assumptions!$B$48,Assumptions!$C$6<Assumptions!$B$48+Assumptions!$B$49),B49,Assumptions!$C$102*Assumptions!$B$47) | D49: =IF(AND(Assumptions!$B$48>0,Assumptions!$D$6>=Assumptions!$B$48,Assumptions!$D$6<Assumptions!$B$48+Assumptions!$B$49),C49,Assumptions!$D$102*Assumptions!$B$47) | E49: =IF(AND(Assumptions!$B$48>0,Assumptions!$E$6>=Assumptions!$B$48,Assumptions!$E$6<Assumptions!$B$48+Assumptions!$B$49),D49,Assumptions!$E$102*Assumptions!$B$47) | F49: =IF(AND(Assumptions!$B$48>0,Assumptions!$F$6>=Assumptions!$B$48,Assumptions!$F$6<Assumptions!$B$48+Assumptions!$B$49),E49,Assumptions!$F$102*Assumptions!$B$47) | G49: =IF(AND(Assumptions!$B$48>0,Assumptions!$G$6>=Assumptions!$B$48,Assumptions!$G$6<Assumptions!$B$48+Assumptions!$B$49),F49,Assumptions!$G$102*Assumptions!$B$47) | H49: =IF(AND(Assumptions!$B$48>0,Assumptions!$H$6>=Assumptions!$B$48,Assumptions!$H$6<Assumptions!$B$48+Assumptions!$B$49),G49,Assumptions!$H$102*Assumptions!$B$47)
A50: Office, software, admin, accounting | B50: =Assumptions!$B$103 | C50: =IF(AND(Assumptions!$B$48>0,Assumptions!$C$6>=Assumptions!$B$48,Assumptions!$C$6<Assumptions!$B$48+Assumptions!$B$49),B50,Assumptions!$C$103*Assumptions!$B$47) | D50: =IF(AND(Assumptions!$B$48>0,Assumptions!$D$6>=Assumptions!$B$48,Assumptions!$D$6<Assumptions!$B$48+Assumptions!$B$49),C50,Assumptions!$D$103*Assumptions!$B$47) | E50: =IF(AND(Assumptions!$B$48>0,Assumptions!$E$6>=Assumptions!$B$48,Assumptions!$E$6<Assumptions!$B$48+Assumptions!$B$49),D50,Assumptions!$E$103*Assumptions!$B$47) | F50: =IF(AND(Assumptions!$B$48>0,Assumptions!$F$6>=Assumptions!$B$48,Assumptions!$F$6<Assumptions!$B$48+Assumptions!$B$49),E50,Assumptions!$F$103*Assumptions!$B$47) | G50: =IF(AND(Assumptions!$B$48>0,Assumptions!$G$6>=Assumptions!$B$48,Assumptions!$G$6<Assumptions!$B$48+Assumptions!$B$49),F50,Assumptions!$G$103*Assumptions!$B$47) | H50: =IF(AND(Assumptions!$B$48>0,Assumptions!$H$6>=Assumptions!$B$48,Assumptions!$H$6<Assumptions!$B$48+Assumptions!$B$49),G50,Assumptions!$H$103*Assumptions!$B$47)
A51: Partner commission on carrier revenue | B51: =B24*Assumptions!$B$43 | C51: =C24*Assumptions!$B$43 | D51: =D24*Assumptions!$B$43 | E51: =E24*Assumptions!$B$43 | F51: =F24*Assumptions!$B$43 | G51: =G24*Assumptions!$B$43 | H51: =H24*Assumptions!$B$43
A52: Cost of revenue | B52: =B43+B45+B30*Assumptions!$B$50 | C52: =C43+C45+C30*Assumptions!$B$50 | D52: =D43+D45+D30*Assumptions!$B$50 | E52: =E43+E45+E30*Assumptions!$B$50 | F52: =F43+F45+F30*Assumptions!$B$50 | G52: =G43+G45+G30*Assumptions!$B$50 | H52: =H43+H45+H30*Assumptions!$B$50
A53: Gross profit | B53: =B30-B52 | C53: =C30-C52 | D53: =D30-D52 | E53: =E30-E52 | F53: =F30-F52 | G53: =G30-G52 | H53: =H30-H52
A54: Gross margin | B54: =IF(B30=0,0,B53/B30) | C54: =IF(C30=0,0,C53/C30) | D54: =IF(D30=0,0,D53/D30) | E54: =IF(E30=0,0,E53/E30) | F54: =IF(F30=0,0,F53/F30) | G54: =IF(G30=0,0,G53/G30) | H54: =IF(H30=0,0,H53/H30)
A55: Operating expense | B55: =B44+B46+B47+B48+B49+B50+B51 | C55: =C44+C46+C47+C48+C49+C50+C51 | D55: =D44+D46+D47+D48+D49+D50+D51 | E55: =E44+E46+E47+E48+E49+E50+E51 | F55: =F44+F46+F47+F48+F49+F50+F51 | G55: =G44+G46+G47+G48+G49+G50+G51 | H55: =H44+H46+H47+H48+H49+H50+H51
A56: EBITDA | B56: =B53-B55 | C56: =C53-C55 | D56: =D53-D55 | E56: =E53-E55 | F56: =F53-F55 | G56: =G53-G55 | H56: =H53-H55
A57: Capex | B57: =Assumptions!$B$15*B42 | C57: =Assumptions!$B$15*MAX(0,C42-B42) | D57: =Assumptions!$B$15*MAX(0,D42-C42) | E57: =Assumptions!$B$15*MAX(0,E42-D42) | F57: =Assumptions!$B$15*MAX(0,F42-E42) | G57: =Assumptions!$B$15*MAX(0,G42-F42) | H57: =Assumptions!$B$15*MAX(0,H42-G42)
A58: Depreciation | B58: =SUMPRODUCT((Assumptions!$B$6:$H$6<=Assumptions!$B$6)*(Assumptions!$B$6:$H$6>Assumptions!$B$6-Assumptions!$B$16)*$B$57:$H$57)/Assumptions!$B$16 | C58: =SUMPRODUCT((Assumptions!$B$6:$H$6<=Assumptions!$C$6)*(Assumptions!$B$6:$H$6>Assumptions!$C$6-Assumptions!$B$16)*$B$57:$H$57)/Assumptions!$B$16 | D58: =SUMPRODUCT((Assumptions!$B$6:$H$6<=Assumptions!$D$6)*(Assumptions!$B$6:$H$6>Assumptions!$D$6-Assumptions!$B$16)*$B$57:$H$57)/Assumptions!$B$16 | E58: =SUMPRODUCT((Assumptions!$B$6:$H$6<=Assumptions!$E$6)*(Assumptions!$B$6:$H$6>Assumptions!$E$6-Assumptions!$B$16)*$B$57:$H$57)/Assumptions!$B$16 | F58: =SUMPRODUCT((Assumptions!$B$6:$H$6<=Assumptions!$F$6)*(Assumptions!$B$6:$H$6>Assumptions!$F$6-Assumptions!$B$16)*$B$57:$H$57)/Assumptions!$B$16 | G58: =SUMPRODUCT((Assumptions!$B$6:$H$6<=Assumptions!$G$6)*(Assumptions!$B$6:$H$6>Assumptions!$G$6-Assumptions!$B$16)*$B$57:$H$57)/Assumptions!$B$16 | H58: =SUMPRODUCT((Assumptions!$B$6:$H$6<=Assumptions!$H$6)*(Assumptions!$B$6:$H$6>Assumptions!$H$6-Assumptions!$B$16)*$B$57:$H$57)/Assumptions!$B$16
A59: Profit before tax | B59: =B56-B58+Assumptions!$B$18*Assumptions!$B$17 | C59: =C56-C58+B66*Assumptions!$B$17 | D59: =D56-D58+C66*Assumptions!$B$17 | E59: =E56-E58+D66*Assumptions!$B$17 | F59: =F56-F58+E66*Assumptions!$B$17 | G59: =G56-G58+F66*Assumptions!$B$17 | H59: =H56-H58+G66*Assumptions!$B$17
A60: Cumulative profit before tax | B60: =B59 | C60: =B60+C59 | D60: =C60+D59 | E60: =D60+E59 | F60: =E60+F59 | G60: =F60+G59 | H60: =G60+H59
A61: Tax | B61: =MAX(0,B60)*Assumptions!$B$12 | C61: =MAX(0,MAX(0,C60)-MAX(0,B60))*Assumptions!$B$12 | D61: =MAX(0,MAX(0,D60)-MAX(0,C60))*Assumptions!$B$12 | E61: =MAX(0,MAX(0,E60)-MAX(0,D60))*Assumptions!$B$12 | F61: =MAX(0,MAX(0,F60)-MAX(0,E60))*Assumptions!$B$12 | G61: =MAX(0,MAX(0,G60)-MAX(0,F60))*Assumptions!$B$12 | H61: =MAX(0,MAX(0,H60)-MAX(0,G60))*Assumptions!$B$12
A62: Net income | B62: =B59-B61 | C62: =C59-C61 | D62: =D59-D61 | E62: =E59-E61 | F62: =F59-F61 | G62: =G59-G61 | H62: =H59-H61
A63: Receivables | B63: =B30*Assumptions!$B$13/365 | C63: =C30*Assumptions!$B$13/365 | D63: =D30*Assumptions!$B$13/365 | E63: =E30*Assumptions!$B$13/365 | F63: =F30*Assumptions!$B$13/365 | G63: =G30*Assumptions!$B$13/365 | H63: =H30*Assumptions!$B$13/365
A64: Payables | B64: =(B45+B30*Assumptions!$B$50+B46+B47+B48+B49+B50+B51)*Assumptions!$B$14/365 | C64: =(C45+C30*Assumptions!$B$50+C46+C47+C48+C49+C50+C51)*Assumptions!$B$14/365 | D64: =(D45+D30*Assumptions!$B$50+D46+D47+D48+D49+D50+D51)*Assumptions!$B$14/365 | E64: =(E45+E30*Assumptions!$B$50+E46+E47+E48+E49+E50+E51)*Assumptions!$B$14/365 | F64: =(F45+F30*Assumptions!$B$50+F46+F47+F48+F49+F50+F51)*Assumptions!$B$14/365 | G64: =(G45+G30*Assumptions!$B$50+G46+G47+G48+G49+G50+G51)*Assumptions!$B$14/365 | H64: =(H45+H30*Assumptions!$B$50+H46+H47+H48+H49+H50+H51)*Assumptions!$B$14/365
A65: Free cash flow (before financing) | B65: =B62+B58-(B63)+(B64)-B57 | C65: =C62+C58-(C63-B63)+(C64-B64)-C57 | D65: =D62+D58-(D63-C63)+(D64-C64)-D57 | E65: =E62+E58-(E63-D63)+(E64-D64)-E57 | F65: =F62+F58-(F63-E63)+(F64-E64)-F57 | G65: =G62+G58-(G63-F63)+(G64-F64)-G57 | H65: =H62+H58-(H63-G63)+(H64-G64)-H57
A66: Closing cash with the planned rounds | B66: =Assumptions!$B$18+B65+IF(Assumptions!$B$6=Assumptions!$B$22,Assumptions!$B$21,0)+IF(Assumptions!$B$6=Assumptions!$B$24,Assumptions!$B$23,0)+IF(Assumptions!$B$6=Assumptions!$B$26,Assumptions!$B$25,0) | C66: =B66+C65+IF(Assumptions!$C$6=Assumptions!$B$22,Assumptions!$B$21,0)+IF(Assumptions!$C$6=Assumptions!$B$24,Assumptions!$B$23,0)+IF(Assumptions!$C$6=Assumptions!$B$26,Assumptions!$B$25,0) | D66: =C66+D65+IF(Assumptions!$D$6=Assumptions!$B$22,Assumptions!$B$21,0)+IF(Assumptions!$D$6=Assumptions!$B$24,Assumptions!$B$23,0)+IF(Assumptions!$D$6=Assumptions!$B$26,Assumptions!$B$25,0) | E66: =D66+E65+IF(Assumptions!$E$6=Assumptions!$B$22,Assumptions!$B$21,0)+IF(Assumptions!$E$6=Assumptions!$B$24,Assumptions!$B$23,0)+IF(Assumptions!$E$6=Assumptions!$B$26,Assumptions!$B$25,0) | F66: =E66+F65+IF(Assumptions!$F$6=Assumptions!$B$22,Assumptions!$B$21,0)+IF(Assumptions!$F$6=Assumptions!$B$24,Assumptions!$B$23,0)+IF(Assumptions!$F$6=Assumptions!$B$26,Assumptions!$B$25,0) | G66: =F66+G65+IF(Assumptions!$G$6=Assumptions!$B$22,Assumptions!$B$21,0)+IF(Assumptions!$G$6=Assumptions!$B$24,Assumptions!$B$23,0)+IF(Assumptions!$G$6=Assumptions!$B$26,Assumptions!$B$25,0) | H66: =G66+H65+IF(Assumptions!$H$6=Assumptions!$B$22,Assumptions!$B$21,0)+IF(Assumptions!$H$6=Assumptions!$B$24,Assumptions!$B$23,0)+IF(Assumptions!$H$6=Assumptions!$B$26,Assumptions!$B$25,0)
A67: Cumulative free cash flow | B67: =B65 | C67: =B67+C65 | D67: =C67+D65 | E67: =D67+E65 | F67: =E67+F65 | G67: =F67+G65 | H67: =G67+H65
A68: Cumulative FCF before the Series A year | B68: =IF(Assumptions!$B$6<Assumptions!$B$26,B67,0) | C68: =IF(Assumptions!$C$6<Assumptions!$B$26,C67,0) | D68: =IF(Assumptions!$D$6<Assumptions!$B$26,D67,0) | E68: =IF(Assumptions!$E$6<Assumptions!$B$26,E67,0) | F68: =IF(Assumptions!$F$6<Assumptions!$B$26,F67,0) | G68: =IF(Assumptions!$G$6<Assumptions!$B$26,G67,0) | H68: =IF(Assumptions!$H$6<Assumptions!$B$26,H67,0)
A69: Lowest year-end cash with the planned rounds | B69: =MIN(B66:H66)
A70: Total equity need incl. buffer | B70: =MAX(0,-MIN(B67:H67))*(1+Assumptions!$B$20)
A71: Seed need incl. buffer (deepest point before a mid-year Series A) | B71: =MAX(0,-MIN(0,MIN(B68:H68),SUMPRODUCT((Assumptions!$B$6:$H$6<Assumptions!$B$26)*$B$65:$H$65)+0.5*SUMPRODUCT((Assumptions!$B$6:$H$6=Assumptions!$B$26)*$B$65:$H$65)))*(1+Assumptions!$B$20)
A72: Month ARR crosses the Series A milestone (linear within year) | B72: =IF(B31>=Assumptions!$B$19,12*Assumptions!$B$19/B31,"") | C72: =IF(AND(C31>=Assumptions!$B$19,B31<Assumptions!$B$19),12*(Assumptions!$C$6-1)+12*(Assumptions!$B$19-B31)/(C31-B31),"") | D72: =IF(AND(D31>=Assumptions!$B$19,C31<Assumptions!$B$19),12*(Assumptions!$D$6-1)+12*(Assumptions!$B$19-C31)/(D31-C31),"") | E72: =IF(AND(E31>=Assumptions!$B$19,D31<Assumptions!$B$19),12*(Assumptions!$E$6-1)+12*(Assumptions!$B$19-D31)/(E31-D31),"") | F72: =IF(AND(F31>=Assumptions!$B$19,E31<Assumptions!$B$19),12*(Assumptions!$F$6-1)+12*(Assumptions!$B$19-E31)/(F31-E31),"") | G72: =IF(AND(G31>=Assumptions!$B$19,F31<Assumptions!$B$19),12*(Assumptions!$G$6-1)+12*(Assumptions!$B$19-F31)/(G31-F31),"") | H72: =IF(AND(H31>=Assumptions!$B$19,G31<Assumptions!$B$19),12*(Assumptions!$H$6-1)+12*(Assumptions!$B$19-G31)/(H31-G31),"")
A73: Series A milestone month | B73: =IF(COUNT(B72:H72)=0,"not reached",ROUNDUP(SUM(B72:H72),0))
A74: Cash if only the seed is raised | B74: =(Assumptions!$B$18+Assumptions!$B$21+Assumptions!$B$23)+B67 | C74: =(Assumptions!$B$18+Assumptions!$B$21+Assumptions!$B$23)+C67 | D74: =(Assumptions!$B$18+Assumptions!$B$21+Assumptions!$B$23)+D67 | E74: =(Assumptions!$B$18+Assumptions!$B$21+Assumptions!$B$23)+E67 | F74: =(Assumptions!$B$18+Assumptions!$B$21+Assumptions!$B$23)+F67 | G74: =(Assumptions!$B$18+Assumptions!$B$21+Assumptions!$B$23)+G67 | H74: =(Assumptions!$B$18+Assumptions!$B$21+Assumptions!$B$23)+H67
A75: Month seed-only cash runs out (linear within year) | B75: =IF(B74<0,12*(Assumptions!$B$18+Assumptions!$B$21+Assumptions!$B$23)/((Assumptions!$B$18+Assumptions!$B$21+Assumptions!$B$23)-B74),"") | C75: =IF(AND(C74<0,B74>=0),12*(Assumptions!$C$6-1)+12*B74/(B74-C74),"") | D75: =IF(AND(D74<0,C74>=0),12*(Assumptions!$D$6-1)+12*C74/(C74-D74),"") | E75: =IF(AND(E74<0,D74>=0),12*(Assumptions!$E$6-1)+12*D74/(D74-E74),"") | F75: =IF(AND(F74<0,E74>=0),12*(Assumptions!$F$6-1)+12*E74/(E74-F74),"") | G75: =IF(AND(G74<0,F74>=0),12*(Assumptions!$G$6-1)+12*F74/(F74-G74),"") | H75: =IF(AND(H74<0,G74>=0),12*(Assumptions!$H$6-1)+12*G74/(G74-H74),"")
A76: Seed runway in months, without a Series A | B76: =IF(COUNT(B75:H75)=0,"beyond month 84",ROUNDDOWN(SUM(B75:H75),0))
A78: Bull case | B78: ="Y"&Assumptions!$B$6 | C78: ="Y"&Assumptions!$C$6 | D78: ="Y"&Assumptions!$D$6 | E78: ="Y"&Assumptions!$E$6 | F78: ="Y"&Assumptions!$F$6 | G78: ="Y"&Assumptions!$G$6 | H78: ="Y"&Assumptions!$H$6
A79: Shippers (mid-market): new accounts | B79: =ROUND(Assumptions!$B$53*Assumptions!$B$39,0) | C79: =ROUND(Assumptions!$C$53*Assumptions!$B$39,0) | D79: =ROUND(Assumptions!$D$53*Assumptions!$B$39,0) | E79: =ROUND(Assumptions!$E$53*Assumptions!$B$39,0) | F79: =ROUND(Assumptions!$F$53*Assumptions!$B$39,0) | G79: =ROUND(Assumptions!$G$53*Assumptions!$B$39,0) | H79: =ROUND(Assumptions!$H$53*Assumptions!$B$39,0)
A80: Shippers (mid-market): accounts lost = ROUND(prior year-end x churn) | B80: =0 | C80: =ROUND(B81*Assumptions!$C$45,0) | D80: =ROUND(C81*Assumptions!$C$45,0) | E80: =ROUND(D81*Assumptions!$C$45,0) | F80: =ROUND(E81*Assumptions!$C$45,0) | G80: =ROUND(F81*Assumptions!$C$45,0) | H80: =ROUND(G81*Assumptions!$C$45,0)
A81: Shippers (mid-market): accounts at year end | B81: =B79 | C81: =B81-C80+C79 | D81: =C81-D80+D79 | E81: =D81-E80+E79 | F81: =E81-F80+F79 | G81: =F81-G80+G79 | H81: =G81-H80+H79
A82: Shippers (mid-market): average accounts | B82: =B81/2 | C82: =(B81+C81)/2 | D82: =(C81+D81)/2 | E82: =(D81+E81)/2 | F82: =(E81+F81)/2 | G82: =(F81+G81)/2 | H82: =(G81+H81)/2
A83: Shippers (mid-market): revenue per account ($K) | B83: =(Assumptions!$B$35+Assumptions!$B$36*Assumptions!$B$40*Assumptions!$B$37)*Assumptions!$C$46 | C83: =(Assumptions!$C$35+Assumptions!$C$36*Assumptions!$B$40*Assumptions!$C$37)*Assumptions!$C$46 | D83: =(Assumptions!$D$35+Assumptions!$D$36*Assumptions!$B$40*Assumptions!$D$37)*Assumptions!$C$46 | E83: =(Assumptions!$E$35+Assumptions!$E$36*Assumptions!$B$40*Assumptions!$E$37)*Assumptions!$C$46 | F83: =(Assumptions!$F$35+Assumptions!$F$36*Assumptions!$B$40*Assumptions!$F$37)*Assumptions!$C$46 | G83: =(Assumptions!$G$35+Assumptions!$G$36*Assumptions!$B$40*Assumptions!$G$37)*Assumptions!$C$46 | H83: =(Assumptions!$H$35+Assumptions!$H$36*Assumptions!$B$40*Assumptions!$H$37)*Assumptions!$C$46
A84: Shippers (mid-market): revenue | B84: =B82*B83 | C84: =C82*C83 | D84: =D82*D83 | E84: =E82*E83 | F84: =F82*F83 | G84: =G82*G83 | H84: =H82*H83
A85: Shippers (mid-market): ARR at year end | B85: =B81*B83 | C85: =C81*C83 | D85: =D81*D83 | E85: =E81*E83 | F85: =F81*F83 | G85: =G81*G83 | H85: =H81*H83
A86: SME importers: new accounts | B86: =Assumptions!$B$53-ROUND(Assumptions!$B$53*Assumptions!$B$39,0) | C86: =Assumptions!$C$53-ROUND(Assumptions!$C$53*Assumptions!$B$39,0) | D86: =Assumptions!$D$53-ROUND(Assumptions!$D$53*Assumptions!$B$39,0) | E86: =Assumptions!$E$53-ROUND(Assumptions!$E$53*Assumptions!$B$39,0) | F86: =Assumptions!$F$53-ROUND(Assumptions!$F$53*Assumptions!$B$39,0) | G86: =Assumptions!$G$53-ROUND(Assumptions!$G$53*Assumptions!$B$39,0) | H86: =Assumptions!$H$53-ROUND(Assumptions!$H$53*Assumptions!$B$39,0)
A87: SME importers: accounts lost = ROUND(prior year-end x churn) | B87: =0 | C87: =ROUND(B88*Assumptions!$C$45,0) | D87: =ROUND(C88*Assumptions!$C$45,0) | E87: =ROUND(D88*Assumptions!$C$45,0) | F87: =ROUND(E88*Assumptions!$C$45,0) | G87: =ROUND(F88*Assumptions!$C$45,0) | H87: =ROUND(G88*Assumptions!$C$45,0)
A88: SME importers: accounts at year end | B88: =B86 | C88: =B88-C87+C86 | D88: =C88-D87+D86 | E88: =D88-E87+E86 | F88: =E88-F87+F86 | G88: =F88-G87+G86 | H88: =G88-H87+H86
A89: SME importers: average accounts | B89: =B88/2 | C89: =(B88+C88)/2 | D89: =(C88+D88)/2 | E89: =(D88+E88)/2 | F89: =(E88+F88)/2 | G89: =(F88+G88)/2 | H89: =(G88+H88)/2
A90: SME importers: revenue per account ($K) | B90: =(Assumptions!$B$35+Assumptions!$B$36*Assumptions!$B$37)*Assumptions!$C$46 | C90: =(Assumptions!$C$35+Assumptions!$C$36*Assumptions!$C$37)*Assumptions!$C$46 | D90: =(Assumptions!$D$35+Assumptions!$D$36*Assumptions!$D$37)*Assumptions!$C$46 | E90: =(Assumptions!$E$35+Assumptions!$E$36*Assumptions!$E$37)*Assumptions!$C$46 | F90: =(Assumptions!$F$35+Assumptions!$F$36*Assumptions!$F$37)*Assumptions!$C$46 | G90: =(Assumptions!$G$35+Assumptions!$G$36*Assumptions!$G$37)*Assumptions!$C$46 | H90: =(Assumptions!$H$35+Assumptions!$H$36*Assumptions!$H$37)*Assumptions!$C$46
A91: SME importers: revenue | B91: =B89*B90 | C91: =C89*C90 | D91: =D89*D90 | E91: =E89*E90 | F91: =F89*F90 | G91: =G89*G90 | H91: =H89*H90
A92: SME importers: ARR at year end | B92: =B88*B90 | C92: =C88*C90 | D92: =D88*D90 | E92: =E88*E90 | F92: =F88*F90 | G92: =G88*G90 | H92: =H88*H90
A93: Carriers (partner-led): new accounts | B93: =Assumptions!$B$57 | C93: =Assumptions!$C$57 | D93: =Assumptions!$D$57 | E93: =Assumptions!$E$57 | F93: =Assumptions!$F$57 | G93: =Assumptions!$G$57 | H93: =Assumptions!$H$57
A94: Carriers (partner-led): accounts lost = ROUND(prior year-end x churn) | B94: =0 | C94: =ROUND(B95*Assumptions!$C$45,0) | D94: =ROUND(C95*Assumptions!$C$45,0) | E94: =ROUND(D95*Assumptions!$C$45,0) | F94: =ROUND(E95*Assumptions!$C$45,0) | G94: =ROUND(F95*Assumptions!$C$45,0) | H94: =ROUND(G95*Assumptions!$C$45,0)
A95: Carriers (partner-led): accounts at year end | B95: =B93 | C95: =B95-C94+C93 | D95: =C95-D94+D93 | E95: =D95-E94+E93 | F95: =E95-F94+F93 | G95: =F95-G94+G93 | H95: =G95-H94+H93
A96: Carriers (partner-led): average accounts | B96: =B95/2 | C96: =(B95+C95)/2 | D96: =(C95+D95)/2 | E96: =(D95+E95)/2 | F96: =(E95+F95)/2 | G96: =(F95+G95)/2 | H96: =(G95+H95)/2
A97: Carriers (partner-led): revenue per account ($K) | B97: =Assumptions!$B$41*Assumptions!$B$42*Assumptions!$C$46 | C97: =Assumptions!$C$41*Assumptions!$B$42*Assumptions!$C$46 | D97: =Assumptions!$D$41*Assumptions!$B$42*Assumptions!$C$46 | E97: =Assumptions!$E$41*Assumptions!$B$42*Assumptions!$C$46 | F97: =Assumptions!$F$41*Assumptions!$B$42*Assumptions!$C$46 | G97: =Assumptions!$G$41*Assumptions!$B$42*Assumptions!$C$46 | H97: =Assumptions!$H$41*Assumptions!$B$42*Assumptions!$C$46
A98: Carriers (partner-led): revenue | B98: =B96*B97 | C98: =C96*C97 | D98: =D96*D97 | E98: =E96*E97 | F98: =F96*F97 | G98: =G96*G97 | H98: =H96*H97
A99: Carriers (partner-led): ARR at year end | B99: =B95*B97 | C99: =C95*C97 | D99: =D95*D97 | E99: =E95*E97 | F99: =F95*F97 | G99: =G95*G97 | H99: =H95*H97
A100: All segments: new accounts won | B100: =B79+B86+B93 | C100: =C79+C86+C93 | D100: =D79+D86+D93 | E100: =E79+E86+E93 | F100: =F79+F86+F93 | G100: =G79+G86+G93 | H100: =H79+H86+H93
A101: All segments: accounts lost | B101: =B80+B87+B94 | C101: =C80+C87+C94 | D101: =D80+D87+D94 | E101: =E80+E87+E94 | F101: =F80+F87+F94 | G101: =G80+G87+G94 | H101: =H80+H87+H94
A102: All segments: paying accounts at year end | B102: =B81+B88+B95 | C102: =C81+C88+C95 | D102: =D81+D88+D95 | E102: =E81+E88+E95 | F102: =F81+F88+F95 | G102: =G81+G88+G95 | H102: =H81+H88+H95
...
