Workbook

Sheet Source review 2026-10-19
A1: scoup.ai — financial model provenance review
A2: NOT APPROVED FOR EXTERNAL USE. This workbook is a planning scenario, not an audited result, actual forecast, or owner-approved source of truth. Company inputs and projections remain assumptions.
A4: Review date | B4: 2026-10-19. Scope: source/caveat review; existing numeric inputs and formulas are preserved.
A5: Calculation status | B5: Recalculated 2026-10-22 with the Python formulas engine (no Excel or LibreOffice on this machine); Excel recalculates on open. Financing!B4:D8 use MATCH(TRUE,INDEX(...)), which that engine cannot evaluate; recomputed in business/tools/recalc_model.py instead.
A6: Model authority | B6: No model was designated by the owner. This workbook conflicts with a separate local model. Select one model and reconcile before any investor or planning use.
A7: Primary source: FMC | B7: Nine carriers reported roughly $15.4B of D&D collected from 2020-04-01 through 2025-03-31. This is historical collected charges, not recoverable market spend. https://www.fmc.gov/detention-and-demurrage/
A8: Primary source: eCFR | B8: 46 CFR Part 541 current through 2026-10-15; §541.4 reserved; see §§541.5–541.8. https://www.ecfr.gov/current/title-46/chapter-IV/subchapter-B/part-541
A9: Primary source: ATRI | B9: The 2023 detention study estimates $15.1B cost of waiting; it is not a recovery pool. https://truckingresearch.org/2024/09/new-research-documents-substantial-financial-and-safety-impacts-from-truck-driver-detention/
A10: Assumptions | B10: Recovery rate, fees, account counts, margins, CAC, churn, use of funds, round sizes, valuation and runway are planning assumptions unless individually sourced; none is a measured company result.
A11: Internal benchmarks | B11: Model inputs that rely on charge classification, forecast performance or simulated invoice recovery remain unverified. Internal records conflict on 145/159 versus 158/159 classifier names.
A12: Full ledger and customer-value review | B12: See repository file _launch/02-data-provenance.md for source dates, limits, itemized PDF claims, and remaining release blockers. Customer-value scenarios in this workbook are unvalidated assumptions, not observed customer results.
A13: Change scope | B13: This review sheet and source links were added. Existing model values/formulas were not edited. Recalculate and reconcile before external use.
A14: Customer-value scenario inputs | B14: Customer value sheet B4:B12/C4:C12 contains hardcoded scenario amounts ($56,400, $7,540, $12,670, $16,000, $240,000, and $36,000). No customer files, observed recovery outcomes, or owner-approved method support these figures in the reviewed materials. Treat them as unvalidated assumptions; do not present as customer value or actual results.
A15: Untraced denominator | B15: Customer value!C10 uses 25.66M U.S. imports/TEU without a traceable source, date, geography/method definition, or reproducible calculation in the reviewed workbook. Do not use as a sourced fact until reconciled.
... A17: 2026-10-22 update | B17: Sourced inputs re-verified; a Sources (verified) sheet maps cells to source, URL and dates. Recalculated outside Excel with business/tools/recalc_model.py: base Y5 revenue $7.30M, Y5 ARR $9.03M, Y7 ARR $18.63M. Customer value B10/B11 now use a sourced TEU denominator. Assumptions!B14 ($52K in year 1) still rests on the old $36K D&D figure; the sourced figure gives about $32.9K, so B14 would be about $48.9K. Left for the owner to decide.

Sheet Cover
A1: scoup.ai | Financial model
A3: Seven-year operating plan and financing requirement, three scenarios. Pre-revenue company: plan figures, not results.
A5: How to read this workbook
A6: Blue numbers are inputs. Black numbers are formulas. Change an input and every sheet updates.
A7: Each input has a source and a grade: A = primary source; B = reputable secondary source; C = estimate or company assumption.
A8: Years are 12-month periods from the seed close. All amounts in US dollars.
A10: Sheets
A11: Assumptions - global inputs, revenue per account build, headcount plan and operating costs
A12: Base, Upside, Downside - accounts, revenue, gross profit, costs, EBITDA, sales cost per $1 of new ARR
A13: Monthly - month-by-month ARR and EBITDA used to size the rounds
A14: Financing - round sizes, timing and the downside cost response
A15: Use of funds - how the seed and the Series A are spent, by function
... A19: Sources - external figures used

Sheet Assumptions
A1: Assumptions
A3: Global input | B3: Value | C3: Source / grade
A4: Compensation inflation per year | B4: 0.04 | C4: Planning assumption (C)
A5: Series A ARR milestone ($M) | B5: 2.5 | C5: Carta: median ARR at Series A was $2.8M in 2025, up from $2.3M in 2024 (B, carta.com/data; accessed 2026-10-22). Input kept at $2.5M as a planning choice (C)
A6: Cash buffer on each round | B6: 0.2 | C6: Planning assumption (C)
A7: Months to close the next round after the milestone | B7: 6 | C7: Planning assumption (C)
A8: Series A runway (months) | B8: 30 | C8: Common norm 24-30 months (C)
A9: NOK per USD (planning rate) | B9: 10.5 | C9: Assumption (C)
A11: Revenue per account, base case ($K per year)
A12: Component | B12: Y1 | C12: Y2 | D12: Y3 | E12: Y4 | F12: Y5 | G12: Y6 | H12: Y7 | I12: Basis / grade
A13: Platform fee ($K/yr) | B13: 0 | C13: 6 | D13: 10 | E13: 13 | F13: 15 | G13: 16 | H13: 17 | I13: Platform fee from year 2 (C)
A14: Amount recovered per account ($K/yr) | B14: 52 | C14: 70 | D14: 85 | E14: 95 | F14: 105 | G14: 110 | H14: 115 | I14: Year 1: ~$52K for a mid-size importer-shipper (business case, our analysis); grows as modules are added (C)
A15: Recovery share | B15: 0.25 | C15: 0.17 | D15: 0.14 | E15: 0.12 | F15: 0.12 | G15: 0.12 | H15: 0.12 | I15: 25% in pilots, 12% with the platform fee (C). Published parcel-refund pricing: Refund Retriever 50%/45%/40% of refunds by volume band (A, refundretriever.com/pricing, accessed 2026-10-22)
A16: Revenue per account, base ($K) | B16: =ROUND(B13+B14*B15,1) | C16: =ROUND(C13+C14*C15,1) | D16: =ROUND(D13+D14*D15,1) | E16: =ROUND(E13+E14*E15,1) | F16: =ROUND(F13+F14*F15,1) | G16: =ROUND(G13+G14*G15,1) | H16: =ROUND(H13+H14*H15,1)
A18: Headcount plan (base case, people at year end) and loaded cost
A19: Role | B19: Location | C19: Loaded cost $K/yr | D19: Y1 | E19: Y2 | F19: Y3 | G19: Y4 | H19: Y5 | I19: Y6 | J19: Y7 | K19: Basis / grade
A20: Founder / CEO | B20: NO | C20: 140 | D20: 1 | E20: 1 | F20: 1 | G20: 1 | H20: 1 | I20: 1 | J20: 1 | K20: Founder salary held below market until Series A (C)
A21: Software engineers | B21: NO | C21: 115 | D21: 2 | E21: 3 | F21: 5 | G21: 8 | H21: 10 | I21: 12 | J21: 13 | K21: SSB ICT pay NOK ~969K x 1.22 (A/C)
A22: ML / data engineers | B22: NO | C22: 125 | D22: 1 | E22: 1 | F22: 2 | G22: 3 | H22: 3 | I22: 4 | J22: 4 | K22: SSB ICT pay, upper range, x 1.22 (A/C)
A23: Security engineer | B23: NO | C23: 125 | D23: 1 | E23: 1 | F23: 1 | G23: 2 | H23: 2 | I23: 3 | J23: 3 | K23: SSB ICT pay x 1.22; BLS infosec median $129K for US comparison (A)
A24: Account executives (US) | B24: US | C24: 230 | D24: 0 | E24: 1 | F24: 3 | G24: 5 | H24: 7 | I24: 8 | J24: 9 | K24: BLS technical sales base $105K, on-target earnings ~2x base, loaded (A/C)
A25: Sales engineer (US) | B25: US | C25: 175 | D25: 0 | E25: 1 | F25: 1 | G25: 2 | H25: 2 | I25: 3 | J25: 3 | K25: BLS sales engineer median $125K x 1.43 (A)
A26: Claims analysts / customer success (US) | B26: US | C26: 100 | D26: 1 | E26: 2 | F26: 4 | G26: 7 | H26: 10 | I26: 13 | J26: 16 | K26: Analyst base ~$70K x 1.43 (C)
A27: Marketing (US) | B27: US | C27: 150 | D27: 0 | E27: 0 | F27: 1 | G27: 1 | H27: 2 | I27: 2 | J27: 2 | K27: Estimate (C)
A28: Finance, legal operations, people | B28: NO | C28: 130 | D28: 0 | E28: 1 | F28: 1 | G28: 2 | H28: 2 | I28: 3 | J28: 3 | K28: SSB pay x 1.22 (A/C)
A30: Other operating costs (base case, $K per year)
A31: Item | D31: Y1 | E31: Y2 | F31: Y3 | G31: Y4 | H31: Y5 | I31: Y6 | J31: Y7 | K31: Basis / grade
A32: Cloud hosting, data feeds and tooling | D32: 45 | E32: 80 | F32: 140 | G32: 220 | H32: 300 | I32: 370 | J32: 430 | K32: Terraform footprint + container-event data fees (C)
A33: Security programme | D33: 120 | E33: 150 | F33: 170 | G33: 190 | H33: 210 | I33: 230 | J33: 250 | K33: SOC 2 Type II first year $50-110K, penetration tests $15-35K each (C), tooling, insurance (C)
A34: Legal and regulatory | D34: 150 | E34: 110 | F34: 120 | G34: 140 | H34: 150 | I34: 160 | J34: 170 | K34: US entity, customer contracts, FMC and data-protection counsel (C)
A35: Marketing programmes and events | D35: 30 | E35: 90 | F35: 200 | G35: 320 | H35: 420 | I35: 480 | J35: 520 | K35: Trade shows (TIA, CSCMP, TPM), content, list data (C)
A36: Travel and customer visits | D36: 60 | E36: 100 | F36: 150 | G36: 200 | H36: 240 | I36: 270 | J36: 300 | K36: US customer and partner visits (C)
A37: Office, software, admin, accounting | D37: 50 | E37: 80 | F37: 110 | G37: 150 | H37: 180 | I37: 210 | J37: 240 | K37: Estimate (C)

Sheet Downside
A1: Downside case
A2: Recovery per account is 20% lower than the base case, buyers insist on long security reviews, only shippers and importers convert, and the broker channel slips to year 4.
A4: $M unless stated | B4: Y1 | C4: Y2 | D4: Y3 | E4: Y4 | F4: Y5 | G4: Y6 | H4: Y7 | I4: Note
A5: New accounts won | B5: 4 | C5: 16 | D5: 35 | E5: 55 | F5: 75 | G5: 90 | H5: 105 | I5: Plan input (C)
A6: Annual account churn | B6: 0.3 | I6: Share of accounts at the start of a year lost during it (C); median gross revenue retention 88% (Benchmarkit, B)
A7: Revenue per account vs base | B7: 0.8
A8: Cost scale vs base headcount and spend | B8: 0.85
A9: Accounts lost in year | B9: =0 | C9: =ROUND(B10*$B$6,0) | D9: =ROUND(C10*$B$6,0) | E9: =ROUND(D10*$B$6,0) | F9: =ROUND(E10*$B$6,0) | G9: =ROUND(F10*$B$6,0) | H9: =ROUND(G10*$B$6,0)
A10: Paying accounts at year end | B10: =B5 | C10: =B10-C9+C5 | D10: =C10-D9+D5 | E10: =D10-E9+E5 | F10: =E10-F9+F5 | G10: =F10-G9+G5 | H10: =G10-H9+H5
A11: Revenue per account ($K) | B11: =Assumptions!B16*$B$7 | C11: =Assumptions!C16*$B$7 | D11: =Assumptions!D16*$B$7 | E11: =Assumptions!E16*$B$7 | F11: =Assumptions!F16*$B$7 | G11: =Assumptions!G16*$B$7 | H11: =Assumptions!H16*$B$7
A12: Gross margin | B12: 0.45 | C12: 0.52 | D12: 0.57 | E12: 0.6 | F12: 0.62 | G12: 0.64 | H12: 0.65 | I12: After hosting, data feeds and claim review labour (C)
A14: Revenue | B14: =(0+B10)/2*B11/1000 | C14: =(B10+C10)/2*C11/1000 | D14: =(C10+D10)/2*D11/1000 | E14: =(D10+E10)/2*E11/1000 | F14: =(E10+F10)/2*F11/1000 | G14: =(F10+G10)/2*G11/1000 | H14: =(G10+H10)/2*H11/1000
A15: Cost of revenue | B15: =B14*(1-B12) | C15: =C14*(1-C12) | D15: =D14*(1-D12) | E15: =E14*(1-E12) | F15: =F14*(1-F12) | G15: =G14*(1-G12) | H15: =H14*(1-H12)
A16: Gross profit | B16: =B14-B15 | C16: =C14-C15 | D16: =D14-D15 | E16: =E14-E15 | F16: =F14-F15 | G16: =G14-G15 | H16: =H14-H15
A17: People costs | B17: =(Assumptions!D20*Assumptions!$C$20+(ROUND(Assumptions!D21*$B$8,0)*0.6)*Assumptions!$C$21+(ROUND(Assumptions!D22*$B$8,0)*0.6)*Assumptions!$C$22+(ROUND(Assumptions!D23*$B$8,0)*0.6)*Assumptions!$C$23+(ROUND(Assumptions!D24*$B$8,0)*0.6)*Assumptions!$C$24+(ROUND(Assumptions!D25*$B$8,0)*0.6)*Assumptions!$C$25+(ROUND(Assumptions!D26*$B$8,0)*0.6)*Assumptions!$C$26+(ROUND(Assumptions!D27*$B$8,0)*0.6)*Assumptions!$C$27+(ROUND(Assumptions!D28*$B$8,0)*0.6)*Assumptions!$C$28)*(1+Assumptions!$B$4)^0/1000 | C17: =(((Assumptions!D20+Assumptions!E20)/2)*Assumptions!$C$20+((ROUND(Assumptions!D21*$B$8,0)+ROUND(Assumptions!E21*$B$8,0))/2)*Assumptions!$C$21+((ROUND(Assumptions!D22*$B$8,0)+ROUND(Assumptions!E22*$B$8,0))/2)*Assumptions!$C$22+((ROUND(Assumptions!D23*$B$8,0)+ROUND(Assumptions!E23*$B$8,0))/2)*Assumptions!$C$23+((ROUND(Assumptions!D24*$B$8,0)+ROUND(Assumptions!E24*$B$8,0))/2)*Assumptions!$C$24+((ROUND(Assumptions!D25*$B$8,0)+ROUND(Assumptions!E25*$B$8,0))/2)*Assumptions!$C$25+((ROUND(Assumptions!D26*$B$8,0)+ROUND(Assumptions!E26*$B$8,0))/2)*Assumptions!$C$26+((ROUND(Assumptions!D27*$B$8,0)+ROUND(Assumptions!E27*$B$8,0))/2)*Assumptions!$C$27+((ROUND(Assumptions!D28*$B$8,0)+ROUND(Assumptions!E28*$B$8,0))/2)*Assumptions!$C$28)*(1+Assumptions!$B$4)^1/1000 | D17: =(((Assumptions!E20+Assumptions!F20)/2)*Assumptions!$C$20+((ROUND(Assumptions!E21*$B$8,0)+ROUND(Assumptions!F21*$B$8,0))/2)*Assumptions!$C$21+((ROUND(Assumptions!E22*$B$8,0)+ROUND(Assumptions!F22*$B$8,0))/2)*Assumptions!$C$22+((ROUND(Assumptions!E23*$B$8,0)+ROUND(Assumptions!F23*$B$8,0))/2)*Assumptions!$C$23+((ROUND(Assumptions!E24*$B$8,0)+ROUND(Assumptions!F24*$B$8,0))/2)*Assumptions!$C$24+((ROUND(Assumptions!E25*$B$8,0)+ROUND(Assumptions!F25*$B$8,0))/2)*Assumptions!$C$25+((ROUND(Assumptions!E26*$B$8,0)+ROUND(Assumptions!F26*$B$8,0))/2)*Assumptions!$C$26+((ROUND(Assumptions!E27*$B$8,0)+ROUND(Assumptions!F27*$B$8,0))/2)*Assumptions!$C$27+((ROUND(Assumptions!E28*$B$8,0)+ROUND(Assumptions!F28*$B$8,0))/2)*Assumptions!$C$28)*(1+Assumptions!$B$4)^2/1000 | E17: =(((Assumptions!F20+Assumptions!G20)/2)*Assumptions!$C$20+((ROUND(Assumptions!F21*$B$8,0)+ROUND(Assumptions!G21*$B$8,0))/2)*Assumptions!$C$21+((ROUND(Assumptions!F22*$B$8,0)+ROUND(Assumptions!G22*$B$8,0))/2)*Assumptions!$C$22+((ROUND(Assumptions!F23*$B$8,0)+ROUND(Assumptions!G23*$B$8,0))/2)*Assumptions!$C$23+((ROUND(Assumptions!F24*$B$8,0)+ROUND(Assumptions!G24*$B$8,0))/2)*Assumptions!$C$24+((ROUND(Assumptions!F25*$B$8,0)+ROUND(Assumptions!G25*$B$8,0))/2)*Assumptions!$C$25+((ROUND(Assumptions!F26*$B$8,0)+ROUND(Assumptions!G26*$B$8,0))/2)*Assumptions!$C$26+((ROUND(Assumptions!F27*$B$8,0)+ROUND(Assumptions!G27*$B$8,0))/2)*Assumptions!$C$27+((ROUND(Assumptions!F28*$B$8,0)+ROUND(Assumptions!G28*$B$8,0))/2)*Assumptions!$C$28)*(1+Assumptions!$B$4)^3/1000 | F17: =(((Assumptions!G20+Assumptions!H20)/2)*Assumptions!$C$20+((ROUND(Assumptions!G21*$B$8,0)+ROUND(Assumptions!H21*$B$8,0))/2)*Assumptions!$C$21+((ROUND(Assumptions!G22*$B$8,0)+ROUND(Assumptions!H22*$B$8,0))/2)*Assumptions!$C$22+((ROUND(Assumptions!G23*$B$8,0)+ROUND(Assumptions!H23*$B$8,0))/2)*Assumptions!$C$23+((ROUND(Assumptions!G24*$B$8,0)+ROUND(Assumptions!H24*$B$8,0))/2)*Assumptions!$C$24+((ROUND(Assumptions!G25*$B$8,0)+ROUND(Assumptions!H25*$B$8,0))/2)*Assumptions!$C$25+((ROUND(Assumptions!G26*$B$8,0)+ROUND(Assumptions!H26*$B$8,0))/2)*Assumptions!$C$26+((ROUND(Assumptions!G27*$B$8,0)+ROUND(Assumptions!H27*$B$8,0))/2)*Assumptions!$C$27+((ROUND(Assumptions!G28*$B$8,0)+ROUND(Assumptions!H28*$B$8,0))/2)*Assumptions!$C$28)*(1+Assumptions!$B$4)^4/1000 | G17: =(((Assumptions!H20+Assumptions!I20)/2)*Assumptions!$C$20+((ROUND(Assumptions!H21*$B$8,0)+ROUND(Assumptions!I21*$B$8,0))/2)*Assumptions!$C$21+((ROUND(Assumptions!H22*$B$8,0)+ROUND(Assumptions!I22*$B$8,0))/2)*Assumptions!$C$22+((ROUND(Assumptions!H23*$B$8,0)+ROUND(Assumptions!I23*$B$8,0))/2)*Assumptions!$C$23+((ROUND(Assumptions!H24*$B$8,0)+ROUND(Assumptions!I24*$B$8,0))/2)*Assumptions!$C$24+((ROUND(Assumptions!H25*$B$8,0)+ROUND(Assumptions!I25*$B$8,0))/2)*Assumptions!$C$25+((ROUND(Assumptions!H26*$B$8,0)+ROUND(Assumptions!I26*$B$8,0))/2)*Assumptions!$C$26+((ROUND(Assumptions!H27*$B$8,0)+ROUND(Assumptions!I27*$B$8,0))/2)*Assumptions!$C$27+((ROUND(Assumptions!H28*$B$8,0)+ROUND(Assumptions!I28*$B$8,0))/2)*Assumptions!$C$28)*(1+Assumptions!$B$4)^5/1000 | H17: =(((Assumptions!I20+Assumptions!J20)/2)*Assumptions!$C$20+((ROUND(Assumptions!I21*$B$8,0)+ROUND(Assumptions!J21*$B$8,0))/2)*Assumptions!$C$21+((ROUND(Assumptions!I22*$B$8,0)+ROUND(Assumptions!J22*$B$8,0))/2)*Assumptions!$C$22+((ROUND(Assumptions!I23*$B$8,0)+ROUND(Assumptions!J23*$B$8,0))/2)*Assumptions!$C$23+((ROUND(Assumptions!I24*$B$8,0)+ROUND(Assumptions!J24*$B$8,0))/2)*Assumptions!$C$24+((ROUND(Assumptions!I25*$B$8,0)+ROUND(Assumptions!J25*$B$8,0))/2)*Assumptions!$C$25+((ROUND(Assumptions!I26*$B$8,0)+ROUND(Assumptions!J26*$B$8,0))/2)*Assumptions!$C$26+((ROUND(Assumptions!I27*$B$8,0)+ROUND(Assumptions!J27*$B$8,0))/2)*Assumptions!$C$27+((ROUND(Assumptions!I28*$B$8,0)+ROUND(Assumptions!J28*$B$8,0))/2)*Assumptions!$C$28)*(1+Assumptions!$B$4)^6/1000
A18: Other operating costs | B18: =SUM(Assumptions!D32:D37)*1/1000 | C18: =SUM(Assumptions!E32:E37)*$B$8/1000 | D18: =SUM(Assumptions!F32:F37)*$B$8/1000 | E18: =SUM(Assumptions!G32:G37)*$B$8/1000 | F18: =SUM(Assumptions!H32:H37)*$B$8/1000 | G18: =SUM(Assumptions!I32:I37)*$B$8/1000 | H18: =SUM(Assumptions!J32:J37)*$B$8/1000
A19: Total operating costs | B19: =B17+B18 | C19: =C17+C18 | D19: =D17+D18 | E19: =E17+E18 | F19: =F17+F18 | G19: =G17+G18 | H19: =H17+H18
A20: EBITDA | B20: =B16-B19 | C20: =C16-C19 | D20: =D16-D19 | E20: =E16-E19 | F20: =F16-F19 | G20: =G16-G19 | H20: =H16-H19
A21: EBITDA margin | B21: =IF(B14=0,0,B20/B14) | C21: =IF(C14=0,0,C20/C14) | D21: =IF(D14=0,0,D20/D14) | E21: =IF(E14=0,0,E20/E14) | F21: =IF(F14=0,0,F20/F14) | G21: =IF(G14=0,0,G20/G14) | H21: =IF(H14=0,0,H20/H14)
A22: ARR at year end | B22: =B10*B11/1000 | C22: =C10*C11/1000 | D22: =D10*D11/1000 | E22: =E10*E11/1000 | F22: =F10*F11/1000 | G22: =G10*G11/1000 | H22: =H10*H11/1000
A23: Headcount at year end | B23: =Assumptions!D20+ROUND(Assumptions!D21*$B$8,0)+ROUND(Assumptions!D22*$B$8,0)+ROUND(Assumptions!D23*$B$8,0)+ROUND(Assumptions!D24*$B$8,0)+ROUND(Assumptions!D25*$B$8,0)+ROUND(Assumptions!D26*$B$8,0)+ROUND(Assumptions!D27*$B$8,0)+ROUND(Assumptions!D28*$B$8,0) | C23: =Assumptions!E20+ROUND(Assumptions!E21*$B$8,0)+ROUND(Assumptions!E22*$B$8,0)+ROUND(Assumptions!E23*$B$8,0)+ROUND(Assumptions!E24*$B$8,0)+ROUND(Assumptions!E25*$B$8,0)+ROUND(Assumptions!E26*$B$8,0)+ROUND(Assumptions!E27*$B$8,0)+ROUND(Assumptions!E28*$B$8,0) | D23: =Assumptions!F20+ROUND(Assumptions!F21*$B$8,0)+ROUND(Assumptions!F22*$B$8,0)+ROUND(Assumptions!F23*$B$8,0)+ROUND(Assumptions!F24*$B$8,0)+ROUND(Assumptions!F25*$B$8,0)+ROUND(Assumptions!F26*$B$8,0)+ROUND(Assumptions!F27*$B$8,0)+ROUND(Assumptions!F28*$B$8,0) | E23: =Assumptions!G20+ROUND(Assumptions!G21*$B$8,0)+ROUND(Assumptions!G22*$B$8,0)+ROUND(Assumptions!G23*$B$8,0)+ROUND(Assumptions!G24*$B$8,0)+ROUND(Assumptions!G25*$B$8,0)+ROUND(Assumptions!G26*$B$8,0)+ROUND(Assumptions!G27*$B$8,0)+ROUND(Assumptions!G28*$B$8,0) | F23: =Assumptions!H20+ROUND(Assumptions!H21*$B$8,0)+ROUND(Assumptions!H22*$B$8,0)+ROUND(Assumptions!H23*$B$8,0)+ROUND(Assumptions!H24*$B$8,0)+ROUND(Assumptions!H25*$B$8,0)+ROUND(Assumptions!H26*$B$8,0)+ROUND(Assumptions!H27*$B$8,0)+ROUND(Assumptions!H28*$B$8,0) | G23: =Assumptions!I20+ROUND(Assumptions!I21*$B$8,0)+ROUND(Assumptions!I22*$B$8,0)+ROUND(Assumptions!I23*$B$8,0)+ROUND(Assumptions!I24*$B$8,0)+ROUND(Assumptions!I25*$B$8,0)+ROUND(Assumptions!I26*$B$8,0)+ROUND(Assumptions!I27*$B$8,0)+ROUND(Assumptions!I28*$B$8,0) | H23: =Assumptions!J20+ROUND(Assumptions!J21*$B$8,0)+ROUND(Assumptions!J22*$B$8,0)+ROUND(Assumptions!J23*$B$8,0)+ROUND(Assumptions!J24*$B$8,0)+ROUND(Assumptions!J25*$B$8,0)+ROUND(Assumptions!J26*$B$8,0)+ROUND(Assumptions!J27*$B$8,0)+ROUND(Assumptions!J28*$B$8,0)
A24: Sales and marketing cost | B24: =((ROUND(Assumptions!D24*$B$8,0)*0.6)*Assumptions!$C$24+(ROUND(Assumptions!D25*$B$8,0)*0.6)*Assumptions!$C$25+(ROUND(Assumptions!D27*$B$8,0)*0.6)*Assumptions!$C$27)*(1+Assumptions!$B$4)^0/1000+(Assumptions!D35+Assumptions!D36)*1/1000 | C24: =(((ROUND(Assumptions!D24*$B$8,0)+ROUND(Assumptions!E24*$B$8,0))/2)*Assumptions!$C$24+((ROUND(Assumptions!D25*$B$8,0)+ROUND(Assumptions!E25*$B$8,0))/2)*Assumptions!$C$25+((ROUND(Assumptions!D27*$B$8,0)+ROUND(Assumptions!E27*$B$8,0))/2)*Assumptions!$C$27)*(1+Assumptions!$B$4)^1/1000+(Assumptions!E35+Assumptions!E36)*$B$8/1000 | D24: =(((ROUND(Assumptions!E24*$B$8,0)+ROUND(Assumptions!F24*$B$8,0))/2)*Assumptions!$C$24+((ROUND(Assumptions!E25*$B$8,0)+ROUND(Assumptions!F25*$B$8,0))/2)*Assumptions!$C$25+((ROUND(Assumptions!E27*$B$8,0)+ROUND(Assumptions!F27*$B$8,0))/2)*Assumptions!$C$27)*(1+Assumptions!$B$4)^2/1000+(Assumptions!F35+Assumptions!F36)*$B$8/1000 | E24: =(((ROUND(Assumptions!F24*$B$8,0)+ROUND(Assumptions!G24*$B$8,0))/2)*Assumptions!$C$24+((ROUND(Assumptions!F25*$B$8,0)+ROUND(Assumptions!G25*$B$8,0))/2)*Assumptions!$C$25+((ROUND(Assumptions!F27*$B$8,0)+ROUND(Assumptions!G27*$B$8,0))/2)*Assumptions!$C$27)*(1+Assumptions!$B$4)^3/1000+(Assumptions!G35+Assumptions!G36)*$B$8/1000 | F24: =(((ROUND(Assumptions!G24*$B$8,0)+ROUND(Assumptions!H24*$B$8,0))/2)*Assumptions!$C$24+((ROUND(Assumptions!G25*$B$8,0)+ROUND(Assumptions!H25*$B$8,0))/2)*Assumptions!$C$25+((ROUND(Assumptions!G27*$B$8,0)+ROUND(Assumptions!H27*$B$8,0))/2)*Assumptions!$C$27)*(1+Assumptions!$B$4)^4/1000+(Assumptions!H35+Assumptions!H36)*$B$8/1000 | G24: =(((ROUND(Assumptions!H24*$B$8,0)+ROUND(Assumptions!I24*$B$8,0))/2)*Assumptions!$C$24+((ROUND(Assumptions!H25*$B$8,0)+ROUND(Assumptions!I25*$B$8,0))/2)*Assumptions!$C$25+((ROUND(Assumptions!H27*$B$8,0)+ROUND(Assumptions!I27*$B$8,0))/2)*Assumptions!$C$27)*(1+Assumptions!$B$4)^5/1000+(Assumptions!I35+Assumptions!I36)*$B$8/1000 | H24: =(((ROUND(Assumptions!I24*$B$8,0)+ROUND(Assumptions!J24*$B$8,0))/2)*Assumptions!$C$24+((ROUND(Assumptions!I25*$B$8,0)+ROUND(Assumptions!J25*$B$8,0))/2)*Assumptions!$C$25+((ROUND(Assumptions!I27*$B$8,0)+ROUND(Assumptions!J27*$B$8,0))/2)*Assumptions!$C$27)*(1+Assumptions!$B$4)^6/1000+(Assumptions!J35+Assumptions!J36)*$B$8/1000
A25: Sales and marketing cost per $1 of new ARR | B25: =IF(B5=0,0,B24/(B5*B11/1000)) | C25: =IF(C5=0,0,C24/(C5*C11/1000)) | D25: =IF(D5=0,0,D24/(D5*D11/1000)) | E25: =IF(E5=0,0,E24/(E5*E11/1000)) | F25: =IF(F5=0,0,F24/(F5*F11/1000)) | G25: =IF(G5=0,0,G24/(G5*G11/1000)) | H25: =IF(H5=0,0,H24/(H5*H11/1000)) | I25: 2024 median $2.00 (Benchmarkit 2025 report, B); key plan risk

Sheet Base
A1: Base case
A2: Design partners convert, importers add the container-fee and fuel checks, a broker channel opens in year 2 and a factoring partner adds carrier volume from year 3.
A4: $M unless stated | B4: Y1 | C4: Y2 | D4: Y3 | E4: Y4 | F4: Y5 | G4: Y6 | H4: Y7 | I4: Note
A5: New accounts won | B5: 6 | C5: 30 | D5: 75 | E5: 120 | F5: 165 | G5: 200 | H5: 235 | I5: Plan input (C)
A6: Annual account churn | B6: 0.2 | I6: Share of accounts at the start of a year lost during it (C); median gross revenue retention 88% (Benchmarkit, B)
A7: Revenue per account vs base | B7: 1
A8: Cost scale vs base headcount and spend | B8: 1
A9: Accounts lost in year | B9: =0 | C9: =ROUND(B10*$B$6,0) | D9: =ROUND(C10*$B$6,0) | E9: =ROUND(D10*$B$6,0) | F9: =ROUND(E10*$B$6,0) | G9: =ROUND(F10*$B$6,0) | H9: =ROUND(G10*$B$6,0)
A10: Paying accounts at year end | B10: =B5 | C10: =B10-C9+C5 | D10: =C10-D9+D5 | E10: =D10-E9+E5 | F10: =E10-F9+F5 | G10: =F10-G9+G5 | H10: =G10-H9+H5
A11: Revenue per account ($K) | B11: =Assumptions!B16*$B$7 | C11: =Assumptions!C16*$B$7 | D11: =Assumptions!D16*$B$7 | E11: =Assumptions!E16*$B$7 | F11: =Assumptions!F16*$B$7 | G11: =Assumptions!G16*$B$7 | H11: =Assumptions!H16*$B$7
A12: Gross margin | B12: 0.5 | C12: 0.58 | D12: 0.64 | E12: 0.68 | F12: 0.71 | G12: 0.73 | H12: 0.74 | I12: After hosting, data feeds and claim review labour (C)
A14: Revenue | B14: =(0+B10)/2*B11/1000 | C14: =(B10+C10)/2*C11/1000 | D14: =(C10+D10)/2*D11/1000 | E14: =(D10+E10)/2*E11/1000 | F14: =(E10+F10)/2*F11/1000 | G14: =(F10+G10)/2*G11/1000 | H14: =(G10+H10)/2*H11/1000
A15: Cost of revenue | B15: =B14*(1-B12) | C15: =C14*(1-C12) | D15: =D14*(1-D12) | E15: =E14*(1-E12) | F15: =F14*(1-F12) | G15: =G14*(1-G12) | H15: =H14*(1-H12)
A16: Gross profit | B16: =B14-B15 | C16: =C14-C15 | D16: =D14-D15 | E16: =E14-E15 | F16: =F14-F15 | G16: =G14-G15 | H16: =H14-H15
A17: People costs | B17: =(Assumptions!D20*Assumptions!$C$20+(ROUND(Assumptions!D21*$B$8,0)*0.6)*Assumptions!$C$21+(ROUND(Assumptions!D22*$B$8,0)*0.6)*Assumptions!$C$22+(ROUND(Assumptions!D23*$B$8,0)*0.6)*Assumptions!$C$23+(ROUND(Assumptions!D24*$B$8,0)*0.6)*Assumptions!$C$24+(ROUND(Assumptions!D25*$B$8,0)*0.6)*Assumptions!$C$25+(ROUND(Assumptions!D26*$B$8,0)*0.6)*Assumptions!$C$26+(ROUND(Assumptions!D27*$B$8,0)*0.6)*Assumptions!$C$27+(ROUND(Assumptions!D28*$B$8,0)*0.6)*Assumptions!$C$28)*(1+Assumptions!$B$4)^0/1000 | C17: =(((Assumptions!D20+Assumptions!E20)/2)*Assumptions!$C$20+((ROUND(Assumptions!D21*$B$8,0)+ROUND(Assumptions!E21*$B$8,0))/2)*Assumptions!$C$21+((ROUND(Assumptions!D22*$B$8,0)+ROUND(Assumptions!E22*$B$8,0))/2)*Assumptions!$C$22+((ROUND(Assumptions!D23*$B$8,0)+ROUND(Assumptions!E23*$B$8,0))/2)*Assumptions!$C$23+((ROUND(Assumptions!D24*$B$8,0)+ROUND(Assumptions!E24*$B$8,0))/2)*Assumptions!$C$24+((ROUND(Assumptions!D25*$B$8,0)+ROUND(Assumptions!E25*$B$8,0))/2)*Assumptions!$C$25+((ROUND(Assumptions!D26*$B$8,0)+ROUND(Assumptions!E26*$B$8,0))/2)*Assumptions!$C$26+((ROUND(Assumptions!D27*$B$8,0)+ROUND(Assumptions!E27*$B$8,0))/2)*Assumptions!$C$27+((ROUND(Assumptions!D28*$B$8,0)+ROUND(Assumptions!E28*$B$8,0))/2)*Assumptions!$C$28)*(1+Assumptions!$B$4)^1/1000 | D17: =(((Assumptions!E20+Assumptions!F20)/2)*Assumptions!$C$20+((ROUND(Assumptions!E21*$B$8,0)+ROUND(Assumptions!F21*$B$8,0))/2)*Assumptions!$C$21+((ROUND(Assumptions!E22*$B$8,0)+ROUND(Assumptions!F22*$B$8,0))/2)*Assumptions!$C$22+((ROUND(Assumptions!E23*$B$8,0)+ROUND(Assumptions!F23*$B$8,0))/2)*Assumptions!$C$23+((ROUND(Assumptions!E24*$B$8,0)+ROUND(Assumptions!F24*$B$8,0))/2)*Assumptions!$C$24+((ROUND(Assumptions!E25*$B$8,0)+ROUND(Assumptions!F25*$B$8,0))/2)*Assumptions!$C$25+((ROUND(Assumptions!E26*$B$8,0)+ROUND(Assumptions!F26*$B$8,0))/2)*Assumptions!$C$26+((ROUND(Assumptions!E27*$B$8,0)+ROUND(Assumptions!F27*$B$8,0))/2)*Assumptions!$C$27+((ROUND(Assumptions!E28*$B$8,0)+ROUND(Assumptions!F28*$B$8,0))/2)*Assumptions!$C$28)*(1+Assumptions!$B$4)^2/1000 | E17: =(((Assumptions!F20+Assumptions!G20)/2)*Assumptions!$C$20+((ROUND(Assumptions!F21*$B$8,0)+ROUND(Assumptions!G21*$B$8,0))/2)*Assumptions!$C$21+((ROUND(Assumptions!F22*$B$8,0)+ROUND(Assumptions!G22*$B$8,0))/2)*Assumptions!$C$22+((ROUND(Assumptions!F23*$B$8,0)+ROUND(Assumptions!G23*$B$8,0))/2)*Assumptions!$C$23+((ROUND(Assumptions!F24*$B$8,0)+ROUND(Assumptions!G24*$B$8,0))/2)*Assumptions!$C$24+((ROUND(Assumptions!F25*$B$8,0)+ROUND(Assumptions!G25*$B$8,0))/2)*Assumptions!$C$25+((ROUND(Assumptions!F26*$B$8,0)+ROUND(Assumptions!G26*$B$8,0))/2)*Assumptions!$C$26+((ROUND(Assumptions!F27*$B$8,0)+ROUND(Assumptions!G27*$B$8,0))/2)*Assumptions!$C$27+((ROUND(Assumptions!F28*$B$8,0)+ROUND(Assumptions!G28*$B$8,0))/2)*Assumptions!$C$28)*(1+Assumptions!$B$4)^3/1000 | F17: =(((Assumptions!G20+Assumptions!H20)/2)*Assumptions!$C$20+((ROUND(Assumptions!G21*$B$8,0)+ROUND(Assumptions!H21*$B$8,0))/2)*Assumptions!$C$21+((ROUND(Assumptions!G22*$B$8,0)+ROUND(Assumptions!H22*$B$8,0))/2)*Assumptions!$C$22+((ROUND(Assumptions!G23*$B$8,0)+ROUND(Assumptions!H23*$B$8,0))/2)*Assumptions!$C$23+((ROUND(Assumptions!G24*$B$8,0)+ROUND(Assumptions!H24*$B$8,0))/2)*Assumptions!$C$24+((ROUND(Assumptions!G25*$B$8,0)+ROUND(Assumptions!H25*$B$8,0))/2)*Assumptions!$C$25+((ROUND(Assumptions!G26*$B$8,0)+ROUND(Assumptions!H26*$B$8,0))/2)*Assumptions!$C$26+((ROUND(Assumptions!G27*$B$8,0)+ROUND(Assumptions!H27*$B$8,0))/2)*Assumptions!$C$27+((ROUND(Assumptions!G28*$B$8,0)+ROUND(Assumptions!H28*$B$8,0))/2)*Assumptions!$C$28)*(1+Assumptions!$B$4)^4/1000 | G17: =(((Assumptions!H20+Assumptions!I20)/2)*Assumptions!$C$20+((ROUND(Assumptions!H21*$B$8,0)+ROUND(Assumptions!I21*$B$8,0))/2)*Assumptions!$C$21+((ROUND(Assumptions!H22*$B$8,0)+ROUND(Assumptions!I22*$B$8,0))/2)*Assumptions!$C$22+((ROUND(Assumptions!H23*$B$8,0)+ROUND(Assumptions!I23*$B$8,0))/2)*Assumptions!$C$23+((ROUND(Assumptions!H24*$B$8,0)+ROUND(Assumptions!I24*$B$8,0))/2)*Assumptions!$C$24+((ROUND(Assumptions!H25*$B$8,0)+ROUND(Assumptions!I25*$B$8,0))/2)*Assumptions!$C$25+((ROUND(Assumptions!H26*$B$8,0)+ROUND(Assumptions!I26*$B$8,0))/2)*Assumptions!$C$26+((ROUND(Assumptions!H27*$B$8,0)+ROUND(Assumptions!I27*$B$8,0))/2)*Assumptions!$C$27+((ROUND(Assumptions!H28*$B$8,0)+ROUND(Assumptions!I28*$B$8,0))/2)*Assumptions!$C$28)*(1+Assumptions!$B$4)^5/1000 | H17: =(((Assumptions!I20+Assumptions!J20)/2)*Assumptions!$C$20+((ROUND(Assumptions!I21*$B$8,0)+ROUND(Assumptions!J21*$B$8,0))/2)*Assumptions!$C$21+((ROUND(Assumptions!I22*$B$8,0)+ROUND(Assumptions!J22*$B$8,0))/2)*Assumptions!$C$22+((ROUND(Assumptions!I23*$B$8,0)+ROUND(Assumptions!J23*$B$8,0))/2)*Assumptions!$C$23+((ROUND(Assumptions!I24*$B$8,0)+ROUND(Assumptions!J24*$B$8,0))/2)*Assumptions!$C$24+((ROUND(Assumptions!I25*$B$8,0)+ROUND(Assumptions!J25*$B$8,0))/2)*Assumptions!$C$25+((ROUND(Assumptions!I26*$B$8,0)+ROUND(Assumptions!J26*$B$8,0))/2)*Assumptions!$C$26+((ROUND(Assumptions!I27*$B$8,0)+ROUND(Assumptions!J27*$B$8,0))/2)*Assumptions!$C$27+((ROUND(Assumptions!I28*$B$8,0)+ROUND(Assumptions!J28*$B$8,0))/2)*Assumptions!$C$28)*(1+Assumptions!$B$4)^6/1000
A18: Other operating costs | B18: =SUM(Assumptions!D32:D37)*1/1000 | C18: =SUM(Assumptions!E32:E37)*$B$8/1000 | D18: =SUM(Assumptions!F32:F37)*$B$8/1000 | E18: =SUM(Assumptions!G32:G37)*$B$8/1000 | F18: =SUM(Assumptions!H32:H37)*$B$8/1000 | G18: =SUM(Assumptions!I32:I37)*$B$8/1000 | H18: =SUM(Assumptions!J32:J37)*$B$8/1000
A19: Total operating costs | B19: =B17+B18 | C19: =C17+C18 | D19: =D17+D18 | E19: =E17+E18 | F19: =F17+F18 | G19: =G17+G18 | H19: =H17+H18
A20: EBITDA | B20: =B16-B19 | C20: =C16-C19 | D20: =D16-D19 | E20: =E16-E19 | F20: =F16-F19 | G20: =G16-G19 | H20: =H16-H19
A21: EBITDA margin | B21: =IF(B14=0,0,B20/B14) | C21: =IF(C14=0,0,C20/C14) | D21: =IF(D14=0,0,D20/D14) | E21: =IF(E14=0,0,E20/E14) | F21: =IF(F14=0,0,F20/F14) | G21: =IF(G14=0,0,G20/G14) | H21: =IF(H14=0,0,H20/H14)
A22: ARR at year end | B22: =B10*B11/1000 | C22: =C10*C11/1000 | D22: =D10*D11/1000 | E22: =E10*E11/1000 | F22: =F10*F11/1000 | G22: =G10*G11/1000 | H22: =H10*H11/1000
A23: Headcount at year end | B23: =Assumptions!D20+ROUND(Assumptions!D21*$B$8,0)+ROUND(Assumptions!D22*$B$8,0)+ROUND(Assumptions!D23*$B$8,0)+ROUND(Assumptions!D24*$B$8,0)+ROUND(Assumptions!D25*$B$8,0)+ROUND(Assumptions!D26*$B$8,0)+ROUND(Assumptions!D27*$B$8,0)+ROUND(Assumptions!D28*$B$8,0) | C23: =Assumptions!E20+ROUND(Assumptions!E21*$B$8,0)+ROUND(Assumptions!E22*$B$8,0)+ROUND(Assumptions!E23*$B$8,0)+ROUND(Assumptions!E24*$B$8,0)+ROUND(Assumptions!E25*$B$8,0)+ROUND(Assumptions!E26*$B$8,0)+ROUND(Assumptions!E27*$B$8,0)+ROUND(Assumptions!E28*$B$8,0) | D23: =Assumptions!F20+ROUND(Assumptions!F21*$B$8,0)+ROUND(Assumptions!F22*$B$8,0)+ROUND(Assumptions!F23*$B$8,0)+ROUND(Assumptions!F24*$B$8,0)+ROUND(Assumptions!F25*$B$8,0)+ROUND(Assumptions!F26*$B$8,0)+ROUND(Assumptions!F27*$B$8,0)+ROUND(Assumptions!F28*$B$8,0) | E23: =Assumptions!G20+ROUND(Assumptions!G21*$B$8,0)+ROUND(Assumptions!G22*$B$8,0)+ROUND(Assumptions!G23*$B$8,0)+ROUND(Assumptions!G24*$B$8,0)+ROUND(Assumptions!G25*$B$8,0)+ROUND(Assumptions!G26*$B$8,0)+ROUND(Assumptions!G27*$B$8,0)+ROUND(Assumptions!G28*$B$8,0) | F23: =Assumptions!H20+ROUND(Assumptions!H21*$B$8,0)+ROUND(Assumptions!H22*$B$8,0)+ROUND(Assumptions!H23*$B$8,0)+ROUND(Assumptions!H24*$B$8,0)+ROUND(Assumptions!H25*$B$8,0)+ROUND(Assumptions!H26*$B$8,0)+ROUND(Assumptions!H27*$B$8,0)+ROUND(Assumptions!H28*$B$8,0) | G23: =Assumptions!I20+ROUND(Assumptions!I21*$B$8,0)+ROUND(Assumptions!I22*$B$8,0)+ROUND(Assumptions!I23*$B$8,0)+ROUND(Assumptions!I24*$B$8,0)+ROUND(Assumptions!I25*$B$8,0)+ROUND(Assumptions!I26*$B$8,0)+ROUND(Assumptions!I27*$B$8,0)+ROUND(Assumptions!I28*$B$8,0) | H23: =Assumptions!J20+ROUND(Assumptions!J21*$B$8,0)+ROUND(Assumptions!J22*$B$8,0)+ROUND(Assumptions!J23*$B$8,0)+ROUND(Assumptions!J24*$B$8,0)+ROUND(Assumptions!J25*$B$8,0)+ROUND(Assumptions!J26*$B$8,0)+ROUND(Assumptions!J27*$B$8,0)+ROUND(Assumptions!J28*$B$8,0)
A24: Sales and marketing cost | B24: =((ROUND(Assumptions!D24*$B$8,0)*0.6)*Assumptions!$C$24+(ROUND(Assumptions!D25*$B$8,0)*0.6)*Assumptions!$C$25+(ROUND(Assumptions!D27*$B$8,0)*0.6)*Assumptions!$C$27)*(1+Assumptions!$B$4)^0/1000+(Assumptions!D35+Assumptions!D36)*1/1000 | C24: =(((ROUND(Assumptions!D24*$B$8,0)+ROUND(Assumptions!E24*$B$8,0))/2)*Assumptions!$C$24+((ROUND(Assumptions!D25*$B$8,0)+ROUND(Assumptions!E25*$B$8,0))/2)*Assumptions!$C$25+((ROUND(Assumptions!D27*$B$8,0)+ROUND(Assumptions!E27*$B$8,0))/2)*Assumptions!$C$27)*(1+Assumptions!$B$4)^1/1000+(Assumptions!E35+Assumptions!E36)*$B$8/1000 | D24: =(((ROUND(Assumptions!E24*$B$8,0)+ROUND(Assumptions!F24*$B$8,0))/2)*Assumptions!$C$24+((ROUND(Assumptions!E25*$B$8,0)+ROUND(Assumptions!F25*$B$8,0))/2)*Assumptions!$C$25+((ROUND(Assumptions!E27*$B$8,0)+ROUND(Assumptions!F27*$B$8,0))/2)*Assumptions!$C$27)*(1+Assumptions!$B$4)^2/1000+(Assumptions!F35+Assumptions!F36)*$B$8/1000 | E24: =(((ROUND(Assumptions!F24*$B$8,0)+ROUND(Assumptions!G24*$B$8,0))/2)*Assumptions!$C$24+((ROUND(Assumptions!F25*$B$8,0)+ROUND(Assumptions!G25*$B$8,0))/2)*Assumptions!$C$25+((ROUND(Assumptions!F27*$B$8,0)+ROUND(Assumptions!G27*$B$8,0))/2)*Assumptions!$C$27)*(1+Assumptions!$B$4)^3/1000+(Assumptions!G35+Assumptions!G36)*$B$8/1000 | F24: =(((ROUND(Assumptions!G24*$B$8,0)+ROUND(Assumptions!H24*$B$8,0))/2)*Assumptions!$C$24+((ROUND(Assumptions!G25*$B$8,0)+ROUND(Assumptions!H25*$B$8,0))/2)*Assumptions!$C$25+((ROUND(Assumptions!G27*$B$8,0)+ROUND(Assumptions!H27*$B$8,0))/2)*Assumptions!$C$27)*(1+Assumptions!$B$4)^4/1000+(Assumptions!H35+Assumptions!H36)*$B$8/1000 | G24: =(((ROUND(Assumptions!H24*$B$8,0)+ROUND(Assumptions!I24*$B$8,0))/2)*Assumptions!$C$24+((ROUND(Assumptions!H25*$B$8,0)+ROUND(Assumptions!I25*$B$8,0))/2)*Assumptions!$C$25+((ROUND(Assumptions!H27*$B$8,0)+ROUND(Assumptions!I27*$B$8,0))/2)*Assumptions!$C$27)*(1+Assumptions!$B$4)^5/1000+(Assumptions!I35+Assumptions!I36)*$B$8/1000 | H24: =(((ROUND(Assumptions!I24*$B$8,0)+ROUND(Assumptions!J24*$B$8,0))/2)*Assumptions!$C$24+((ROUND(Assumptions!I25*$B$8,0)+ROUND(Assumptions!J25*$B$8,0))/2)*Assumptions!$C$25+((ROUND(Assumptions!I27*$B$8,0)+ROUND(Assumptions!J27*$B$8,0))/2)*Assumptions!$C$27)*(1+Assumptions!$B$4)^6/1000+(Assumptions!J35+Assumptions!J36)*$B$8/1000
A25: Sales and marketing cost per $1 of new ARR | B25: =IF(B5=0,0,B24/(B5*B11/1000)) | C25: =IF(C5=0,0,C24/(C5*C11/1000)) | D25: =IF(D5=0,0,D24/(D5*D11/1000)) | E25: =IF(E5=0,0,E24/(E5*E11/1000)) | F25: =IF(F5=0,0,F24/(F5*F11/1000)) | G25: =IF(G5=0,0,G24/(G5*G11/1000)) | H25: =IF(H5=0,0,H24/(H5*H11/1000)) | I25: 2024 median $2.00 (Benchmarkit 2025 report, B); key plan risk

Sheet Upside
A1: Upside case
A2: A factoring or ELD distribution partner is signed in year 2, the platform fee is adopted early and importers extend checks from one port to their whole network.
A4: $M unless stated | B4: Y1 | C4: Y2 | D4: Y3 | E4: Y4 | F4: Y5 | G4: Y6 | H4: Y7 | I4: Note
A5: New accounts won | B5: 8 | C5: 40 | D5: 100 | E5: 160 | F5: 215 | G5: 260 | H5: 300 | I5: Plan input (C)
A6: Annual account churn | B6: 0.15 | I6: Share of accounts at the start of a year lost during it (C); median gross revenue retention 88% (Benchmarkit, B)
A7: Revenue per account vs base | B7: 1.15
A8: Cost scale vs base headcount and spend | B8: 1.1
A9: Accounts lost in year | B9: =0 | C9: =ROUND(B10*$B$6,0) | D9: =ROUND(C10*$B$6,0) | E9: =ROUND(D10*$B$6,0) | F9: =ROUND(E10*$B$6,0) | G9: =ROUND(F10*$B$6,0) | H9: =ROUND(G10*$B$6,0)
A10: Paying accounts at year end | B10: =B5 | C10: =B10-C9+C5 | D10: =C10-D9+D5 | E10: =D10-E9+E5 | F10: =E10-F9+F5 | G10: =F10-G9+G5 | H10: =G10-H9+H5
A11: Revenue per account ($K) | B11: =Assumptions!B16*$B$7 | C11: =Assumptions!C16*$B$7 | D11: =Assumptions!D16*$B$7 | E11: =Assumptions!E16*$B$7 | F11: =Assumptions!F16*$B$7 | G11: =Assumptions!G16*$B$7 | H11: =Assumptions!H16*$B$7
A12: Gross margin | B12: 0.55 | C12: 0.62 | D12: 0.68 | E12: 0.72 | F12: 0.75 | G12: 0.77 | H12: 0.78 | I12: After hosting, data feeds and claim review labour (C)
A14: Revenue | B14: =(0+B10)/2*B11/1000 | C14: =(B10+C10)/2*C11/1000 | D14: =(C10+D10)/2*D11/1000 | E14: =(D10+E10)/2*E11/1000 | F14: =(E10+F10)/2*F11/1000 | G14: =(F10+G10)/2*G11/1000 | H14: =(G10+H10)/2*H11/1000
A15: Cost of revenue | B15: =B14*(1-B12) | C15: =C14*(1-C12) | D15: =D14*(1-D12) | E15: =E14*(1-E12) | F15: =F14*(1-F12) | G15: =G14*(1-G12) | H15: =H14*(1-H12)
A16: Gross profit | B16: =B14-B15 | C16: =C14-C15 | D16: =D14-D15 | E16: =E14-E15 | F16: =F14-F15 | G16: =G14-G15 | H16: =H14-H15
A17: People costs | B17: =(Assumptions!D20*Assumptions!$C$20+(ROUND(Assumptions!D21*$B$8,0)*0.6)*Assumptions!$C$21+(ROUND(Assumptions!D22*$B$8,0)*0.6)*Assumptions!$C$22+(ROUND(Assumptions!D23*$B$8,0)*0.6)*Assumptions!$C$23+(ROUND(Assumptions!D24*$B$8,0)*0.6)*Assumptions!$C$24+(ROUND(Assumptions!D25*$B$8,0)*0.6)*Assumptions!$C$25+(ROUND(Assumptions!D26*$B$8,0)*0.6)*Assumptions!$C$26+(ROUND(Assumptions!D27*$B$8,0)*0.6)*Assumptions!$C$27+(ROUND(Assumptions!D28*$B$8,0)*0.6)*Assumptions!$C$28)*(1+Assumptions!$B$4)^0/1000 | C17: =(((Assumptions!D20+Assumptions!E20)/2)*Assumptions!$C$20+((ROUND(Assumptions!D21*$B$8,0)+ROUND(Assumptions!E21*$B$8,0))/2)*Assumptions!$C$21+((ROUND(Assumptions!D22*$B$8,0)+ROUND(Assumptions!E22*$B$8,0))/2)*Assumptions!$C$22+((ROUND(Assumptions!D23*$B$8,0)+ROUND(Assumptions!E23*$B$8,0))/2)*Assumptions!$C$23+((ROUND(Assumptions!D24*$B$8,0)+ROUND(Assumptions!E24*$B$8,0))/2)*Assumptions!$C$24+((ROUND(Assumptions!D25*$B$8,0)+ROUND(Assumptions!E25*$B$8,0))/2)*Assumptions!$C$25+((ROUND(Assumptions!D26*$B$8,0)+ROUND(Assumptions!E26*$B$8,0))/2)*Assumptions!$C$26+((ROUND(Assumptions!D27*$B$8,0)+ROUND(Assumptions!E27*$B$8,0))/2)*Assumptions!$C$27+((ROUND(Assumptions!D28*$B$8,0)+ROUND(Assumptions!E28*$B$8,0))/2)*Assumptions!$C$28)*(1+Assumptions!$B$4)^1/1000 | D17: =(((Assumptions!E20+Assumptions!F20)/2)*Assumptions!$C$20+((ROUND(Assumptions!E21*$B$8,0)+ROUND(Assumptions!F21*$B$8,0))/2)*Assumptions!$C$21+((ROUND(Assumptions!E22*$B$8,0)+ROUND(Assumptions!F22*$B$8,0))/2)*Assumptions!$C$22+((ROUND(Assumptions!E23*$B$8,0)+ROUND(Assumptions!F23*$B$8,0))/2)*Assumptions!$C$23+((ROUND(Assumptions!E24*$B$8,0)+ROUND(Assumptions!F24*$B$8,0))/2)*Assumptions!$C$24+((ROUND(Assumptions!E25*$B$8,0)+ROUND(Assumptions!F25*$B$8,0))/2)*Assumptions!$C$25+((ROUND(Assumptions!E26*$B$8,0)+ROUND(Assumptions!F26*$B$8,0))/2)*Assumptions!$C$26+((ROUND(Assumptions!E27*$B$8,0)+ROUND(Assumptions!F27*$B$8,0))/2)*Assumptions!$C$27+((ROUND(Assumptions!E28*$B$8,0)+ROUND(Assumptions!F28*$B$8,0))/2)*Assumptions!$C$28)*(1+Assumptions!$B$4)^2/1000 | E17: =(((Assumptions!F20+Assumptions!G20)/2)*Assumptions!$C$20+((ROUND(Assumptions!F21*$B$8,0)+ROUND(Assumptions!G21*$B$8,0))/2)*Assumptions!$C$21+((ROUND(Assumptions!F22*$B$8,0)+ROUND(Assumptions!G22*$B$8,0))/2)*Assumptions!$C$22+((ROUND(Assumptions!F23*$B$8,0)+ROUND(Assumptions!G23*$B$8,0))/2)*Assumptions!$C$23+((ROUND(Assumptions!F24*$B$8,0)+ROUND(Assumptions!G24*$B$8,0))/2)*Assumptions!$C$24+((ROUND(Assumptions!F25*$B$8,0)+ROUND(Assumptions!G25*$B$8,0))/2)*Assumptions!$C$25+((ROUND(Assumptions!F26*$B$8,0)+ROUND(Assumptions!G26*$B$8,0))/2)*Assumptions!$C$26+((ROUND(Assumptions!F27*$B$8,0)+ROUND(Assumptions!G27*$B$8,0))/2)*Assumptions!$C$27+((ROUND(Assumptions!F28*$B$8,0)+ROUND(Assumptions!G28*$B$8,0))/2)*Assumptions!$C$28)*(1+Assumptions!$B$4)^3/1000 | F17: =(((Assumptions!G20+Assumptions!H20)/2)*Assumptions!$C$20+((ROUND(Assumptions!G21*$B$8,0)+ROUND(Assumptions!H21*$B$8,0))/2)*Assumptions!$C$21+((ROUND(Assumptions!G22*$B$8,0)+ROUND(Assumptions!H22*$B$8,0))/2)*Assumptions!$C$22+((ROUND(Assumptions!G23*$B$8,0)+ROUND(Assumptions!H23*$B$8,0))/2)*Assumptions!$C$23+((ROUND(Assumptions!G24*$B$8,0)+ROUND(Assumptions!H24*$B$8,0))/2)*Assumptions!$C$24+((ROUND(Assumptions!G25*$B$8,0)+ROUND(Assumptions!H25*$B$8,0))/2)*Assumptions!$C$25+((ROUND(Assumptions!G26*$B$8,0)+ROUND(Assumptions!H26*$B$8,0))/2)*Assumptions!$C$26+((ROUND(Assumptions!G27*$B$8,0)+ROUND(Assumptions!H27*$B$8,0))/2)*Assumptions!$C$27+((ROUND(Assumptions!G28*$B$8,0)+ROUND(Assumptions!H28*$B$8,0))/2)*Assumptions!$C$28)*(1+Assumptions!$B$4)^4/1000 | G17: =(((Assumptions!H20+Assumptions!I20)/2)*Assumptions!$C$20+((ROUND(Assumptions!H21*$B$8,0)+ROUND(Assumptions!I21*$B$8,0))/2)*Assumptions!$C$21+((ROUND(Assumptions!H22*$B$8,0)+ROUND(Assumptions!I22*$B$8,0))/2)*Assumptions!$C$22+((ROUND(Assumptions!H23*$B$8,0)+ROUND(Assumptions!I23*$B$8,0))/2)*Assumptions!$C$23+((ROUND(Assumptions!H24*$B$8,0)+ROUND(Assumptions!I24*$B$8,0))/2)*Assumptions!$C$24+((ROUND(Assumptions!H25*$B$8,0)+ROUND(Assumptions!I25*$B$8,0))/2)*Assumptions!$C$25+((ROUND(Assumptions!H26*$B$8,0)+ROUND(Assumptions!I26*$B$8,0))/2)*Assumptions!$C$26+((ROUND(Assumptions!H27*$B$8,0)+ROUND(Assumptions!I27*$B$8,0))/2)*Assumptions!$C$27+((ROUND(Assumptions!H28*$B$8,0)+ROUND(Assumptions!I28*$B$8,0))/2)*Assumptions!$C$28)*(1+Assumptions!$B$4)^5/1000 | H17: =(((Assumptions!I20+Assumptions!J20)/2)*Assumptions!$C$20+((ROUND(Assumptions!I21*$B$8,0)+ROUND(Assumptions!J21*$B$8,0))/2)*Assumptions!$C$21+((ROUND(Assumptions!I22*$B$8,0)+ROUND(Assumptions!J22*$B$8,0))/2)*Assumptions!$C$22+((ROUND(Assumptions!I23*$B$8,0)+ROUND(Assumptions!J23*$B$8,0))/2)*Assumptions!$C$23+((ROUND(Assumptions!I24*$B$8,0)+ROUND(Assumptions!J24*$B$8,0))/2)*Assumptions!$C$24+((ROUND(Assumptions!I25*$B$8,0)+ROUND(Assumptions!J25*$B$8,0))/2)*Assumptions!$C$25+((ROUND(Assumptions!I26*$B$8,0)+ROUND(Assumptions!J26*$B$8,0))/2)*Assumptions!$C$26+((ROUND(Assumptions!I27*$B$8,0)+ROUND(Assumptions!J27*$B$8,0))/2)*Assumptions!$C$27+((ROUND(Assumptions!I28*$B$8,0)+ROUND(Assumptions!J28*$B$8,0))/2)*Assumptions!$C$28)*(1+Assumptions!$B$4)^6/1000
A18: Other operating costs | B18: =SUM(Assumptions!D32:D37)*1/1000 | C18: =SUM(Assumptions!E32:E37)*$B$8/1000 | D18: =SUM(Assumptions!F32:F37)*$B$8/1000 | E18: =SUM(Assumptions!G32:G37)*$B$8/1000 | F18: =SUM(Assumptions!H32:H37)*$B$8/1000 | G18: =SUM(Assumptions!I32:I37)*$B$8/1000 | H18: =SUM(Assumptions!J32:J37)*$B$8/1000
A19: Total operating costs | B19: =B17+B18 | C19: =C17+C18 | D19: =D17+D18 | E19: =E17+E18 | F19: =F17+F18 | G19: =G17+G18 | H19: =H17+H18
A20: EBITDA | B20: =B16-B19 | C20: =C16-C19 | D20: =D16-D19 | E20: =E16-E19 | F20: =F16-F19 | G20: =G16-G19 | H20: =H16-H19
A21: EBITDA margin | B21: =IF(B14=0,0,B20/B14) | C21: =IF(C14=0,0,C20/C14) | D21: =IF(D14=0,0,D20/D14) | E21: =IF(E14=0,0,E20/E14) | F21: =IF(F14=0,0,F20/F14) | G21: =IF(G14=0,0,G20/G14) | H21: =IF(H14=0,0,H20/H14)
A22: ARR at year end | B22: =B10*B11/1000 | C22: =C10*C11/1000 | D22: =D10*D11/1000 | E22: =E10*E11/1000 | F22: =F10*F11/1000 | G22: =G10*G11/1000 | H22: =H10*H11/1000
A23: Headcount at year end | B23: =Assumptions!D20+ROUND(Assumptions!D21*$B$8,0)+ROUND(Assumptions!D22*$B$8,0)+ROUND(Assumptions!D23*$B$8,0)+ROUND(Assumptions!D24*$B$8,0)+ROUND(Assumptions!D25*$B$8,0)+ROUND(Assumptions!D26*$B$8,0)+ROUND(Assumptions!D27*$B$8,0)+ROUND(Assumptions!D28*$B$8,0) | C23: =Assumptions!E20+ROUND(Assumptions!E21*$B$8,0)+ROUND(Assumptions!E22*$B$8,0)+ROUND(Assumptions!E23*$B$8,0)+ROUND(Assumptions!E24*$B$8,0)+ROUND(Assumptions!E25*$B$8,0)+ROUND(Assumptions!E26*$B$8,0)+ROUND(Assumptions!E27*$B$8,0)+ROUND(Assumptions!E28*$B$8,0) | D23: =Assumptions!F20+ROUND(Assumptions!F21*$B$8,0)+ROUND(Assumptions!F22*$B$8,0)+ROUND(Assumptions!F23*$B$8,0)+ROUND(Assumptions!F24*$B$8,0)+ROUND(Assumptions!F25*$B$8,0)+ROUND(Assumptions!F26*$B$8,0)+ROUND(Assumptions!F27*$B$8,0)+ROUND(Assumptions!F28*$B$8,0) | E23: =Assumptions!G20+ROUND(Assumptions!G21*$B$8,0)+ROUND(Assumptions!G22*$B$8,0)+ROUND(Assumptions!G23*$B$8,0)+ROUND(Assumptions!G24*$B$8,0)+ROUND(Assumptions!G25*$B$8,0)+ROUND(Assumptions!G26*$B$8,0)+ROUND(Assumptions!G27*$B$8,0)+ROUND(Assumptions!G28*$B$8,0) | F23: =Assumptions!H20+ROUND(Assumptions!H21*$B$8,0)+ROUND(Assumptions!H22*$B$8,0)+ROUND(Assumptions!H23*$B$8,0)+ROUND(Assumptions!H24*$B$8,0)+ROUND(Assumptions!H25*$B$8,0)+ROUND(Assumptions!H26*$B$8,0)+ROUND(Assumptions!H27*$B$8,0)+ROUND(Assumptions!H28*$B$8,0) | G23: =Assumptions!I20+ROUND(Assumptions!I21*$B$8,0)+ROUND(Assumptions!I22*$B$8,0)+ROUND(Assumptions!I23*$B$8,0)+ROUND(Assumptions!I24*$B$8,0)+ROUND(Assumptions!I25*$B$8,0)+ROUND(Assumptions!I26*$B$8,0)+ROUND(Assumptions!I27*$B$8,0)+ROUND(Assumptions!I28*$B$8,0) | H23: =Assumptions!J20+ROUND(Assumptions!J21*$B$8,0)+ROUND(Assumptions!J22*$B$8,0)+ROUND(Assumptions!J23*$B$8,0)+ROUND(Assumptions!J24*$B$8,0)+ROUND(Assumptions!J25*$B$8,0)+ROUND(Assumptions!J26*$B$8,0)+ROUND(Assumptions!J27*$B$8,0)+ROUND(Assumptions!J28*$B$8,0)
A24: Sales and marketing cost | B24: =((ROUND(Assumptions!D24*$B$8,0)*0.6)*Assumptions!$C$24+(ROUND(Assumptions!D25*$B$8,0)*0.6)*Assumptions!$C$25+(ROUND(Assumptions!D27*$B$8,0)*0.6)*Assumptions!$C$27)*(1+Assumptions!$B$4)^0/1000+(Assumptions!D35+Assumptions!D36)*1/1000 | C24: =(((ROUND(Assumptions!D24*$B$8,0)+ROUND(Assumptions!E24*$B$8,0))/2)*Assumptions!$C$24+((ROUND(Assumptions!D25*$B$8,0)+ROUND(Assumptions!E25*$B$8,0))/2)*Assumptions!$C$25+((ROUND(Assumptions!D27*$B$8,0)+ROUND(Assumptions!E27*$B$8,0))/2)*Assumptions!$C$27)*(1+Assumptions!$B$4)^1/1000+(Assumptions!E35+Assumptions!E36)*$B$8/1000 | D24: =(((ROUND(Assumptions!E24*$B$8,0)+ROUND(Assumptions!F24*$B$8,0))/2)*Assumptions!$C$24+((ROUND(Assumptions!E25*$B$8,0)+ROUND(Assumptions!F25*$B$8,0))/2)*Assumptions!$C$25+((ROUND(Assumptions!E27*$B$8,0)+ROUND(Assumptions!F27*$B$8,0))/2)*Assumptions!$C$27)*(1+Assumptions!$B$4)^2/1000+(Assumptions!F35+Assumptions!F36)*$B$8/1000 | E24: =(((ROUND(Assumptions!F24*$B$8,0)+ROUND(Assumptions!G24*$B$8,0))/2)*Assumptions!$C$24+((ROUND(Assumptions!F25*$B$8,0)+ROUND(Assumptions!G25*$B$8,0))/2)*Assumptions!$C$25+((ROUND(Assumptions!F27*$B$8,0)+ROUND(Assumptions!G27*$B$8,0))/2)*Assumptions!$C$27)*(1+Assumptions!$B$4)^3/1000+(Assumptions!G35+Assumptions!G36)*$B$8/1000 | F24: =(((ROUND(Assumptions!G24*$B$8,0)+ROUND(Assumptions!H24*$B$8,0))/2)*Assumptions!$C$24+((ROUND(Assumptions!G25*$B$8,0)+ROUND(Assumptions!H25*$B$8,0))/2)*Assumptions!$C$25+((ROUND(Assumptions!G27*$B$8,0)+ROUND(Assumptions!H27*$B$8,0))/2)*Assumptions!$C$27)*(1+Assumptions!$B$4)^4/1000+(Assumptions!H35+Assumptions!H36)*$B$8/1000 | G24: =(((ROUND(Assumptions!H24*$B$8,0)+ROUND(Assumptions!I24*$B$8,0))/2)*Assumptions!$C$24+((ROUND(Assumptions!H25*$B$8,0)+ROUND(Assumptions!I25*$B$8,0))/2)*Assumptions!$C$25+((ROUND(Assumptions!H27*$B$8,0)+ROUND(Assumptions!I27*$B$8,0))/2)*Assumptions!$C$27)*(1+Assumptions!$B$4)^5/1000+(Assumptions!I35+Assumptions!I36)*$B$8/1000 | H24: =(((ROUND(Assumptions!I24*$B$8,0)+ROUND(Assumptions!J24*$B$8,0))/2)*Assumptions!$C$24+((ROUND(Assumptions!I25*$B$8,0)+ROUND(Assumptions!J25*$B$8,0))/2)*Assumptions!$C$25+((ROUND(Assumptions!I27*$B$8,0)+ROUND(Assumptions!J27*$B$8,0))/2)*Assumptions!$C$27)*(1+Assumptions!$B$4)^6/1000+(Assumptions!J35+Assumptions!J36)*$B$8/1000
A25: Sales and marketing cost per $1 of new ARR | B25: =IF(B5=0,0,B24/(B5*B11/1000)) | C25: =IF(C5=0,0,C24/(C5*C11/1000)) | D25: =IF(D5=0,0,D24/(D5*D11/1000)) | E25: =IF(E5=0,0,E24/(E5*E11/1000)) | F25: =IF(F5=0,0,F24/(F5*F11/1000)) | G25: =IF(G5=0,0,G24/(G5*G11/1000)) | H25: =IF(H5=0,0,H24/(H5*H11/1000)) | I25: 2024 median $2.00 (Benchmarkit 2025 report, B); key plan risk

Sheet Monthly
A1: Monthly ARR and EBITDA, used to size the rounds
A3: Month | B3: Year | C3: Base ARR $M | D3: Base EBITDA $M | E3: Upside ARR | F3: Upside EBITDA | G3: Downside ARR | H3: Downside EBITDA
A4: 1 | B4: 1 | C4: =0+('Base'!B22-0)*(1-0)/12 | D4: ='Base'!B20/12 | E4: =0+('Upside'!B22-0)*(1-0)/12 | F4: ='Upside'!B20/12 | G4: =0+('Downside'!B22-0)*(1-0)/12 | H4: ='Downside'!B20/12
A5: 2 | B5: 1 | C5: =0+('Base'!B22-0)*(2-0)/12 | D5: ='Base'!B20/12 | E5: =0+('Upside'!B22-0)*(2-0)/12 | F5: ='Upside'!B20/12 | G5: =0+('Downside'!B22-0)*(2-0)/12 | H5: ='Downside'!B20/12
A6: 3 | B6: 1 | C6: =0+('Base'!B22-0)*(3-0)/12 | D6: ='Base'!B20/12 | E6: =0+('Upside'!B22-0)*(3-0)/12 | F6: ='Upside'!B20/12 | G6: =0+('Downside'!B22-0)*(3-0)/12 | H6: ='Downside'!B20/12
A7: 4 | B7: 1 | C7: =0+('Base'!B22-0)*(4-0)/12 | D7: ='Base'!B20/12 | E7: =0+('Upside'!B22-0)*(4-0)/12 | F7: ='Upside'!B20/12 | G7: =0+('Downside'!B22-0)*(4-0)/12 | H7: ='Downside'!B20/12
A8: 5 | B8: 1 | C8: =0+('Base'!B22-0)*(5-0)/12 | D8: ='Base'!B20/12 | E8: =0+('Upside'!B22-0)*(5-0)/12 | F8: ='Upside'!B20/12 | G8: =0+('Downside'!B22-0)*(5-0)/12 | H8: ='Downside'!B20/12
A9: 6 | B9: 1 | C9: =0+('Base'!B22-0)*(6-0)/12 | D9: ='Base'!B20/12 | E9: =0+('Upside'!B22-0)*(6-0)/12 | F9: ='Upside'!B20/12 | G9: =0+('Downside'!B22-0)*(6-0)/12 | H9: ='Downside'!B20/12
A10: 7 | B10: 1 | C10: =0+('Base'!B22-0)*(7-0)/12 | D10: ='Base'!B20/12 | E10: =0+('Upside'!B22-0)*(7-0)/12 | F10: ='Upside'!B20/12 | G10: =0+('Downside'!B22-0)*(7-0)/12 | H10: ='Downside'!B20/12
A11: 8 | B11: 1 | C11: =0+('Base'!B22-0)*(8-0)/12 | D11: ='Base'!B20/12 | E11: =0+('Upside'!B22-0)*(8-0)/12 | F11: ='Upside'!B20/12 | G11: =0+('Downside'!B22-0)*(8-0)/12 | H11: ='Downside'!B20/12
A12: 9 | B12: 1 | C12: =0+('Base'!B22-0)*(9-0)/12 | D12: ='Base'!B20/12 | E12: =0+('Upside'!B22-0)*(9-0)/12 | F12: ='Upside'!B20/12 | G12: =0+('Downside'!B22-0)*(9-0)/12 | H12: ='Downside'!B20/12
A13: 10 | B13: 1 | C13: =0+('Base'!B22-0)*(10-0)/12 | D13: ='Base'!B20/12 | E13: =0+('Upside'!B22-0)*(10-0)/12 | F13: ='Upside'!B20/12 | G13: =0+('Downside'!B22-0)*(10-0)/12 | H13: ='Downside'!B20/12
A14: 11 | B14: 1 | C14: =0+('Base'!B22-0)*(11-0)/12 | D14: ='Base'!B20/12 | E14: =0+('Upside'!B22-0)*(11-0)/12 | F14: ='Upside'!B20/12 | G14: =0+('Downside'!B22-0)*(11-0)/12 | H14: ='Downside'!B20/12
A15: 12 | B15: 1 | C15: =0+('Base'!B22-0)*(12-0)/12 | D15: ='Base'!B20/12 | E15: =0+('Upside'!B22-0)*(12-0)/12 | F15: ='Upside'!B20/12 | G15: =0+('Downside'!B22-0)*(12-0)/12 | H15: ='Downside'!B20/12
A16: 13 | B16: 2 | C16: ='Base'!B22+('Base'!C22-'Base'!B22)*(13-12)/12 | D16: ='Base'!C20/12 | E16: ='Upside'!B22+('Upside'!C22-'Upside'!B22)*(13-12)/12 | F16: ='Upside'!C20/12 | G16: ='Downside'!B22+('Downside'!C22-'Downside'!B22)*(13-12)/12 | H16: ='Downside'!C20/12
A17: 14 | B17: 2 | C17: ='Base'!B22+('Base'!C22-'Base'!B22)*(14-12)/12 | D17: ='Base'!C20/12 | E17: ='Upside'!B22+('Upside'!C22-'Upside'!B22)*(14-12)/12 | F17: ='Upside'!C20/12 | G17: ='Downside'!B22+('Downside'!C22-'Downside'!B22)*(14-12)/12 | H17: ='Downside'!C20/12
A18: 15 | B18: 2 | C18: ='Base'!B22+('Base'!C22-'Base'!B22)*(15-12)/12 | D18: ='Base'!C20/12 | E18: ='Upside'!B22+('Upside'!C22-'Upside'!B22)*(15-12)/12 | F18: ='Upside'!C20/12 | G18: ='Downside'!B22+('Downside'!C22-'Downside'!B22)*(15-12)/12 | H18: ='Downside'!C20/12
A19: 16 | B19: 2 | C19: ='Base'!B22+('Base'!C22-'Base'!B22)*(16-12)/12 | D19: ='Base'!C20/12 | E19: ='Upside'!B22+('Upside'!C22-'Upside'!B22)*(16-12)/12 | F19: ='Upside'!C20/12 | G19: ='Downside'!B22+('Downside'!C22-'Downside'!B22)*(16-12)/12 | H19: ='Downside'!C20/12
A20: 17 | B20: 2 | C20: ='Base'!B22+('Base'!C22-'Base'!B22)*(17-12)/12 | D20: ='Base'!C20/12 | E20: ='Upside'!B22+('Upside'!C22-'Upside'!B22)*(17-12)/12 | F20: ='Upside'!C20/12 | G20: ='Downside'!B22+('Downside'!C22-'Downside'!B22)*(17-12)/12 | H20: ='Downside'!C20/12
A21: 18 | B21: 2 | C21: ='Base'!B22+('Base'!C22-'Base'!B22)*(18-12)/12 | D21: ='Base'!C20/12 | E21: ='Upside'!B22+('Upside'!C22-'Upside'!B22)*(18-12)/12 | F21: ='Upside'!C20/12 | G21: ='Downside'!B22+('Downside'!C22-'Downside'!B22)*(18-12)/12 | H21: ='Downside'!C20/12
A22: 19 | B22: 2 | C22: ='Base'!B22+('Base'!C22-'Base'!B22)*(19-12)/12 | D22: ='Base'!C20/12 | E22: ='Upside'!B22+('Upside'!C22-'Upside'!B22)*(19-12)/12 | F22: ='Upside'!C20/12 | G22: ='Downside'!B22+('Downside'!C22-'Downside'!B22)*(19-12)/12 | H22: ='Downside'!C20/12
A23: 20 | B23: 2 | C23: ='Base'!B22+('Base'!C22-'Base'!B22)*(20-12)/12 | D23: ='Base'!C20/12 | E23: ='Upside'!B22+('Upside'!C22-'Upside'!B22)*(20-12)/12 | F23: ='Upside'!C20/12 | G23: ='Downside'!B22+('Downside'!C22-'Downside'!B22)*(20-12)/12 | H23: ='Downside'!C20/12
A24: 21 | B24: 2 | C24: ='Base'!B22+('Base'!C22-'Base'!B22)*(21-12)/12 | D24: ='Base'!C20/12 | E24: ='Upside'!B22+('Upside'!C22-'Upside'!B22)*(21-12)/12 | F24: ='Upside'!C20/12 | G24: ='Downside'!B22+('Downside'!C22-'Downside'!B22)*(21-12)/12 | H24: ='Downside'!C20/12
A25: 22 | B25: 2 | C25: ='Base'!B22+('Base'!C22-'Base'!B22)*(22-12)/12 | D25: ='Base'!C20/12 | E25: ='Upside'!B22+('Upside'!C22-'Upside'!B22)*(22-12)/12 | F25: ='Upside'!C20/12 | G25: ='Downside'!B22+('Downside'!C22-'Downside'!B22)*(22-12)/12 | H25: ='Downside'!C20/12
A26: 23 | B26: 2 | C26: ='Base'!B22+('Base'!C22-'Base'!B22)*(23-12)/12 | D26: ='Base'!C20/12 | E26: ='Upside'!B22+('Upside'!C22-'Upside'!B22)*(23-12)/12 | F26: ='Upside'!C20/12 | G26: ='Downside'!B22+('Downside'!C22-'Downside'!B22)*(23-12)/12 | H26: ='Downside'!C20/12
A27: 24 | B27: 2 | C27: ='Base'!B22+('Base'!C22-'Base'!B22)*(24-12)/12 | D27: ='Base'!C20/12 | E27: ='Upside'!B22+('Upside'!C22-'Upside'!B22)*(24-12)/12 | F27: ='Upside'!C20/12 | G27: ='Downside'!B22+('Downside'!C22-'Downside'!B22)*(24-12)/12 | H27: ='Downside'!C20/12
A28: 25 | B28: 3 | C28: ='Base'!C22+('Base'!D22-'Base'!C22)*(25-24)/12 | D28: ='Base'!D20/12 | E28: ='Upside'!C22+('Upside'!D22-'Upside'!C22)*(25-24)/12 | F28: ='Upside'!D20/12 | G28: ='Downside'!C22+('Downside'!D22-'Downside'!C22)*(25-24)/12 | H28: ='Downside'!D20/12
A29: 26 | B29: 3 | C29: ='Base'!C22+('Base'!D22-'Base'!C22)*(26-24)/12 | D29: ='Base'!D20/12 | E29: ='Upside'!C22+('Upside'!D22-'Upside'!C22)*(26-24)/12 | F29: ='Upside'!D20/12 | G29: ='Downside'!C22+('Downside'!D22-'Downside'!C22)*(26-24)/12 | H29: ='Downside'!D20/12
A30: 27 | B30: 3 | C30: ='Base'!C22+('Base'!D22-'Base'!C22)*(27-24)/12 | D30: ='Base'!D20/12 | E30: ='Upside'!C22+('Upside'!D22-'Upside'!C22)*(27-24)/12 | F30: ='Upside'!D20/12 | G30: ='Downside'!C22+('Downside'!D22-'Downside'!C22)*(27-24)/12 | H30: ='Downside'!D20/12
A31: 28 | B31: 3 | C31: ='Base'!C22+('Base'!D22-'Base'!C22)*(28-24)/12 | D31: ='Base'!D20/12 | E31: ='Upside'!C22+('Upside'!D22-'Upside'!C22)*(28-24)/12 | F31: ='Upside'!D20/12 | G31: ='Downside'!C22+('Downside'!D22-'Downside'!C22)*(28-24)/12 | H31: ='Downside'!D20/12
A32: 29 | B32: 3 | C32: ='Base'!C22+('Base'!D22-'Base'!C22)*(29-24)/12 | D32: ='Base'!D20/12 | E32: ='Upside'!C22+('Upside'!D22-'Upside'!C22)*(29-24)/12 | F32: ='Upside'!D20/12 | G32: ='Downside'!C22+('Downside'!D22-'Downside'!C22)*(29-24)/12 | H32: ='Downside'!D20/12
A33: 30 | B33: 3 | C33: ='Base'!C22+('Base'!D22-'Base'!C22)*(30-24)/12 | D33: ='Base'!D20/12 | E33: ='Upside'!C22+('Upside'!D22-'Upside'!C22)*(30-24)/12 | F33: ='Upside'!D20/12 | G33: ='Downside'!C22+('Downside'!D22-'Downside'!C22)*(30-24)/12 | H33: ='Downside'!D20/12
A34: 31 | B34: 3 | C34: ='Base'!C22+('Base'!D22-'Base'!C22)*(31-24)/12 | D34: ='Base'!D20/12 | E34: ='Upside'!C22+('Upside'!D22-'Upside'!C22)*(31-24)/12 | F34: ='Upside'!D20/12 | G34: ='Downside'!C22+('Downside'!D22-'Downside'!C22)*(31-24)/12 | H34: ='Downside'!D20/12
A35: 32 | B35: 3 | C35: ='Base'!C22+('Base'!D22-'Base'!C22)*(32-24)/12 | D35: ='Base'!D20/12 | E35: ='Upside'!C22+('Upside'!D22-'Upside'!C22)*(32-24)/12 | F35: ='Upside'!D20/12 | G35: ='Downside'!C22+('Downside'!D22-'Downside'!C22)*(32-24)/12 | H35: ='Downside'!D20/12
A36: 33 | B36: 3 | C36: ='Base'!C22+('Base'!D22-'Base'!C22)*(33-24)/12 | D36: ='Base'!D20/12 | E36: ='Upside'!C22+('Upside'!D22-'Upside'!C22)*(33-24)/12 | F36: ='Upside'!D20/12 | G36: ='Downside'!C22+('Downside'!D22-'Downside'!C22)*(33-24)/12 | H36: ='Downside'!D20/12
A37: 34 | B37: 3 | C37: ='Base'!C22+('Base'!D22-'Base'!C22)*(34-24)/12 | D37: ='Base'!D20/12 | E37: ='Upside'!C22+('Upside'!D22-'Upside'!C22)*(34-24)/12 | F37: ='Upside'!D20/12 | G37: ='Downside'!C22+('Downside'!D22-'Downside'!C22)*(34-24)/12 | H37: ='Downside'!D20/12
A38: 35 | B38: 3 | C38: ='Base'!C22+('Base'!D22-'Base'!C22)*(35-24)/12 | D38: ='Base'!D20/12 | E38: ='Upside'!C22+('Upside'!D22-'Upside'!C22)*(35-24)/12 | F38: ='Upside'!D20/12 | G38: ='Downside'!C22+('Downside'!D22-'Downside'!C22)*(35-24)/12 | H38: ='Downside'!D20/12
A39: 36 | B39: 3 | C39: ='Base'!C22+('Base'!D22-'Base'!C22)*(36-24)/12 | D39: ='Base'!D20/12 | E39: ='Upside'!C22+('Upside'!D22-'Upside'!C22)*(36-24)/12 | F39: ='Upside'!D20/12 | G39: ='Downside'!C22+('Downside'!D22-'Downside'!C22)*(36-24)/12 | H39: ='Downside'!D20/12
A40: 37 | B40: 4 | C40: ='Base'!D22+('Base'!E22-'Base'!D22)*(37-36)/12 | D40: ='Base'!E20/12 | E40: ='Upside'!D22+('Upside'!E22-'Upside'!D22)*(37-36)/12 | F40: ='Upside'!E20/12 | G40: ='Downside'!D22+('Downside'!E22-'Downside'!D22)*(37-36)/12 | H40: ='Downside'!E20/12
A41: 38 | B41: 4 | C41: ='Base'!D22+('Base'!E22-'Base'!D22)*(38-36)/12 | D41: ='Base'!E20/12 | E41: ='Upside'!D22+('Upside'!E22-'Upside'!D22)*(38-36)/12 | F41: ='Upside'!E20/12 | G41: ='Downside'!D22+('Downside'!E22-'Downside'!D22)*(38-36)/12 | H41: ='Downside'!E20/12
A42: 39 | B42: 4 | C42: ='Base'!D22+('Base'!E22-'Base'!D22)*(39-36)/12 | D42: ='Base'!E20/12 | E42: ='Upside'!D22+('Upside'!E22-'Upside'!D22)*(39-36)/12 | F42: ='Upside'!E20/12 | G42: ='Downside'!D22+('Downside'!E22-'Downside'!D22)*(39-36)/12 | H42: ='Downside'!E20/12
A43: 40 | B43: 4 | C43: ='Base'!D22+('Base'!E22-'Base'!D22)*(40-36)/12 | D43: ='Base'!E20/12 | E43: ='Upside'!D22+('Upside'!E22-'Upside'!D22)*(40-36)/12 | F43: ='Upside'!E20/12 | G43: ='Downside'!D22+('Downside'!E22-'Downside'!D22)*(40-36)/12 | H43: ='Downside'!E20/12
A44: 41 | B44: 4 | C44: ='Base'!D22+('Base'!E22-'Base'!D22)*(41-36)/12 | D44: ='Base'!E20/12 | E44: ='Upside'!D22+('Upside'!E22-'Upside'!D22)*(41-36)/12 | F44: ='Upside'!E20/12 | G44: ='Downside'!D22+('Downside'!E22-'Downside'!D22)*(41-36)/12 | H44: ='Downside'!E20/12
A45: 42 | B45: 4 | C45: ='Base'!D22+('Base'!E22-'Base'!D22)*(42-36)/12 | D45: ='Base'!E20/12 | E45: ='Upside'!D22+('Upside'!E22-'Upside'!D22)*(42-36)/12 | F45: ='Upside'!E20/12 | G45: ='Downside'!D22+('Downside'!E22-'Downside'!D22)*(42-36)/12 | H45: ='Downside'!E20/12
A46: 43 | B46: 4 | C46: ='Base'!D22+('Base'!E22-'Base'!D22)*(43-36)/12 | D46: ='Base'!E20/12 | E46: ='Upside'!D22+('Upside'!E22-'Upside'!D22)*(43-36)/12 | F46: ='Upside'!E20/12 | G46: ='Downside'!D22+('Downside'!E22-'Downside'!D22)*(43-36)/12 | H46: ='Downside'!E20/12
A47: 44 | B47: 4 | C47: ='Base'!D22+('Base'!E22-'Base'!D22)*(44-36)/12 | D47: ='Base'!E20/12 | E47: ='Upside'!D22+('Upside'!E22-'Upside'!D22)*(44-36)/12 | F47: ='Upside'!E20/12 | G47: ='Downside'!D22+('Downside'!E22-'Downside'!D22)*(44-36)/12 | H47: ='Downside'!E20/12
A48: 45 | B48: 4 | C48: ='Base'!D22+('Base'!E22-'Base'!D22)*(45-36)/12 | D48: ='Base'!E20/12 | E48: ='Upside'!D22+('Upside'!E22-'Upside'!D22)*(45-36)/12 | F48: ='Upside'!E20/12 | G48: ='Downside'!D22+('Downside'!E22-'Downside'!D22)*(45-36)/12 | H48: ='Downside'!E20/12
A49: 46 | B49: 4 | C49: ='Base'!D22+('Base'!E22-'Base'!D22)*(46-36)/12 | D49: ='Base'!E20/12 | E49: ='Upside'!D22+('Upside'!E22-'Upside'!D22)*(46-36)/12 | F49: ='Upside'!E20/12 | G49: ='Downside'!D22+('Downside'!E22-'Downside'!D22)*(46-36)/12 | H49: ='Downside'!E20/12
A50: 47 | B50: 4 | C50: ='Base'!D22+('Base'!E22-'Base'!D22)*(47-36)/12 | D50: ='Base'!E20/12 | E50: ='Upside'!D22+('Upside'!E22-'Upside'!D22)*(47-36)/12 | F50: ='Upside'!E20/12 | G50: ='Downside'!D22+('Downside'!E22-'Downside'!D22)*(47-36)/12 | H50: ='Downside'!E20/12
A51: 48 | B51: 4 | C51: ='Base'!D22+('Base'!E22-'Base'!D22)*(48-36)/12 | D51: ='Base'!E20/12 | E51: ='Upside'!D22+('Upside'!E22-'Upside'!D22)*(48-36)/12 | F51: ='Upside'!E20/12 | G51: ='Downside'!D22+('Downside'!E22-'Downside'!D22)*(48-36)/12 | H51: ='Downside'!E20/12
A52: 49 | B52: 5 | C52: ='Base'!E22+('Base'!F22-'Base'!E22)*(49-48)/12 | D52: ='Base'!F20/12 | E52: ='Upside'!E22+('Upside'!F22-'Upside'!E22)*(49-48)/12 | F52: ='Upside'!F20/12 | G52: ='Downside'!E22+('Downside'!F22-'Downside'!E22)*(49-48)/12 | H52: ='Downside'!F20/12
A53: 50 | B53: 5 | C53: ='Base'!E22+('Base'!F22-'Base'!E22)*(50-48)/12 | D53: ='Base'!F20/12 | E53: ='Upside'!E22+('Upside'!F22-'Upside'!E22)*(50-48)/12 | F53: ='Upside'!F20/12 | G53: ='Downside'!E22+('Downside'!F22-'Downside'!E22)*(50-48)/12 | H53: ='Downside'!F20/12
A54: 51 | B54: 5 | C54: ='Base'!E22+('Base'!F22-'Base'!E22)*(51-48)/12 | D54: ='Base'!F20/12 | E54: ='Upside'!E22+('Upside'!F22-'Upside'!E22)*(51-48)/12 | F54: ='Upside'!F20/12 | G54: ='Downside'!E22+('Downside'!F22-'Downside'!E22)*(51-48)/12 | H54: ='Downside'!F20/12
A55: 52 | B55: 5 | C55: ='Base'!E22+('Base'!F22-'Base'!E22)*(52-48)/12 | D55: ='Base'!F20/12 | E55: ='Upside'!E22+('Upside'!F22-'Upside'!E22)*(52-48)/12 | F55: ='Upside'!F20/12 | G55: ='Downside'!E22+('Downside'!F22-'Downside'!E22)*(52-48)/12 | H55: ='Downside'!F20/12
A56: 53 | B56: 5 | C56: ='Base'!E22+('Base'!F22-'Base'!E22)*(53-48)/12 | D56: ='Base'!F20/12 | E56: ='Upside'!E22+('Upside'!F22-'Upside'!E22)*(53-48)/12 | F56: ='Upside'!F20/12 | G56: ='Downside'!E22+('Downside'!F22-'Downside'!E22)*(53-48)/12 | H56: ='Downside'!F20/12
A57: 54 | B57: 5 | C57: ='Base'!E22+('Base'!F22-'Base'!E22)*(54-48)/12 | D57: ='Base'!F20/12 | E57: ='Upside'!E22+('Upside'!F22-'Upside'!E22)*(54-48)/12 | F57: ='Upside'!F20/12 | G57: ='Downside'!E22+('Downside'!F22-'Downside'!E22)*(54-48)/12 | H57: ='Downside'!F20/12
A58: 55 | B58: 5 | C58: ='Base'!E22+('Base'!F22-'Base'!E22)*(55-48)/12 | D58: ='Base'!F20/12 | E58: ='Upside'!E22+('Upside'!F22-'Upside'!E22)*(55-48)/12 | F58: ='Upside'!F20/12 | G58: ='Downside'!E22+('Downside'!F22-'Downside'!E22)*(55-48)/12 | H58: ='Downside'!F20/12
A59: 56 | B59: 5 | C59: ='Base'!E22+('Base'!F22-'Base'!E22)*(56-48)/12 | D59: ='Base'!F20/12 | E59: ='Upside'!E22+('Upside'!F22-'Upside'!E22)*(56-48)/12 | F59: ='Upside'!F20/12 | G59: ='Downside'!E22+('Downside'!F22-'Downside'!E22)*(56-48)/12 | H59: ='Downside'!F20/12
A60: 57 | B60: 5 | C60: ='Base'!E22+('Base'!F22-'Base'!E22)*(57-48)/12 | D60: ='Base'!F20/12 | E60: ='Upside'!E22+('Upside'!F22-'Upside'!E22)*(57-48)/12 | F60: ='Upside'!F20/12 | G60: ='Downside'!E22+('Downside'!F22-'Downside'!E22)*(57-48)/12 | H60: ='Downside'!F20/12
A61: 58 | B61: 5 | C61: ='Base'!E22+('Base'!F22-'Base'!E22)*(58-48)/12 | D61: ='Base'!F20/12 | E61: ='Upside'!E22+('Upside'!F22-'Upside'!E22)*(58-48)/12 | F61: ='Upside'!F20/12 | G61: ='Downside'!E22+('Downside'!F22-'Downside'!E22)*(58-48)/12 | H61: ='Downside'!F20/12
A62: 59 | B62: 5 | C62: ='Base'!E22+('Base'!F22-'Base'!E22)*(59-48)/12 | D62: ='Base'!F20/12 | E62: ='Upside'!E22+('Upside'!F22-'Upside'!E22)*(59-48)/12 | F62: ='Upside'!F20/12 | G62: ='Downside'!E22+('Downside'!F22-'Downside'!E22)*(59-48)/12 | H62: ='Downside'!F20/12
A63: 60 | B63: 5 | C63: ='Base'!E22+('Base'!F22-'Base'!E22)*(60-48)/12 | D63: ='Base'!F20/12 | E63: ='Upside'!E22+('Upside'!F22-'Upside'!E22)*(60-48)/12 | F63: ='Upside'!F20/12 | G63: ='Downside'!E22+('Downside'!F22-'Downside'!E22)*(60-48)/12 | H63: ='Downside'!F20/12
A64: 61 | B64: 6 | C64: ='Base'!F22+('Base'!G22-'Base'!F22)*(61-60)/12 | D64: ='Base'!G20/12 | E64: ='Upside'!F22+('Upside'!G22-'Upside'!F22)*(61-60)/12 | F64: ='Upside'!G20/12 | G64: ='Downside'!F22+('Downside'!G22-'Downside'!F22)*(61-60)/12 | H64: ='Downside'!G20/12
A65: 62 | B65: 6 | C65: ='Base'!F22+('Base'!G22-'Base'!F22)*(62-60)/12 | D65: ='Base'!G20/12 | E65: ='Upside'!F22+('Upside'!G22-'Upside'!F22)*(62-60)/12 | F65: ='Upside'!G20/12 | G65: ='Downside'!F22+('Downside'!G22-'Downside'!F22)*(62-60)/12 | H65: ='Downside'!G20/12
A66: 63 | B66: 6 | C66: ='Base'!F22+('Base'!G22-'Base'!F22)*(63-60)/12 | D66: ='Base'!G20/12 | E66: ='Upside'!F22+('Upside'!G22-'Upside'!F22)*(63-60)/12 | F66: ='Upside'!G20/12 | G66: ='Downside'!F22+('Downside'!G22-'Downside'!F22)*(63-60)/12 | H66: ='Downside'!G20/12
A67: 64 | B67: 6 | C67: ='Base'!F22+('Base'!G22-'Base'!F22)*(64-60)/12 | D67: ='Base'!G20/12 | E67: ='Upside'!F22+('Upside'!G22-'Upside'!F22)*(64-60)/12 | F67: ='Upside'!G20/12 | G67: ='Downside'!F22+('Downside'!G22-'Downside'!F22)*(64-60)/12 | H67: ='Downside'!G20/12
A68: 65 | B68: 6 | C68: ='Base'!F22+('Base'!G22-'Base'!F22)*(65-60)/12 | D68: ='Base'!G20/12 | E68: ='Upside'!F22+('Upside'!G22-'Upside'!F22)*(65-60)/12 | F68: ='Upside'!G20/12 | G68: ='Downside'!F22+('Downside'!G22-'Downside'!F22)*(65-60)/12 | H68: ='Downside'!G20/12
A69: 66 | B69: 6 | C69: ='Base'!F22+('Base'!G22-'Base'!F22)*(66-60)/12 | D69: ='Base'!G20/12 | E69: ='Upside'!F22+('Upside'!G22-'Upside'!F22)*(66-60)/12 | F69: ='Upside'!G20/12 | G69: ='Downside'!F22+('Downside'!G22-'Downside'!F22)*(66-60)/12 | H69: ='Downside'!G20/12
A70: 67 | B70: 6 | C70: ='Base'!F22+('Base'!G22-'Base'!F22)*(67-60)/12 | D70: ='Base'!G20/12 | E70: ='Upside'!F22+('Upside'!G22-'Upside'!F22)*(67-60)/12 | F70: ='Upside'!G20/12 | G70: ='Downside'!F22+('Downside'!G22-'Downside'!F22)*(67-60)/12 | H70: ='Downside'!G20/12
A71: 68 | B71: 6 | C71: ='Base'!F22+('Base'!G22-'Base'!F22)*(68-60)/12 | D71: ='Base'!G20/12 | E71: ='Upside'!F22+('Upside'!G22-'Upside'!F22)*(68-60)/12 | F71: ='Upside'!G20/12 | G71: ='Downside'!F22+('Downside'!G22-'Downside'!F22)*(68-60)/12 | H71: ='Downside'!G20/12
A72: 69 | B72: 6 | C72: ='Base'!F22+('Base'!G22-'Base'!F22)*(69-60)/12 | D72: ='Base'!G20/12 | E72: ='Upside'!F22+('Upside'!G22-'Upside'!F22)*(69-60)/12 | F72: ='Upside'!G20/12 | G72: ='Downside'!F22+('Downside'!G22-'Downside'!F22)*(69-60)/12 | H72: ='Downside'!G20/12
A73: 70 | B73: 6 | C73: ='Base'!F22+('Base'!G22-'Base'!F22)*(70-60)/12 | D73: ='Base'!G20/12 | E73: ='Upside'!F22+('Upside'!G22-'Upside'!F22)*(70-60)/12 | F73: ='Upside'!G20/12 | G73: ='Downside'!F22+('Downside'!G22-'Downside'!F22)*(70-60)/12 | H73: ='Downside'!G20/12
A74: 71 | B74: 6 | C74: ='Base'!F22+('Base'!G22-'Base'!F22)*(71-60)/12 | D74: ='Base'!G20/12 | E74: ='Upside'!F22+('Upside'!G22-'Upside'!F22)*(71-60)/12 | F74: ='Upside'!G20/12 | G74: ='Downside'!F22+('Downside'!G22-'Downside'!F22)*(71-60)/12 | H74: ='Downside'!G20/12
A75: 72 | B75: 6 | C75: ='Base'!F22+('Base'!G22-'Base'!F22)*(72-60)/12 | D75: ='Base'!G20/12 | E75: ='Upside'!F22+('Upside'!G22-'Upside'!F22)*(72-60)/12 | F75: ='Upside'!G20/12 | G75: ='Downside'!F22+('Downside'!G22-'Downside'!F22)*(72-60)/12 | H75: ='Downside'!G20/12
A76: 73 | B76: 7 | C76: ='Base'!G22+('Base'!H22-'Base'!G22)*(73-72)/12 | D76: ='Base'!H20/12 | E76: ='Upside'!G22+('Upside'!H22-'Upside'!G22)*(73-72)/12 | F76: ='Upside'!H20/12 | G76: ='Downside'!G22+('Downside'!H22-'Downside'!G22)*(73-72)/12 | H76: ='Downside'!H20/12
A77: 74 | B77: 7 | C77: ='Base'!G22+('Base'!H22-'Base'!G22)*(74-72)/12 | D77: ='Base'!H20/12 | E77: ='Upside'!G22+('Upside'!H22-'Upside'!G22)*(74-72)/12 | F77: ='Upside'!H20/12 | G77: ='Downside'!G22+('Downside'!H22-'Downside'!G22)*(74-72)/12 | H77: ='Downside'!H20/12
A78: 75 | B78: 7 | C78: ='Base'!G22+('Base'!H22-'Base'!G22)*(75-72)/12 | D78: ='Base'!H20/12 | E78: ='Upside'!G22+('Upside'!H22-'Upside'!G22)*(75-72)/12 | F78: ='Upside'!H20/12 | G78: ='Downside'!G22+('Downside'!H22-'Downside'!G22)*(75-72)/12 | H78: ='Downside'!H20/12
A79: 76 | B79: 7 | C79: ='Base'!G22+('Base'!H22-'Base'!G22)*(76-72)/12 | D79: ='Base'!H20/12 | E79: ='Upside'!G22+('Upside'!H22-'Upside'!G22)*(76-72)/12 | F79: ='Upside'!H20/12 | G79: ='Downside'!G22+('Downside'!H22-'Downside'!G22)*(76-72)/12 | H79: ='Downside'!H20/12
A80: 77 | B80: 7 | C80: ='Base'!G22+('Base'!H22-'Base'!G22)*(77-72)/12 | D80: ='Base'!H20/12 | E80: ='Upside'!G22+('Upside'!H22-'Upside'!G22)*(77-72)/12 | F80: ='Upside'!H20/12 | G80: ='Downside'!G22+('Downside'!H22-'Downside'!G22)*(77-72)/12 | H80: ='Downside'!H20/12
A81: 78 | B81: 7 | C81: ='Base'!G22+('Base'!H22-'Base'!G22)*(78-72)/12 | D81: ='Base'!H20/12 | E81: ='Upside'!G22+('Upside'!H22-'Upside'!G22)*(78-72)/12 | F81: ='Upside'!H20/12 | G81: ='Downside'!G22+('Downside'!H22-'Downside'!G22)*(78-72)/12 | H81: ='Downside'!H20/12
A82: 79 | B82: 7 | C82: ='Base'!G22+('Base'!H22-'Base'!G22)*(79-72)/12 | D82: ='Base'!H20/12 | E82: ='Upside'!G22+('Upside'!H22-'Upside'!G22)*(79-72)/12 | F82: ='Upside'!H20/12 | G82: ='Downside'!G22+('Downside'!H22-'Downside'!G22)*(79-72)/12 | H82: ='Downside'!H20/12
A83: 80 | B83: 7 | C83: ='Base'!G22+('Base'!H22-'Base'!G22)*(80-72)/12 | D83: ='Base'!H20/12 | E83: ='Upside'!G22+('Upside'!H22-'Upside'!G22)*(80-72)/12 | F83: ='Upside'!H20/12 | G83: ='Downside'!G22+('Downside'!H22-'Downside'!G22)*(80-72)/12 | H83: ='Downside'!H20/12
A84: 81 | B84: 7 | C84: ='Base'!G22+('Base'!H22-'Base'!G22)*(81-72)/12 | D84: ='Base'!H20/12 | E84: ='Upside'!G22+('Upside'!H22-'Upside'!G22)*(81-72)/12 | F84: ='Upside'!H20/12 | G84: ='Downside'!G22+('Downside'!H22-'Downside'!G22)*(81-72)/12 | H84: ='Downside'!H20/12
A85: 82 | B85: 7 | C85: ='Base'!G22+('Base'!H22-'Base'!G22)*(82-72)/12 | D85: ='Base'!H20/12 | E85: ='Upside'!G22+('Upside'!H22-'Upside'!G22)*(82-72)/12 | F85: ='Upside'!H20/12 | G85: ='Downside'!G22+('Downside'!H22-'Downside'!G22)*(82-72)/12 | H85: ='Downside'!H20/12
A86: 83 | B86: 7 | C86: ='Base'!G22+('Base'!H22-'Base'!G22)*(83-72)/12 | D86: ='Base'!H20/12 | E86: ='Upside'!G22+('Upside'!H22-'Upside'!G22)*(83-72)/12 | F86: ='Upside'!H20/12 | G86: ='Downside'!G22+('Downside'!H22-'Downside'!G22)*(83-72)/12 | H86: ='Downside'!H20/12
A87: 84 | B87: 7 | C87: ='Base'!G22+('Base'!H22-'Base'!G22)*(84-72)/12 | D87: ='Base'!H20/12 | E87: ='Upside'!G22+('Upside'!H22-'Upside'!G22)*(84-72)/12 | F87: ='Upside'!H20/12 | G87: ='Downside'!G22+('Downside'!H22-'Downside'!G22)*(84-72)/12 | H87: ='Downside'!H20/12

Sheet Financing
A1: Financing requirement
A3: Item | B3: Base | C3: Upside | D3: Downside | E3: How it is calculated
A4: Month ARR reaches the Series A milestone | B4: =IFERROR(MATCH(TRUE,INDEX(Monthly!C4:C87>=Assumptions!$B$5,0),0),"not reached") | C4: =IFERROR(MATCH(TRUE,INDEX(Monthly!E4:E87>=Assumptions!$B$5,0),0),"not reached") | D4: =IFERROR(MATCH(TRUE,INDEX(Monthly!G4:G87>=Assumptions!$B$5,0),0),"not reached") | E4: First month interpolated ARR >= milestone
A5: Seed: net burn to milestone + months to close | B5: =IFERROR(-SUMIFS(Monthly!D4:D87,Monthly!A4:A87,"<="&(B4+Assumptions!$B$7)),"n/a") | C5: =IFERROR(-SUMIFS(Monthly!F4:F87,Monthly!A4:A87,"<="&(C4+Assumptions!$B$7)),"n/a") | D5: =IFERROR(-SUMIFS(Monthly!H4:H87,Monthly!A4:A87,"<="&(D4+Assumptions!$B$7)),"n/a") | E5: Sum of negative monthly EBITDA; profit offsets burn
A6: Seed incl. buffer | B6: =IFERROR(B5*(1+Assumptions!$B$6),"n/a") | C6: =IFERROR(C5*(1+Assumptions!$B$6),"n/a") | D6: =IFERROR(D5*(1+Assumptions!$B$6),"n/a") | E6: Adds the buffer
A7: Series A: net burn over runway after milestone (capped at model end) | B7: =IFERROR(-SUMIFS(Monthly!D4:D87,Monthly!A4:A87,">"&B4,Monthly!A4:A87,"<="&MIN(84,B4+Assumptions!$B$8)),"n/a") | C7: =IFERROR(-SUMIFS(Monthly!F4:F87,Monthly!A4:A87,">"&C4,Monthly!A4:A87,"<="&MIN(84,C4+Assumptions!$B$8)),"n/a") | D7: =IFERROR(-SUMIFS(Monthly!H4:H87,Monthly!A4:A87,">"&D4,Monthly!A4:A87,"<="&MIN(84,D4+Assumptions!$B$8)),"n/a") | E7: Burn in the runway window after the milestone
A8: Series A incl. buffer | B8: =IFERROR(MAX(0,B7)*(1+Assumptions!$B$6),"n/a") | C8: =IFERROR(MAX(0,C7)*(1+Assumptions!$B$6),"n/a") | D8: =IFERROR(MAX(0,D7)*(1+Assumptions!$B$6),"n/a") | E8: Adds the buffer
A11: Proposed rounds
A12: Round | B12: Amount $M | C12: Timing | D12: Basis
A13: Seed (tranche 1 $4.0M at close; tranche 2 $3.5M at milestone) | B13: 7.5 | C13: Now | D13: Recalculated 2026-10-22: base need incl. 20% buffer $7.59M (milestone month 38); the old note said $7.36M. Downside with hiring freeze $7.6M (not recalculated)
A14: Series A | B14: 8.5 | C14: At $2.5M ARR (base case month 38, recalculated 2026-10-22) | D14: Recalculated base need incl. buffer $5.58M; 20% fewer accounts $8.5M (not recalculated)
A16: Downside cost response: if the tranche-2 milestone is missed, hiring and spending are held at year-2 levels. Then the downside case reaches the milestone in month 55, breaks even in year 6 and needs $7.6M including buffer. Without that response, the downside case would run out of seed money around month 45.

Sheet Use of funds
A1: Use of funds
A3: Seed round: $7.50M, months 0-43 of the base case
A4: Function | B4: $M | C4: Share
A5: General and administrative | B5: 1.153 | C5: =B5/SUM($B$5:$B$11)
A6: Product and engineering | B6: 1.697 | C6: =B6/SUM($B$5:$B$11)
A7: Security | B7: 0.707 | C7: =B7/SUM($B$5:$B$11)
A8: Sales and marketing | B8: 1.947 | C8: =B8/SUM($B$5:$B$11)
A9: Claims operations and customer success | B9: 0.63 | C9: =B9/SUM($B$5:$B$11)
A10: Reserve (20% buffer) | B10: 1.227 | C10: =B10/SUM($B$5:$B$11)
A11: Unallocated: faster hiring or downside cover | B11: 0.141 | C11: =B11/SUM($B$5:$B$11)
A12: Total | B12: =SUM(B5:B11)
A13: Gross spend $8.83M less gross profit $2.70M = net burn $6.13M; functions in proportion to gross spend; plus 20% buffer; remainder unallocated.
A25: Series A: $8.50M, months 37-67 of the base case
A26: Function | B26: $M | C26: Share
A27: General and administrative | B27: 0.543 | C27: =B27/SUM($B$27:$B$33)
A28: Product and engineering | B28: 1.298 | C28: =B28/SUM($B$27:$B$33)
A29: Security | B29: 0.341 | C29: =B29/SUM($B$27:$B$33)
A30: Sales and marketing | B30: 1.942 | C30: =B30/SUM($B$27:$B$33)
A31: Claims operations and customer success | B31: 0.662 | C31: =B31/SUM($B$27:$B$33)
A32: Reserve (20% buffer) | B32: 0.957 | C32: =B32/SUM($B$27:$B$33)
A33: Unallocated: faster hiring or downside cover | B33: 2.756 | C33: =B33/SUM($B$27:$B$33)
A34: Total | B34: =SUM(B27:B33)
A35: Gross spend $17.24M less gross profit $12.46M = net burn $4.79M; functions in proportion to gross spend; plus 20% buffer; remainder unallocated.

Sheet Unit economics
A1: Unit economics (base case, year 3)
A3: Metric | B3: Value | C3: Basis
A4: Revenue per account ($K) | B4: =Base!D11 | C4: Base case Y3
A5: Gross margin | B5: =Base!D12 | C5: Base case Y3
A6: Annual account churn | B6: =Base!B6 | C6: Base case
A7: Expected account lifetime (years) | B7: =1/B6 | C7: 1 / churn
A8: Lifetime gross profit per account ($K) | B8: =B4*B5*B7 | C8: Revenue x margin x lifetime
A9: Plan: sales and marketing cost per $1 of new ARR | B9: =Base!D25 | C9: From the base case
A10: Acquisition cost per account ($K) | B10: =B9*B4 | C10: Ratio x revenue per account
A11: Lifetime gross profit / acquisition cost | B11: =B8/B10 | C11: Target above 3x
A12: Months of gross profit to repay acquisition cost | B12: =B10/(B4*B5)*12
A13: Benchmark: sales and marketing per $1 of new ARR | B13: 2 | C13: 2024 median (Benchmarkit 2025 report, B)
A14: Lifetime gross profit / acquisition cost at benchmark | B14: =B8/(B13*B4) | C14: Stress case

Sheet Customer value
A1: What a customer recovers (illustrative, sourced)
A3: Item | B3: Value | C3: Source / grade
A4: Truck detention owed per 1,000 loads ($) | B4: 56400 | C4: Our Monte Carlo calibrated on ATRI 2024 (2023 data); amounts computed with the scoup rules engine
A5: Collected today per 1,000 loads ($) | B5: 22600 | C5: 40% collected; ATRI implies 36-46% (A/B)
A6: Additional collected with scoup, pay rate unchanged ($) | B6: 7540 | C6: Every event with gate times billed; 5-95% range $4.4K-$11.0K
A7: Additional if evidence lifts pay rate to 65% ($, scenario) | B7: 12670 | C7: Pay-rate lift not yet measured
A8: Fuel surcharge overbilling per affected 500-mile load ($) | B8: 9 | C8: $6.86-$11.88 on EIA weekly diesel 2021-2026 (A, our analysis). Latest EIA week 2026-10-19: $6.276/gal (released 2026-10-20)
A9: Fuel surcharge recoverable, 10,000 loads, 20% affected ($) | B9: 16000 | C9: Incidence is an assumption to be measured
A10: Container fee exposure, 2,000 TEU importer ($) | B10: =ROUND(3080000000/28079201*2000,-3) | C10: FMC about $15.4B over Apr 2020-Mar 2025 = $3.08B/yr (A) / US container imports 2025 28,079,201 TEU (Descartes, B) = about $110/TEU (C; rough: FMC covers 9 carriers, imports and exports)
A11: Container fees recoverable at 15% ($) | B11: =ROUND(B10*0.15,-2) | C11: Share is an assumption; 46 CFR 541.5 and 541.7 make non-compliant invoices non-payable (A)
A12: Accessorial names recognised at confidence threshold | B12: 0.91194969 | C12: 145 of 159 in one internal run (158/159 in another record): INTERNAL test on public tariff names, not customer invoices; not independently reproduced. Do not quote externally
A13: Accessorial names recognised by our earlier keyword rules | B13: 0.11949686 | C13: Same test (our analysis)

Sheet Competitors
A1: Comparable companies
A3: Company | B3: What they do | C3: Funding / financials | D3: Grade
A4: Loop | B4: AI freight audit and payment | C4: Series B $35M (Oct 2023); Series C $95M (17 Apr 2026, led by Valor Equity Partners); about $160M total (Sacra estimate) | D4: A (Series C) / C (total)
A5: Intelligent Audit | B5: Freight and parcel audit and recovery | C5: Self-funded; mid-market offer since Jun 2025 | D5: C
A6: Trax Technologies | B6: Global freight audit and payment | C6: Accel-KKR credit facility (Sep 2021) | D6: A
A7: Cass Information Systems | B7: Freight audit and payment (bank-owned) | C7: FY2025 revenue $190.8M; net income $35.1M; transportation dollar volume $36.4B (8-K, 22 Jan 2026) | D7: A
A8: DockClock (Platform Science marketplace) | B8: ELD-based detention billing | C8: Not disclosed | D8: A (product)
A9: Freehand (founded by former Pando executives) | B9: Supply-chain invoice verification and recovery | C9: Series A $25M (Mar 2024); Series B $75M (29 Jul 2026, Battery Ventures and NewRoad); about $100M total | D9: B
A10: Terminal49 | B10: Container tracking | C10: Series A $6.5M (Jan 2023); $8.7M total | D10: B
A11: Vizion | B11: Container event data | C11: Series A $14M (2022); total ~$17M (estimate) | D11: A/C
A12: HappyRobot | B12: AI agents for freight operators | C12: Series B $44M (Sep 2025, led by Base10) at about $500M valuation | D12: B
A13: Freightos (NASDAQ: CRGO) | B13: Booking and rate data | C13: FY2025 revenue $29.5M; IFRS net loss $17.5M | D13: A
A14: Transporeon (Trimble) | B14: Logistics network incl. freight audit | C14: Acquired for ~EUR 1.9B (~$2.0B), 2023 | D14: A

Sheet Sources
A1: Sources
A3: Source | B3: URL | C3: Grade
A4: ATRI, Costs and Consequences of Truck Driver Detention (Sep 2024, 2023 data) | B4: https://truckingresearch.org/wp-content/uploads/2024/09/ATRI-Costs-and-Consequences-of-Truck-Driver-Detention-09-2024.pdf | C4: A/B
A5: FMC detention and demurrage data | B5: https://www.fmc.gov/detention-and-demurrage/ | C5: A
A6: 46 CFR 541.5 / 541.6 / 541.7 | B6: https://www.ecfr.gov/current/title-46/chapter-IV/subchapter-B/part-541 | C6: A
A7: EIA weekly diesel (FRED GASDESW) | B7: https://fred.stlouisfed.org/series/GASDESW | C7: A
A8: BLS PPI long-distance truckload (FRED PCU4841214841212) | B8: https://fred.stlouisfed.org/series/PCU4841214841212 | C8: A
A9: Carta, ARR at Series A | B9: https://carta.com/data/newsletter-arr-at-series-a/ | C9: B
A10: BLS Occupational Outlook; BLS ECEC | B10: https://www.bls.gov/ooh/computer-and-information-technology/software-developers.htm | C10: A
A11: SSB wages; Skatteetaten employer tax | B11: https://www.ssb.no/arbeid-og-lonn/lonn-og-arbeidskraftkostnader/statistikk/lonn | C11: A
A12: Benchmarkit 2025 report (2024 data) | B12: https://www.benchmarkit.ai/2025benchmarks | C12: B
A13: Refund Retriever published pricing | B13: https://www.refundretriever.com/pricing | C13: A
A14: Cass FY2025 10-K | B14: https://www.sec.gov/Archives/edgar/data/708781/000070878126000010/cass-20251231.htm | C14: A
... A18: Federal Register 2025-23920; §541.4 removed/reserved | B18: https://www.federalregister.gov/documents/2025/12/29/2025-23920/demurrage-and-detention-billing-requirements-properly-issued-invoices-provision-set-aside-by-court | C18: Primary; effective 2025-12-29

Sheet Sources (verified)
A1: Cell(s) | B1: Figure | C1: Source | D1: URL | E1: Published | F1: Accessed | G1: Status
A2: Assumptions!B5 | B2: Median ARR at Series A, 2025: $2.8M (2024: $2.3M) | C2: Carta | D2: https://carta.com/data/newsletter-arr-at-series-a/ | E2: 2026 | F2: 2026-10-22 | G2: Secondary: search-indexed Carta page; direct fetch returned 403
A3: Assumptions!I15 | B3: Parcel refund audit fee 50/45/40% by volume band | C3: Refund Retriever pricing | D3: https://www.refundretriever.com/pricing | E3: live page | F3: 2026-10-22 | G3: VERIFIED primary (vendor price)
A4: Base/Upside/Downside!I6 | B4: GRR fell from 90% to 88% over three years; NRR 101% | C4: Benchmarkit 2025 SaaS Performance Metrics | D4: https://www.benchmarkit.ai/2025benchmarks | E4: 2025 | F4: 2026-10-22 | G4: VERIFIED primary
A5: Base!I25; Unit economics!B13 | B5: Median New CAC ratio $2.00 per $1 of new ARR (2024) | C5: Benchmarkit 2025 SaaS Performance Metrics | D5: https://www.benchmarkit.ai/2025benchmarks | E5: 2025 | F5: 2026-10-22 | G5: VERIFIED primary
A6: Customer value!B10:C10 | B6: D&D about $15.4B, 9 carriers, Apr 2020-Mar 2025 | C6: Federal Maritime Commission | D6: https://www.fmc.gov/detention-and-demurrage/ | E6: 2025 | F6: 2026-10-22 | G6: VERIFIED primary
A7: Customer value!B10:C10 | B7: US container imports 2025: 28,079,201 TEU (2024: 28,196,462) | C7: Descartes Global Shipping Report (Jan 2026) | D7: https://www.descartes.com/resources/knowledge-center/descartes-releases-january-global-shipping-report-december-us-0 | E7: 2026-01 | F7: 2026-10-22 | G7: VERIFIED secondary (Descartes release via trade press)
A8: Customer value!B8:C8 | B8: Diesel $6.276/gal, week of 2026-10-19 | C8: U.S. EIA weekly retail diesel | D8: https://www.eia.gov/dnav/pet/pet_pri_gnd_a_epd2d_pte_dpgal_w.htm | E8: 2026-10-20 | F8: 2026-10-22 | G8: VERIFIED primary
A9: Customer value!B4:B7 | B9: Detention in 39.3% of stops; 94.5% of fleets bill; fewer than half of invoices paid; $15.1B | C9: ATRI, Costs and Consequences of Truck Driver Detention | D9: https://truckingresearch.org/2024/09/new-research-documents-substantial-financial-and-safety-impacts-from-truck-driver-detention/ | E9: 2024-09-10 | F9: 2026-10-19 | G9: VERIFIED primary; B4:B7 dollar amounts are our own simulation (C)
A10: Customer value!C11 | B10: 46 CFR 541.5 and 541.7; 541.4 reserved | C10: eCFR; Federal Register 2025-23920 | D10: https://www.ecfr.gov/current/title-46/chapter-IV/subchapter-B/part-541 | E10: current through 2026-10-15 | F10: 2026-10-19 | G10: VERIFIED primary in the 2026-10-19 ledger; eCFR blocked our 2026-10-22 fetch
A11: Competitors!C4 | B11: Loop Series C $95M, 17 Apr 2026 | C11: Loop | D11: https://www.loop.com/article/loop-raises-95m-series-c-to-scale-its-ai-platform-across-the-supply-chain | E11: 2026-04-17 | F11: 2026-10-22 | G11: VERIFIED primary
A12: Competitors!C7 | B12: Cass FY2025 revenue $190.8M, net income $35.1M, $36.4B volume | C12: Cass 8-K exhibit 99.1 | D12: https://www.sec.gov/Archives/edgar/data/708781/000070878126000002/cass-20251231xexx991.htm | E12: 2026-01-22 | F12: 2026-10-22 | G12: VERIFIED primary
... A21: Competitors!C6, C10, C11, C13, C14 | B21: Trax, Terminal49, Vizion, Freightos, Transporeon | C21: various | D21: - | E21: - | F21: 2026-10-22 | G21: NOT re-verified this pass; existing grades kept
